Workbook
Name actual_month: [4]Summary!$I$1
Name cash: #REF!
Name curs: #REF!
Name DANE: '[9]Breakdown CAPEX (PBC)'!$A$6:$J$365
Name eur_rate: [11]Summary!$D$109
Name k: #REF!
Name POW: [13]POW!$A$2:$D$6
Name rate: #REF!
Name tolerance: [14]Inputs!#REF!
Name usd_rur: '[15]Narratives-Subsidiarie'!$F$2
Name Город: #REF!
Name допкоды: #REF!
Name ДоходВсегоПлан: #REF!
Name ДоходВсегоФакт: #REF!
Name доходы1: #REF!
Name доходы2: #REF!
Name Индекс: #REF!
Name Инпутс: #REF!
Name коды: #REF!
Name курс: #REF!
Name МЛН: 1000000
Name Налог_на_прибыль: '[17]input data'!$E$73
Name Отчисления_от_зпл: 0.385
Name па: #REF!
Name ПланФакт: #REF!
Name Площадь: '[18]input data'!$F$19
Name Площадь_гараж: #REF!
Name Площадь_жилая: '[17]input data'!$F$19
Name Площадь_общая: #REF!
Name поступления1: #REF!
Name Поступления2: #REF!
Name ПрРасходыВсегоПлан: #REF!
Name ПрРасходыВсегоФакт: #REF!
Name РасходыВсегоПлан: #REF!
Name РасходыВсегоФакт: #REF!
Name расходыпр1: #REF!
Name расходыпр2: #REF!
Name расходытек1: #REF!
Name расходытек2: #REF!
Name руб.: "остаток вход"
Name ТекРасходыВсегоПлан: #REF!
Name ТекРасходыВсегоФакт: #REF!

Sheet Сводные
G1: Отчет о выполненных работах к приложению №13 к Договору от 17.06.2025 № ДОМУ/2025-06/17 от ИП СИЗОВА ВП
A2: 1 очередь | B2: С1 | C2: С2 | D2: С3-1 | E2: С3-2 | H2: Индексация цен
A3: корпуса С1 С3 | H3: до ввода 1 оч | I3: после ввода 1 оч
A4: Кол-во спален | B4: Сред. площадь, кв. м | C4: Кол-во, шт. | D4: % | E4: Средневзв стартовая цена, руб. | H4: 0.01 | I4: 0.01
A5: Ст | B5: {=AVERAGE( IF((PriceList[Количество комнат]=A5)* ((PriceList[Корпус]=$B$2)+(PriceList[Корпус]=$D$2)+(PriceList[Корпус]=$E$2)), PriceList[Площадь, кв.м] ) )} -> 32.306155 | C5: {=SUM( IF((PriceList[Количество комнат]=A5)* ((PriceList[Корпус]=$B$2)+(PriceList[Корпус]=$D$2)+(PriceList[Корпус]=$E$2)), 1) )} -> 593 | D5: =C5/$C$8 -> 0.88375559 | E5: {=SUMPRODUCT((PriceList[Комнат в шахматку]=A5)*((PriceList[Корпус]=$B$2)+(PriceList[Корпус]=$D$2)+(PriceList[Корпус]=$E$2))*PriceList[ИТОГ Бюджет, руб]) / SUMPRODUCT((PriceList[Комнат в шахматку]=A5)*((PriceList[Корпус]=$B$2)+(PriceList[Корпус]=$D$2)+(PriceList[Корпус]=$E$2))*PriceList[Площадь, кв.м])} -> 365482.87 | K5: Доля
A6: 1К | B6: {=AVERAGE( IF((PriceList[Количество комнат]=A6)* ((PriceList[Корпус]=$B$2)+(PriceList[Корпус]=$D$2)+(PriceList[Корпус]=$E$2)), PriceList[Площадь, кв.м] ) )} -> 57.891818 | C6: {=SUM( IF((PriceList[Количество комнат]=A6)* ((PriceList[Корпус]=$B$2)+(PriceList[Корпус]=$D$2)+(PriceList[Корпус]=$E$2)), 1) )} -> 77 | D6: =C6/$C$8 -> 0.1147541 | E6: {=SUMPRODUCT((PriceList[Комнат в шахматку]=A6)*((PriceList[Корпус]=$B$2)+(PriceList[Корпус]=$D$2)+(PriceList[Корпус]=$E$2))*PriceList[ИТОГ Бюджет, руб]) / SUMPRODUCT((PriceList[Комнат в шахматку]=A6)*((PriceList[Корпус]=$B$2)+(PriceList[Корпус]=$D$2)+(PriceList[Корпус]=$E$2))*PriceList[Площадь, кв.м])} -> 358555.66 | H6: Кладовые | I6: =1050-76 -> 974 | J6: =#REF! -> #REF! | K6: =I6/J6 -> #REF!
A7: 2К | B7: {=AVERAGE( IF((PriceList[Количество комнат]=A7)* ((PriceList[Корпус]=$B$2)+(PriceList[Корпус]=$D$2)+(PriceList[Корпус]=$E$2)), PriceList[Площадь, кв.м] ) )} -> 82.76 | C7: {=SUM( IF((PriceList[Количество комнат]=A7)* ((PriceList[Корпус]=$B$2)+(PriceList[Корпус]=$D$2)+(PriceList[Корпус]=$E$2)), 1) )} -> 1 | D7: =C7/$C$8 -> 0.001490313 | E7: {=SUMPRODUCT((PriceList[Комнат в шахматку]=A7)*((PriceList[Корпус]=$B$2)+(PriceList[Корпус]=$D$2)+(PriceList[Корпус]=$E$2))*PriceList[ИТОГ Бюджет, руб]) / SUMPRODUCT((PriceList[Комнат в шахматку]=A7)*((PriceList[Корпус]=$B$2)+(PriceList[Корпус]=$D$2)+(PriceList[Корпус]=$E$2))*PriceList[Площадь, кв.м])} -> 413118.72 | H7: Машиноместа | I7: 477 | K7: =I7/J6 -> #REF!
C8: =SUM(C5:C7) -> 671 | D8: =SUM(D5:D7) -> 1 | E8: =(SUMIF(PriceList[Корпус],Сводные!B2,PriceList[ИТОГ Бюджет, руб]) +SUMIF(PriceList[Корпус],Сводные!D2,PriceList[ИТОГ Бюджет, руб]) +SUMIF(PriceList[Корпус],Сводные!E2,PriceList[ИТОГ Бюджет, руб])) / (SUMIF(PriceList[Корпус],Сводные!B2,PriceList[Площадь, кв.м]) +SUMIF(PriceList[Корпус],Сводные!D2,PriceList[Площадь, кв.м]) +SUMIF(PriceList[Корпус],Сводные!E2,PriceList[Площадь, кв.м])) -> 364346.2
A10: корпус C2
A11: Кол-во спален | B11: Сред. площадь, кв. м | C11: Кол-во, шт. | D11: % | E11: Средневзв стартовая цена, руб.
A12: Ст | B12: {=AVERAGE( IF((PriceList[Количество комнат]=A12)* ((PriceList[Корпус]=$C$2)), PriceList[Площадь, кв.м] ) )} -> 31.370669 | C12: {=SUM( IF((PriceList[Количество комнат]=A5)* ((PriceList[Корпус]=$C$2)), 1) )} -> 314 | D12: =C12/$C$15 -> 0.94864048 | E12: {=SUMPRODUCT((PriceList[Комнат в шахматку]=A12)*((PriceList[Корпус]=$C$2))*PriceList[ИТОГ Бюджет, руб]) / SUMPRODUCT((PriceList[Комнат в шахматку]=A12)*((PriceList[Корпус]=$C$2))*PriceList[Площадь, кв.м])} -> 376656.95
A13: 1К | B13: {=AVERAGE( IF((PriceList[Количество комнат]=A13)* ((PriceList[Корпус]=$C$2)), PriceList[Площадь, кв.м] ) )} -> 61.362353 | C13: {=SUM( IF((PriceList[Количество комнат]=A6)* ((PriceList[Корпус]=$C$2)), 1) )} -> 17 | D13: =C13/$C$15 -> 0.051359517 | E13: {=SUMPRODUCT((PriceList[Комнат в шахматку]=A13)*((PriceList[Корпус]=$C$2))*PriceList[ИТОГ Бюджет, руб]) / SUMPRODUCT((PriceList[Комнат в шахматку]=A13)*((PriceList[Корпус]=$C$2))*PriceList[Площадь, кв.м])} -> 389374.54
A14: 2К | C14: {=SUM( IF((PriceList[Количество комнат]=A7)* ((PriceList[Корпус]=$C$2)), 1) )} -> 0 | D14: =C14/$C$15 -> 0
C15: =SUM(C12:C14) -> 331 | D15: =SUM(D12:D14) -> 1 | E15: =(SUMIF(PriceList[Корпус],C2,PriceList[ИТОГ Бюджет, руб]) ) / (SUMIF(PriceList[Корпус],C2,PriceList[Площадь, кв.м]) ) -> 377874.77
A18: Первая очередь строительства корпуса: С1, С2, С3 | C18: С2 и С4 (корпуса, которые отдаются под управление гостиничного оператора COSMOS, соответственно цены будут выше, чем основного объема)
A19: Старт первой очереди 15.10.2025 | C19: С5 (премиальный корпус, с дорогой отделкой, с более премиальными материалами и тд)
A20: Ввод в эксплуатацию: ноябрь 2029
A22: Кол-во месяцев продаж | B22: =COUNT(#REF!) -> 0
A23: % распроданности к вводу | B23: 1
A24: Темп продаж в месяц, шт. | B24: =(C15+C8)/B22 -> #DIV/0!
A28: 2 очередь | B28: 4 | C28: 5
A29: корпус С4 | E29: цены кв. м корпуса С4 приравнены ценам корпуса С2 1 очереди в марте 2026 за вычетом индексации, размер которой можно изменять
A30: Кол-во спален | B30: Сред. площадь, кв. м | C30: Кол-во, шт. | D30: % | E30: Средневзв стартовая цена, руб. | F30: индексация на старт 2 оч
A31: ст | B31: {=AVERAGE( IF( (Таблица1[Кол-во комнат]=A31)* (Таблица1[Корпус]=$B$28), Таблица1[Общая площадь с учетом летних помещений с коэф., кв.м] ) )} -> 31.65949 | C31: {=SUM( IF((Таблица1[Кол-во комнат]=A31)* ((Таблица1[Корпус]=$B$28)), 1) )} -> 314 | D31: =C31/$C$33 -> 0.94864048 | E31: =#REF!*(100%+F31) -> #REF! | F31: -0.01
A32: 1АЕ | B32: {=AVERAGE( IF( (Таблица1[Кол-во комнат]=A32)* (Таблица1[Корпус]=$B$28), Таблица1[Общая площадь с учетом летних помещений с коэф., кв.м] ) )} -> 61.72 | C32: {=SUM( IF((Таблица1[Кол-во комнат]=A32)* ((Таблица1[Корпус]=$B$28)), 1) )} -> 17 | D32: =C32/$C$33 -> 0.051359517 | E32: =#REF!*(100%+F32) -> #REF! | F32: -0.01
C33: =SUM(C31:C32) -> 331 | D33: =SUM(D31:D32) -> 1 | E33: =(#REF!+#REF!)/(#REF!+#REF!) -> #REF!
A35: корпус C5 | E35: цены кв. м корпуса С4 приравнены ценам корпуса С1,С3 1 очереди в марте 2026 за вычетом индексации, размер которой можно изменять
A36: Кол-во спален | B36: Сред. площадь, кв. м | C36: Кол-во, шт. | D36: % | E36: Средневзв стартовая цена, руб. | F36: индексация на старт 2 оч
A37: ст | B37: {=AVERAGE( IF( (Таблица1[Кол-во комнат]=A37)* (Таблица1[Корпус]=$C$28), Таблица1[Общая площадь с учетом летних помещений с коэф., кв.м] ) )} -> 39.767406 | C37: {=SUM( IF((Таблица1[Кол-во комнат]=A37)* ((Таблица1[Корпус]=$C$28)), 1) )} -> 239 | D37: =C37/$C$40 -> 0.76357827 | E37: =#REF!*(100%+F37) -> #REF! | F37: 0.03
A38: 1АЕ | B38: {=AVERAGE( IF( (Таблица1[Кол-во комнат]=A38)* (Таблица1[Корпус]=$C$28), Таблица1[Общая площадь с учетом летних помещений с коэф., кв.м] ) )} -> 64.328871 | C38: {=SUM( IF((Таблица1[Кол-во комнат]=A38)* ((Таблица1[Корпус]=$C$28)), 1) )} -> 62 | D38: =C38/$C$40 -> 0.19808307 | E38: =#REF!*(100%+F38) -> #REF! | F38: 0.03
A39: 2АЕ | B39: {=AVERAGE( IF( (Таблица1[Кол-во комнат]=A39)* (Таблица1[Корпус]=$C$28), Таблица1[Общая площадь с учетом летних помещений с коэф., кв.м] ) )} -> 100.18333 | C39: {=SUM( IF((Таблица1[Кол-во комнат]=A39)* ((Таблица1[Корпус]=$C$28)), 1) )} -> 12 | D39: =C39/$C$40 -> 0.038338658 | E39: =#REF!*(100%+F39) -> #REF! | F39: 0.03
C40: =SUM(C37:C39) -> 313 | D40: =SUM(D37:D39) -> 1 | E40: =(#REF!+#REF!+#REF!)/(#REF!+#REF!+#REF!) -> #REF!
A43: Вторая очередь строительства корпуса: С4, С5
A44: Старт продаж второй очереди: 01.03.2026
A45: Ввод в эксплуатацию: сентябрь 2030
A47: Кол-во месяцев продаж | B47: =COUNT(#REF!) -> 0
A48: % распроданности к вводу | B48: 1
A49: Темп продаж в месяц, шт. | B49: =(C40+C33)/B47 -> #DIV/0!

Sheet Доходность
A2: КАЛЬКУЛЯТОР ДОХОДНОСТИ
A3: Номер | B3: 120 | C3: необходимо выбрать из списка | D3: Рост цены
A4: В рассрочку | B4: нет | C4: необходимо выбрать из списка
A5: Этаж | B5: =VLOOKUP($B$3,'Реестр 1 оч '!$C$329:$BI$659,3,0) -> 4 | D5: Рост цены | F5: 0.15 | G5: 0.15 | H5: 0.15 | I5: 0.15 | J5: 0.02 | K5: =J5 -> 0.02 | L5: =K5 -> 0.02 | M5: =L5 -> 0.02 | N5: =M5 -> 0.02 | O5: =N5 -> 0.02 | P5: =O5 -> 0.02 | Q5: =P5 -> 0.02 | R5: =Q5 -> 0.02 | S5: =R5 -> 0.02
A6: площадь лота | B6: =VLOOKUP($B$3,'Реестр 1 оч '!$C$329:$BI$659,5,0) -> 28.53 | D6: год | E6: 2025 | F6: 2026 | G6: 2027 | H6: 2028 | I6: 2029 | J6: 2030 | K6: 2031 | L6: 2032 | M6: 2033 | N6: 2034 | O6: 2035 | P6: 2036 | Q6: 2037 | R6: 2038 | S6: 2039
A7: Тип апартамента | B7: =VLOOKUP($B$3,'Реестр 1 оч '!$C$329:$BI$659,12,0) -> S | D7: цена лота, руб | E7: =IF(B4="да",B11,B10) -> 11105302 | F7: =E7*F5+E7 -> 12771098 | G7: =F7*G5+F7 -> 14686763 | H7: =G7*H5+G7 -> 16889777 | I7: =H7*I5+H7 -> 19423243 | J7: =I7*J5+I7 -> 19811708 | K7: =J7*K5+J7 -> 20207943 | L7: =K7*L5+K7 -> 20612101 | M7: =L7*M5+L7 -> 21024343 | ... S7: =R7*S5+R7 -> 23676825
A8: Вид из окна | B8: =VLOOKUP($B$3,'Реестр 1 оч '!$C$329:$BI$659,17,0) -> Двор | D8: цена лота - цена покупки, руб | E8: =IF(B4="да",E7-B11,E7-B10) -> 0 | F8: =IF(C4="да",F7-$B$11,F7-$B$10) -> 1665795.4 | G8: =IF(D4="да",G7-$B$11,G7-$B$10) -> 3581460.1 | H8: =IF(E4="да",H7-$B$11,H7-$B$10) -> 5784474.4 | I8: =IF(F4="да",I7-$B$11,I7-$B$10) -> 8317941 | J8: =IF(G4="да",J7-$B$11,J7-$B$10) -> 8706405.9 | K8: =IF(H4="да",K7-$B$11,K7-$B$10) -> 9102640 | L8: =IF(I4="да",L7-$B$11,L7-$B$10) -> 9506798.9 | M8: =IF(J4="да",M7-$B$11,M7-$B$10) -> 9919040.9 | ... S8: =IF(P4="да",S7-$B$11,S7-$B$10) -> 12571523
A9: Цена кв. м на сайте | B9: =VLOOKUP($B$3,'Реестр 1 оч '!$C$329:$BI$659,59,0) -> 432500
A10: Цена лота при 100% оплате | B10: =VLOOKUP($B$3,'Реестр 1 оч '!$C$329:$BM$659,63,0) -> 11105302
A11: Цена лота при рассрочке | B11: =VLOOKUP($B$3,'Реестр 1 оч '!$C$329:$BM$659,57,0) -> 12339225
A12: Дата передачи ключей | B12: 47423
A13: Рост цены к передаче ключей | B13: =IF(B4="да",(I7-B11)/B11,(I7-B10)/B10) -> 0.74900625
A14: Цена лота к передаче ключей | B14: =B10+B10*B13 -> 19423243
A15: Цена кв.м. к передаче ключей | B15: =B14/B6 -> 680800.68
A16: Доход от роста цены к передаче ключей | B16: =IF(B4="да",B14-B11,B14-B10) -> 8317941
A18: Цена к 2039 году | B18: =S7 -> 23676825
A19: Доход от роста цены к 2039 году | B19: =IF(B4="да",S7-B11,S7-B10) -> 12571523
A21: Доход от отеля за 10 лет | B21: =SUM(E38:N38) -> 23177598
A22: Средняя годовая прибыль от отеля | B22: =B19/10 -> 1257152.3
A23: Среднегодовой доход от отеля в % | B23: =IF(B4="да", B21/B11/10,B21/B11/10) -> 0.18783674
A25: Совокупный доход (аренда + рост цены) | B25: =B21+B19 -> 35749121
A26: Средняя годовой доход общий (аренды + рост цены) | B26: =B25/10 -> 3574912.1
A27: Среднегодовой доход общий за 10 лет в % | B27: =IF(B4="да",B25/B11/10,B25/B10/10) -> 0.32191037 | E27: 2030 | F27: 2031 | G27: 2032 | H27: 2033 | I27: 2034 | J27: 2035 | K27: 2036 | L27: 2037 | M27: 2038 | N27: 2039
D28: Количество дней | E28: 365 | F28: 365 | G28: 365 | H28: 365 | I28: 365 | J28: 365 | K28: 365 | L28: 365 | M28: 365 | N28: 365
A29: Срок окупаемости за счет доходов от отеля и продажи, лет | B29: {=IF(B4="да",(MATCH(TRUE,$E$43:$N$43+$J$8:$S$8>=$B$11,0)),(MATCH(TRUE,$E$43:$N$43+$J$8:$S$8>=$B$10,0)))} -> 2 | D29: Загрузка | E29: 0.35 | F29: 0.44 | G29: 0.59 | H29: 0.65 | I29: 0.65 | J29: 0.65 | K29: 0.65 | L29: 0.65 | M29: 0.65 | N29: 0.65
A30: Срок окупаемости только за счет доходов от отеля, лет | B30: {=IF(B4="да",(MATCH(TRUE,$E$43:$N$43>=$B$11,0)),(MATCH(TRUE,$E$43:$N$43>=$B$10,0)))} -> 7 | D30: Открытая цена на рынке, руб | E30: =E31 -> 18000 | F30: =F31 -> 19440 | G30: =G31 -> 20995.2 | H30: =H31 -> 22674.816 | I30: =I31 -> 24488.801 | J30: =J31 -> 26447.905 | K30: =K31 -> 28563.738 | L30: =L31 -> 30848.837 | M30: =M31 -> 33316.744 | N30: =M31+M31*$B$48 -> 35982.083
D31: ADR (для расчета) | E31: =SUM(E32:E35) -> 18000 | F31: =F32+F33+F34+F35 -> 19440 | G31: =G32+G33+G34+G35 -> 20995.2 | H31: =H32+H33+H34+H35 -> 22674.816 | I31: =I32+I33+I34+I35 -> 24488.801 | J31: =J32+J33+J34+J35 -> 26447.905 | K31: =K32+K33+K34+K35 -> 28563.738 | L31: =L32+L33+L34+L35 -> 30848.837 | M31: =L31+L31*$B$48 -> 33316.744 | N31: =M31+M31*$B$48 -> 35982.083
D32: в т.ч. Размещение | E32: =INDEX(E46:I469, MATCH($B7,$E$47:$E$51,0),MATCH($B8,$F$46:$I$46,0)) -> 14400 | F32: =E32+E32*$B$48 -> 15552 | G32: =F32+F32*$B$48 -> 16796.16 | H32: =G32+G32*$B$48 -> 18139.853 | I32: =H32+H32*$B$48 -> 19591.041 | J32: =I32+I32*$B$48 -> 21158.324 | K32: =J32+J32*$B$48 -> 22850.99 | L32: =K32+K32*$B$48 -> 24679.069 | M32: =L32+L32*$B$48 -> 26653.395 | N32: =M32+M32*$B$48 -> 28785.667
D33: в т.ч. Завтрак | E33: 3500 | F33: =E33+E33*$B$48 -> 3780 | G33: =F33+F33*$B$48 -> 4082.4 | H33: =G33+G33*$B$48 -> 4408.992 | I33: =H33+H33*$B$48 -> 4761.7114 | J33: =I33+I33*$B$48 -> 5142.6483 | K33: =J33+J33*$B$48 -> 5554.0601 | L33: =K33+K33*$B$48 -> 5998.3849 | M33: =L33+L33*$B$48 -> 6478.2557 | N33: =M33+M33*$B$48 -> 6996.5162
D34: в т.ч. Детская комната | E34: 50 | F34: =E34+E34*$B$48 -> 54 | G34: =F34+F34*$B$48 -> 58.32 | H34: =G34+G34*$B$48 -> 62.9856 | I34: =H34+H34*$B$48 -> 68.024448 | J34: =I34+I34*$B$48 -> 73.466404 | K34: =J34+J34*$B$48 -> 79.343716 | L34: =K34+K34*$B$48 -> 85.691213 | M34: =L34+L34*$B$48 -> 92.546511 | N34: =M34+M34*$B$48 -> 99.950231
A35: Проживание собственника | D35: в т.ч.Коворкинг | E35: 50 | F35: =E35+E35*$B$48 -> 54 | G35: =F35+F35*$B$48 -> 58.32 | H35: =G35+G35*$B$48 -> 62.9856 | I35: =H35+H35*$B$48 -> 68.024448 | J35: =I35+I35*$B$48 -> 73.466404 | K35: =J35+J35*$B$48 -> 79.343716 | L35: =K35+K35*$B$48 -> 85.691213 | M35: =L35+L35*$B$48 -> 92.546511 | N35: =M35+M35*$B$48 -> 99.950231
A36: 20% скидка вне зависимости от сезона в любом апартаменте | D36: Валовая выручка | E36: =E31*E28*E29 -> 2299500 | F36: =F31*F28*F29 -> 3122064 | G36: =G31*G28*G29 -> 4521316.3 | H36: =H31*H28*H29 -> 5379600.1 | I36: =I31*I28*I29 -> 5809968.1 | J36: =J31*J28*J29 -> 6274765.6 | K36: =K31*K28*K29 -> 6776746.8 | L36: =L31*L28*L29 -> 7318886.5 | ... N36: =N31*N28*N29 -> 8536749.3
A37: вне зависимости от его категории, но не более 21 дня | D37: Валовая выручка за размещение | E37: =E28*E32*E29 -> 1839600 | F37: =F28*F32*F29 -> 2497651.2 | G37: =G28*G32*G29 -> 3617053.1 | H37: =H28*H32*H29 -> 4303680.1 | I37: =I28*I32*I29 -> 4647974.5 | J37: =J28*J32*J29 -> 5019812.4 | K37: =K28*K32*K29 -> 5421397.4 | L37: =L28*L32*L29 -> 5855109.2 | ... N37: =N28*N32*N29 -> 6829399.4
D38: Расходы на управления 50% | E38: =E37*$B$47 -> 919800 | F38: =F37*$B$47 -> 1248825.6 | G38: =G37*$B$47 -> 1808526.5 | H38: =H37*$B$47 -> 2151840 | I38: =I37*$B$47 -> 2323987.2 | J38: =J37*$B$47 -> 2509906.2 | K38: =K37*$B$47 -> 2710698.7 | L38: =L37*$B$47 -> 2927554.6 | ... N38: =N37*$B$47 -> 3414699.7
D39: Доход собственника от отеля | E39: =E37-E38 -> 919800 | F39: =F37-F38 -> 1248825.6 | G39: =G37-G38 -> 1808526.5 | H39: =H37-H38 -> 2151840 | I39: =I37-I38 -> 2323987.2 | J39: =J37-J38 -> 2509906.2 | K39: =K37-K38 -> 2710698.7 | L39: =L37-L38 -> 2927554.6 | ... N39: =N37-N38 -> 3414699.7
D40: Ежемесячный доход собственника апартамента | E40: =E39/12 -> 76650 | F40: =F39/12 -> 104068.8 | G40: =G39/12 -> 150710.54 | H40: =H39/12 -> 179320 | I40: =I39/12 -> 193665.6 | J40: =J39/12 -> 209158.85 | K40: =K39/12 -> 225891.56 | L40: =L39/12 -> 243962.88 | ... N40: =N39/12 -> 284558.31
D41: Ежемесячный доход собственника детской комнаты и коворкинга с учетом расхода 35% | E41: =(E35+E34)*E28*E29/12*319*0.65 -> 220741.35 | F41: =(F35+F34)*F28*F29/12*319*0.65 -> 299703.69 | G41: =(G35+G34)*G28*G29/12*319*0.65 -> 434025.43 | H41: =(H35+H34)*H28*H29/12*319*0.65 -> 516416.7 | I41: =(I35+I34)*I28*I29/12*319*0.65 -> 557730.04 | J41: =(J35+J34)*J28*J29/12*319*0.65 -> 602348.44 | K41: =(K35+K34)*K28*K29/12*319*0.65 -> 650536.32 | L41: =(L35+L34)*L28*L29/12*319*0.65 -> 702579.22 | ... N41: =(N35+N34)*N28*N29/12*319*0.65 -> 819488.41
D42: Годовая доходность, % | E42: =IF($B$4="да",E39/$B$11,E39/$B$10) -> 0.082825299 | F42: =IF($B$4="да",F39/$B$11,F39/$B$10) -> 0.11245309 | G42: =IF($B$4="да",G39/$B$11,G39/$B$10) -> 0.16285252 | H42: =IF($B$4="да",H39/$B$11,H39/$B$10) -> 0.1937669 | I42: =IF($B$4="да",I39/$B$11,I39/$B$10) -> 0.20926825 | J42: =IF($B$4="да",J39/$B$11,J39/$B$10) -> 0.22600971 | K42: =IF($B$4="да",K39/$B$11,K39/$B$10) -> 0.24409049 | L42: =IF($B$4="да",L39/$B$11,L39/$B$10) -> 0.26361773 | ... N42: =IF($B$4="да",N39/$B$11,N39/$B$10) -> 0.30748372
D43: Накопленный доход собственника | E43: =E39 -> 919800 | F43: =E43+F39 -> 2168625.6 | G43: =F43+G39 -> 3977152.1 | H43: =G43+H39 -> 6128992.2 | I43: =H43+I39 -> 8452979.4 | J43: =I43+J39 -> 10962886 | K43: =J43+K39 -> 13673584 | L43: =K43+L39 -> 16601139 | M43: =L43+M39 -> 19762898 | N43: =M43+N39 -> 23177598
A45: 47423 | B45: ДАТА РВ | E45: ADR | G45: 0.03 | H45: 0.03 | I45: 0.03
A46: 47727 | F46: ул.Морская | G46: Двор | H46: Море | I46: Озеро
A47: Расход на управление | B47: 0.5 | E47: XS | F47: 14400 | G47: =F47+F47*G$45 -> 14832 | H47: =G47+G47*H$45 -> 15276.96 | I47: =H47+H47*I$45 -> 15735.269
A48: Индексация | B48: 0.08 | D48: 0.02 | E48: S | F48: =F47+F47*D48 -> 14688 | G48: =F48+F48*G$45 -> 15128.64 | H48: =G48+G48*H$45 -> 15582.499 | I48: =H48+H48*I$45 -> 16049.974
D49: 0.15 | E49: M | F49: =F48+F48*D49 -> 16891.2 | G49: =F49+F49*G$45 -> 17397.936 | H49: =G49+G49*H$45 -> 17919.874 | I49: =H49+H49*I$45 -> 18457.47
A50: В рассрочку | B50: да | D50: 0.08 | E50: L | F50: =F49+F49*D50 -> 18242.496 | G50: =F50+F50*G$45 -> 18789.771 | H50: =G50+G50*H$45 -> 19353.464 | I50: =H50+H50*I$45 -> 19934.068
B51: нет | D51: 0.1 | E51: XL | F51: =F50+F50*D51 -> 20066.746 | G51: =F51+F51*G$45 -> 20668.748 | H51: =G51+G51*H$45 -> 21288.81 | I51: =H51+H51*I$45 -> 21927.475

Sheet check
F2: проверка с итогами | I2: сверка с итогами по ценам
A3: Корпус2 | B3: КК | C3: Кол-во | D3: Площадь | L3: Корпус2 | M3: КК | N3: Average of Площадь, кв.м | O3: Площадь | P3: Sum of ИТОГ Бюджет, руб
A4: Group1 | B4: Ст | C4: 593 | D4: 19157.55 | F4: =C4=#REF! -> #REF! | L4: Group1 | M4: Ст | N4: 32.306155 | O4: 19157.55 | P4: 6.8674513e+09 | Q4: =P4/O4 -> 358472.31 | R4: =Q4=Сводные!E5 -> FALSE | T4: =N4=Сводные!B5 -> TRUE | U4: =N4=#REF! -> #REF!
B5: 1К | C5: 77 | D5: 4457.67 | F5: =C5=#REF! -> #REF! | M5: 1К | N5: 57.891818 | O5: 4457.67 | P5: 1.5824629e+09 | Q5: =P5/O5 -> 354997.77 | R5: =Q5=Сводные!E6 -> FALSE | T5: =N5=Сводные!B6 -> TRUE | U5: =GETPIVOTDATA("Average of Площадь, кв.м",$L$3,"КК","1К","Корпус2","Group1")=#REF! -> #REF!
B6: 2К | C6: 1 | D6: 82.76 | F6: =C6=#REF! -> #REF! | M6: 2К | N6: 82.76 | O6: 82.76 | P6: 33813750 | Q6: =P6/O6 -> 408576 | R6: =Q6=Сводные!E7 -> FALSE | T6: =N6=Сводные!B7 -> TRUE | U6: =GETPIVOTDATA("Average of Площадь, кв.м",$L$3,"КК","2К","Корпус2","Group1")=#REF! -> #REF!
A7: Group1 Total | C7: 671 | D7: 23697.98 | L7: Group1 Total | N7: 35.317407 | O7: 23697.98 | P7: 8.4837279e+09 | Q7: =P7/O7 -> 357993.72
A8: С2 | B8: Ст | C8: 314 | D8: 9850.39 | F8: =C8=#REF! -> #REF! | L8: С2 | M8: Ст | N8: 31.370669 | O8: 9850.39 | P8: 3.4558134e+09 | Q8: =P8/O8 -> 350830.11 | R8: =Q8=Сводные!E12 -> FALSE | T8: =N8=Сводные!B12 -> TRUE | U8: =N8=#REF! -> #REF!
B9: 1К | C9: 17 | D9: 1043.16 | F9: =C9=#REF! -> #REF! | M9: 1К | N9: 61.362353 | O9: 1043.16 | P9: 3.6345836e+08 | Q9: =P9/O9 -> 348420.53 | R9: =Q9=Сводные!E13 -> FALSE | T9: =N9=Сводные!B13 -> TRUE | U9: =GETPIVOTDATA("Average of Площадь, кв.м",$L$3,"КК","1К","Корпус2","С2")=#REF! -> #REF!
A10: С2 Total | C10: 331 | D10: 10893.55 | L10: С2 Total | N10: 32.911027 | O10: 10893.55 | P10: 3.8192718e+09 | Q10: =P10/O10 -> 350599.37 | R10: =Q10=Сводные!E15 -> FALSE
A11: Grand Total | C11: 1002 | D11: 34591.53 | F11: =C11=#REF! -> #REF! | L11: Grand Total | N11: 34.522485 | O11: 34591.53 | P11: 1.2303e+10 | Q11: =P11/O11 -> 355665.09
A15: Корпус | B15: Кол-во комнат | C15: Кол-во | D15: Площадь
A16: 4 | B16: ст | C16: 314 | D16: 9941.08 | F16: =C16=#REF! -> #REF!
B17: 1АЕ | C17: 17 | D17: 1049.24 | F17: =C17=#REF! -> #REF! | L17: Корпус | M17: Кол-во комнат | N17: Средняя | O17: Площадь
A18: 4 Total | C18: 331 | D18: 10990.32 | L18: 4 | M18: ст | N18: 31.65949 | O18: 9941.08 | Q18: =N18=Сводные!B31 -> TRUE | R18: =GETPIVOTDATA("Средняя",$L$17,"Корпус",4,"Кол-во комнат","ст")=#REF! -> #REF!
A19: 5 | B19: ст | C19: 239 | D19: 9504.41 | F19: =C19=#REF! -> #REF! | M19: 1АЕ | N19: 61.72 | O19: 1049.24 | Q19: =GETPIVOTDATA("Средняя",$L$17,"Корпус",4,"Кол-во комнат","1АЕ")=Сводные!B32 -> TRUE | R19: =GETPIVOTDATA("Средняя",$L$17,"Корпус",4,"Кол-во комнат","1АЕ")=#REF! -> #REF!
B20: 1АЕ | C20: 62 | D20: 3988.39 | F20: =C20=#REF! -> #REF! | L20: 4 Total | N20: 33.203384 | O20: 10990.32
B21: 2АЕ | C21: 12 | D21: 1202.2 | F21: =C21=#REF! -> #REF! | L21: 5 | M21: ст | N21: 39.767406 | O21: 9504.41 | Q21: =GETPIVOTDATA("Средняя",$L$17,"Корпус",5,"Кол-во комнат","ст")=Сводные!B37 -> TRUE | R21: =#REF!=GETPIVOTDATA("Средняя",check!$L$17,"Корпус",5,"Кол-во комнат","ст") -> #REF!
A22: 5 Total | C22: 313 | D22: 14695 | M22: 1АЕ | N22: 64.328871 | O22: 3988.39 | Q22: =GETPIVOTDATA("Средняя",$L$17,"Корпус",5,"Кол-во комнат","1АЕ")=Сводные!B38 -> TRUE | R22: =GETPIVOTDATA("Средняя",$L$17,"Корпус",5,"Кол-во комнат","1АЕ")=#REF! -> #REF!
A23: Grand Total | C23: 644 | D23: 25685.32 | M23: 2АЕ | N23: 100.18333 | O23: 1202.2 | Q23: =GETPIVOTDATA("Средняя",$L$17,"Корпус",5,"Кол-во комнат","2АЕ")=Сводные!B39 -> TRUE | R23: =GETPIVOTDATA("Средняя",$L$17,"Корпус",5,"Кол-во комнат","2АЕ")=#REF! -> #REF!
L24: 5 Total | N24: 46.948882 | O24: 14695
L25: Grand Total | N25: 39.884037 | O25: 25685.32
N29: =#REF!*(100%+Сводные!F31) -> #REF!

Sheet Реестр 1 оч 
A1: Отчет о выполненных работах к приложению №13 к Договору от 17.06.2025 № ДОМУ/2025-06/17 от ИП СИЗОВА ВП | AZ1: 500 | BA1: ДЛЯ САЙТА | BD1: ФИНАЛЬНАЯ ЦЕНА ДЛЯ ЗАГРУЗКИ | BG1: =AO3 -> 6000 | BI1: ПРОВЕРКА - НЕ БЕРЕМ В ЗАЛИВКУ
A2: № п/п | B2: Код ОН | C2: Условный номер | D2: Корпус | E2: Этаж | F2: Номер на площадке | G2: Площадь, кв.м | H2: Количество комнат | I2: Тип по АР | J2: Площадь летних помещений | K2: Площадь летних помещений с коэф. 0,3 | L2: Площадь без летних помещений, кв.м | M2: Площадь с коэф, кв.м | N2: Размер | O2: Тип планировки | P2: Геометрия | Q2: Удленность от лифта (входа) | R2: Виды | S2: Виды для CRM | T2: Расположение на этаже | U2: Количество лотов на этаже | V2: Базовая цена за кв.м, руб (до поправок) | W2: Поправка на этаж, % | X2: Поправка на размер, % | Y2: Поправка на тип планировки, % | Z2: Поправка геометрию, % | AA2: Поправка на удаленность от лифта (входа), % | AB2: Поправка на виды, % | AC2: Поправка на расположение на этаже, % | AD2: Поправка на количество лотов на этаже, % | AE2: Поправка на корпус, % | AF2: РАСЦЕНКА Цена за кв.м, руб | AG2: РАСЦЕНКА Бюджет, руб | AH2: Повышение цены, скидка | AI2: ИТОГ Цена за кв.м, руб | AJ2: ИТОГ Бюджет, руб | AK2: СТАТУС | AL2: Максимальная скидка | AM2: Цена за кв.м. в CRM | AN2: Стоимость, руб для CRM | AO2: Бронь | AP2: Цена за кв.м. в сайт | AQ2: Стоимость, руб для сбронированием | AR2: Код ОН для шахиатки | AS2: Комнат в шахматку | AT2: Площадь в шахматку | AU2: Цена в шахматку | AV2: СТАТУС В ШАХМАТКУ | AW2: Комментарий | AX2: Столбец1 | AZ2: Цена за кв.м. с повышением 500 | BA2: Стоимость с учетом регистрации | BB2: разница | BD2: Цена за кв.м. с повышением 500 | BE2: Стоимость с учетом регистрации | BG2: Стоимость ДДУ | BH2: Бронь | BI2: Цена за кв.м. в ДДУ | BJ2: Процент брони | BL2: Цена со скидкой 10% | BM2: Стоимость лота со скидкой 10%
A3: 1 | B3: С1-1 | C3: 1 | D3: С1 | E3: 1 | F3: 1 | G3: 32.93 | H3: Ст | I3: Ст | J3: 8.19 | K3: =ROUND(J3*0.3,2) -> 2.46 | L3: =G3-J3 -> 24.74 | M3: =L3+K3 -> 27.2 | N3: S | O3: Линейная | P3: Правильная | Q3: Зона 1 | R3: Двор север | S3: Двор | T3: Около/над входной группой | U3: 13 | V3: =IFERROR(VLOOKUP(H3,'Коэфф для прайса 1 оч'!$A$3:$C$6,3,0),"") -> 327000 | W3: =IFERROR(VLOOKUP(E3,'Коэфф для прайса 1 оч'!$A$10:$C$23,3,0),"") -> -0.045 | X3: =IFERROR(VLOOKUP(N3,'Коэфф для прайса 1 оч'!$E$25:$F$30,2,0),"") -> 0.04 | Y3: =IFERROR(VLOOKUP(O3,'Коэфф для прайса 1 оч'!$E$32:$F$34,2,0),"") -> 0 | Z3: =IFERROR(VLOOKUP(P3,'Коэфф для прайса 1 оч'!$E$36:$F$38,2,0),"") -> 0.03 | AA3: =IFERROR(VLOOKUP(Q3,'Коэфф для прайса 1 оч'!$E$40:$F$43,2,0),"") -> 0.005 | AB3: =IFERROR(VLOOKUP(R3,'Коэфф для прайса 1 оч'!$E$45:$F$59,2,0),"") -> -0.015 | AC3: =IFERROR(VLOOKUP(T3,'Коэфф для прайса 1 оч'!$E$61:$F$67,2,0),"") -> -0.01 | AD3: =IFERROR(VLOOKUP(U3,'Коэфф для прайса 1 оч'!$E$69:$F$82,2,0),"") -> 0.013 | AE3: =IFERROR(VLOOKUP(PriceList[[#This Row],[Корпус]],'Коэфф для прайса 1 оч'!$I$10:$J$15,2,0),"") -> 0 | AF3: =ROUND(V3+(V3*SUM(W3:AE3)),2) -> 332886 | AG3: =AF3*G3 -> 10961936 | AH3: 0 | AI3: =AF3+AF3*AH3 -> 332886 | AJ3: =AI3*G3 -> 10961936 | AK3: Резерв | AL3: 0.1 | AM3: =PriceList[[#This Row],[ИТОГ Цена за кв.м, руб]]*(1+PriceList[[#This Row],[Максимальная скидка]]) -> 366174.6 | AN3: =PriceList[[#This Row],[Цена за кв.м. в CRM]]*PriceList[[#This Row],[Площадь, кв.м]] -> 12058130 | AO3: 6000 | AP3: =PriceList[[#This Row],[Цена за кв.м. в CRM]]+PriceList[[#This Row],[Бронь]] -> 372174.6 | AQ3: =PriceList[[#This Row],[Цена за кв.м. в сайт]]*PriceList[[#This Row],[Площадь, кв.м]] -> 12255710 | AR3: =B3 -> С1-1 | AS3: =H3 -> Ст | AT3: =G3 -> 32.93 | AU3: =PriceList[[#This Row],[Цена за кв.м. в CRM]] -> 366174.6 | AV3: =AK3 -> Резерв | AX3: Резерв | AZ3: =(PriceList[[#This Row],[Цена за кв.м. в сайт]])+$AZ$1 -> 372674.6 | BA3: =AZ3*PriceList[[#This Row],[Площадь, кв.м]] -> 12272175 | BB3: =BA3-PriceList[[#This Row],[Стоимость, руб для сбронированием]] -> 16465 | BD3: =MROUND(AZ3,100) -> 372700 | BE3: =BD3*PriceList[[#This Row],[Площадь, кв.м]] -> 12273011 | BG3: =BE3-$BG$1*PriceList[[#This Row],[Площадь, кв.м]] -> 12075431 | BH3: =BE3-BG3 -> 197580 | BI3: =BG3/PriceList[[#This Row],[Площадь, кв.м]] -> 366700 | BJ3: =BH3/BG3 -> 0.016362149
A4: 10 | B4: С1-10 | C4: 10 | D4: С1 | E4: 1 | F4: 10 | G4: 31.95 | H4: Ст | I4: Ст | J4: 6.96 | K4: =ROUND(J4*0.3,2) -> 2.09 | L4: =G4-J4 -> 24.99 | M4: =L4+K4 -> 27.08 | N4: S | O4: Линейная | P4: Правильная | Q4: Зона 1 | R4: Двор северо-восток | S4: Двор | T4: Стандарт | U4: 13 | V4: =IFERROR(VLOOKUP(H4,'Коэфф для прайса 1 оч'!$A$3:$C$6,3,0),"") -> 327000 | W4: =IFERROR(VLOOKUP(E4,'Коэфф для прайса 1 оч'!$A$10:$C$23,3,0),"") -> -0.045 | X4: =IFERROR(VLOOKUP(N4,'Коэфф для прайса 1 оч'!$E$25:$F$30,2,0),"") -> 0.04 | Y4: =IFERROR(VLOOKUP(O4,'Коэфф для прайса 1 оч'!$E$32:$F$34,2,0),"") -> 0 | Z4: =IFERROR(VLOOKUP(P4,'Коэфф для прайса 1 оч'!$E$36:$F$38,2,0),"") -> 0.03 | AA4: =IFERROR(VLOOKUP(Q4,'Коэфф для прайса 1 оч'!$E$40:$F$43,2,0),"") -> 0.005 | AB4: =IFERROR(VLOOKUP(R4,'Коэфф для прайса 1 оч'!$E$45:$F$59,2,0),"") -> -0.01 | AC4: =IFERROR(VLOOKUP(T4,'Коэфф для прайса 1 оч'!$E$61:$F$67,2,0),"") -> 0 | AD4: =IFERROR(VLOOKUP(U4,'Коэфф для прайса 1 оч'!$E$69:$F$82,2,0),"") -> 0.013 | AE4: =IFERROR(VLOOKUP(PriceList[[#This Row],[Корпус]],'Коэфф для прайса 1 оч'!$I$10:$J$15,2,0),"") -> 0 | AF4: =ROUND(V4+(V4*SUM(W4:AE4)),2) -> 337791 | AG4: =AF4*G4 -> 10792422 | AH4: 0 | AI4: =AF4+AF4*AH4 -> 337791 | AJ4: =AI4*G4 -> 10792422 | AK4: Свободно | AL4: 0.1 | AM4: =PriceList[[#This Row],[ИТОГ Цена за кв.м, руб]]*(1+PriceList[[#This Row],[Максимальная скидка]]) -> 371570.1 | AN4: =PriceList[[#This Row],[Цена за кв.м. в CRM]]*PriceList[[#This Row],[Площадь, кв.м]] -> 11871665 | AO4: 6000 | AP4: =PriceList[[#This Row],[Цена за кв.м. в CRM]]+PriceList[[#This Row],[Бронь]] -> 377570.1 | AQ4: =PriceList[[#This Row],[Цена за кв.м. в сайт]]*PriceList[[#This Row],[Площадь, кв.м]] -> 12063365 | AR4: =B4 -> С1-10 | AS4: =H4 -> Ст | AT4: =G4 -> 31.95 | AU4: =PriceList[[#This Row],[Цена за кв.м. в CRM]] -> 371570.1 | AV4: =AK4 -> Свободно | AX4: Свободно | AZ4: =(PriceList[[#This Row],[Цена за кв.м. в сайт]])+$AZ$1 -> 378070.1 | BA4: =AZ4*PriceList[[#This Row],[Площадь, кв.м]] -> 12079340 | BB4: =BA4-PriceList[[#This Row],[Стоимость, руб для сбронированием]] -> 15975 | BD4: =MROUND(AZ4,100) -> 378100 | BE4: =BD4*PriceList[[#This Row],[Площадь, кв.м]] -> 12080295 | BG4: =BE4-$BG$1*PriceList[[#This Row],[Площадь, кв.м]] -> 11888595 | BH4: =BE4-BG4 -> 191700 | BI4: =BG4/PriceList[[#This Row],[Площадь, кв.м]] -> 372100 | BJ4: =BH4/BG4 -> 0.016124698
A5: 100 | B5: С1-100 | C5: 100 | D5: С1 | E5: 4 | F5: 5 | G5: 29.24 | H5: Ст | I5: Ст | J5: 4.25 | K5: =ROUND(J5*0.3,2) -> 1.28 | L5: =G5-J5 -> 24.99 | M5: =L5+K5 -> 26.27 | N5: S | O5: Линейная | P5: Правильная | Q5: Зона 3 | R5: Двор север | S5: Двор | T5: Стандарт | U5: 42 | V5: =IFERROR(VLOOKUP(H5,'Коэфф для прайса 1 оч'!$A$3:$C$6,3,0),"") -> 327000 | W5: =IFERROR(VLOOKUP(E5,'Коэфф для прайса 1 оч'!$A$10:$C$23,3,0),"") -> 0 | X5: =IFERROR(VLOOKUP(N5,'Коэфф для прайса 1 оч'!$E$25:$F$30,2,0),"") -> 0.04 | Y5: =IFERROR(VLOOKUP(O5,'Коэфф для прайса 1 оч'!$E$32:$F$34,2,0),"") -> 0 | Z5: =IFERROR(VLOOKUP(P5,'Коэфф для прайса 1 оч'!$E$36:$F$38,2,0),"") -> 0.03 | AA5: =IFERROR(VLOOKUP(Q5,'Коэфф для прайса 1 оч'!$E$40:$F$43,2,0),"") -> -0.005 | AB5: =IFERROR(VLOOKUP(R5,'Коэфф для прайса 1 оч'!$E$45:$F$59,2,0),"") -> -0.015 | AC5: =IFERROR(VLOOKUP(T5,'Коэфф для прайса 1 оч'!$E$61:$F$67,2,0),"") -> 0 | AD5: =IFERROR(VLOOKUP(U5,'Коэфф для прайса 1 оч'!$E$69:$F$82,2,0),"") -> -0.016 | AE5: =IFERROR(VLOOKUP(PriceList[[#This Row],[Корпус]],'Коэфф для прайса 1 оч'!$I$10:$J$15,2,0),"") -> 0 | AF5: =ROUND(V5+(V5*SUM(W5:AE5)),2) -> 338118 | AG5: =AF5*G5 -> 9886570.3 | AH5: 0 | AI5: =AF5+AF5*AH5 -> 338118 | AJ5: =AI5*G5 -> 9886570.3 | AK5: Свободно | AL5: 0.1 | AM5: =PriceList[[#This Row],[ИТОГ Цена за кв.м, руб]]*(1+PriceList[[#This Row],[Максимальная скидка]]) -> 371929.8 | AN5: =PriceList[[#This Row],[Цена за кв.м. в CRM]]*PriceList[[#This Row],[Площадь, кв.м]] -> 10875227 | AO5: 6000 | AP5: =PriceList[[#This Row],[Цена за кв.м. в CRM]]+PriceList[[#This Row],[Бронь]] -> 377929.8 | AQ5: =PriceList[[#This Row],[Цена за кв.м. в сайт]]*PriceList[[#This Row],[Площадь, кв.м]] -> 11050667 | AR5: =B5 -> С1-100 | AS5: =H5 -> Ст | AT5: =G5 -> 29.24 | AU5: =PriceList[[#This Row],[Цена за кв.м. в CRM]] -> 371929.8 | AV5: =AK5 -> Свободно | AX5: Бронь | AZ5: =(PriceList[[#This Row],[Цена за кв.м. в сайт]])+$AZ$1 -> 378429.8 | BA5: =AZ5*PriceList[[#This Row],[Площадь, кв.м]] -> 11065287 | BB5: =BA5-PriceList[[#This Row],[Стоимость, руб для сбронированием]] -> 14620 | BD5: =MROUND(AZ5,100) -> 378400 | BE5: =BD5*PriceList[[#This Row],[Площадь, кв.м]] -> 11064416 | BG5: =BE5-$BG$1*PriceList[[#This Row],[Площадь, кв.м]] -> 10888976 | BH5: =BE5-BG5 -> 175440 | BI5: =BG5/PriceList[[#This Row],[Площадь, кв.м]] -> 372400 | BJ5: =BH5/BG5 -> 0.016111708
A6: 101 | B6: С1-101 | C6: 101 | D6: С1 | E6: 4 | F6: 6 | G6: 29.24 | H6: Ст | I6: Ст | J6: 4.25 | K6: =ROUND(J6*0.3,2) -> 1.28 | L6: =G6-J6 -> 24.99 | M6: =L6+K6 -> 26.27 | N6: S | O6: Линейная | P6: Правильная | Q6: Зона 3 | R6: Двор север | S6: Двор | T6: Стандарт | U6: 42 | V6: =IFERROR(VLOOKUP(H6,'Коэфф для прайса 1 оч'!$A$3:$C$6,3,0),"") -> 327000 | W6: =IFERROR(VLOOKUP(E6,'Коэфф для прайса 1 оч'!$A$10:$C$23,3,0),"") -> 0 | X6: =IFERROR(VLOOKUP(N6,'Коэфф для прайса 1 оч'!$E$25:$F$30,2,0),"") -> 0.04 | Y6: =IFERROR(VLOOKUP(O6,'Коэфф для прайса 1 оч'!$E$32:$F$34,2,0),"") -> 0 | Z6: =IFERROR(VLOOKUP(P6,'Коэфф для прайса 1 оч'!$E$36:$F$38,2,0),"") -> 0.03 | AA6: =IFERROR(VLOOKUP(Q6,'Коэфф для прайса 1 оч'!$E$40:$F$43,2,0),"") -> -0.005 | AB6: =IFERROR(VLOOKUP(R6,'Коэфф для прайса 1 оч'!$E$45:$F$59,2,0),"") -> -0.015 | AC6: =IFERROR(VLOOKUP(T6,'Коэфф для прайса 1 оч'!$E$61:$F$67,2,0),"") -> 0 | AD6: =IFERROR(VLOOKUP(U6,'Коэфф для прайса 1 оч'!$E$69:$F$82,2,0),"") -> -0.016 | AE6: =IFERROR(VLOOKUP(PriceList[[#This Row],[Корпус]],'Коэфф для прайса 1 оч'!$I$10:$J$15,2,0),"") -> 0 | AF6: =ROUND(V6+(V6*SUM(W6:AE6)),2) -> 338118 | AG6: =AF6*G6 -> 9886570.3 | AH6: 0 | AI6: =AF6+AF6*AH6 -> 338118 | AJ6: =AI6*G6 -> 9886570.3 | AK6: Свободно | AL6: 0.1 | AM6: =PriceList[[#This Row],[ИТОГ Цена за кв.м, руб]]*(1+PriceList[[#This Row],[Максимальная скидка]]) -> 371929.8 | AN6: =PriceList[[#This Row],[Цена за кв.м. в CRM]]*PriceList[[#This Row],[Площадь, кв.м]] -> 10875227 | AO6: 6000 | AP6: =PriceList[[#This Row],[Цена за кв.м. в CRM]]+PriceList[[#This Row],[Бронь]] -> 377929.8 | AQ6: =PriceList[[#This Row],[Цена за кв.м. в сайт]]*PriceList[[#This Row],[Площадь, кв.м]] -> 11050667 | AR6: =B6 -> С1-101 | AS6: =H6 -> Ст | AT6: =G6 -> 29.24 | AU6: =PriceList[[#This Row],[Цена за кв.м. в CRM]] -> 371929.8 | AV6: =AK6 -> Свободно | AX6: Продано | AZ6: =(PriceList[[#This Row],[Цена за кв.м. в сайт]])+$AZ$1 -> 378429.8 | BA6: =AZ6*PriceList[[#This Row],[Площадь, кв.м]] -> 11065287 | BB6: =BA6-PriceList[[#This Row],[Стоимость, руб для сбронированием]] -> 14620 | BD6: =MROUND(AZ6,100) -> 378400 | BE6: =BD6*PriceList[[#This Row],[Площадь, кв.м]] -> 11064416 | BG6: =BE6-$BG$1*PriceList[[#This Row],[Площадь, кв.м]] -> 10888976 | BH6: =BE6-BG6 -> 175440 | BI6: =BG6/PriceList[[#This Row],[Площадь, кв.м]] -> 372400 | BJ6: =BH6/BG6 -> 0.016111708
A7: 102 | B7: С1-102 | C7: 102 | D7: С1 | E7: 4 | F7: 7 | G7: 28.6 | H7: Ст | I7: Ст | J7: 4.25 | K7: =ROUND(J7*0.3,2) -> 1.28 | L7: =G7-J7 -> 24.35 | M7: =L7+K7 -> 25.63 | N7: S | O7: Линейная | P7: Правильная | Q7: Зона 3 | R7: Двор север | S7: Двор | T7: Стандарт | U7: 42 | V7: =IFERROR(VLOOKUP(H7,'Коэфф для прайса 1 оч'!$A$3:$C$6,3,0),"") -> 327000 | W7: =IFERROR(VLOOKUP(E7,'Коэфф для прайса 1 оч'!$A$10:$C$23,3,0),"") -> 0 | X7: =IFERROR(VLOOKUP(N7,'Коэфф для прайса 1 оч'!$E$25:$F$30,2,0),"") -> 0.04 | Y7: =IFERROR(VLOOKUP(O7,'Коэфф для прайса 1 оч'!$E$32:$F$34,2,0),"") -> 0 | Z7: =IFERROR(VLOOKUP(P7,'Коэфф для прайса 1 оч'!$E$36:$F$38,2,0),"") -> 0.03 | AA7: =IFERROR(VLOOKUP(Q7,'Коэфф для прайса 1 оч'!$E$40:$F$43,2,0),"") -> -0.005 | AB7: =IFERROR(VLOOKUP(R7,'Коэфф для прайса 1 оч'!$E$45:$F$59,2,0),"") -> -0.015 | AC7: =IFERROR(VLOOKUP(T7,'Коэфф для прайса 1 оч'!$E$61:$F$67,2,0),"") -> 0 | AD7: =IFERROR(VLOOKUP(U7,'Коэфф для прайса 1 оч'!$E$69:$F$82,2,0),"") -> -0.016 | AE7: =IFERROR(VLOOKUP(PriceList[[#This Row],[Корпус]],'Коэфф для прайса 1 оч'!$I$10:$J$15,2,0),"") -> 0 | AF7: =ROUND(V7+(V7*SUM(W7:AE7)),2) -> 338118 | AG7: =AF7*G7 -> 9670174.8 | AH7: 0 | AI7: =AF7+AF7*AH7 -> 338118 | AJ7: =AI7*G7 -> 9670174.8 | AK7: Резерв | AL7: 0.1 | AM7: =PriceList[[#This Row],[ИТОГ Цена за кв.м, руб]]*(1+PriceList[[#This Row],[Максимальная скидка]]) -> 371929.8 | AN7: =PriceList[[#This Row],[Цена за кв.м. в CRM]]*PriceList[[#This Row],[Площадь, кв.м]] -> 10637192 | AO7: 6000 | AP7: =PriceList[[#This Row],[Цена за кв.м. в CRM]]+PriceList[[#This Row],[Бронь]] -> 377929.8 | AQ7: =PriceList[[#This Row],[Цена за кв.м. в сайт]]*PriceList[[#This Row],[Площадь, кв.м]] -> 10808792 | AR7: =B7 -> С1-102 | AS7: =H7 -> Ст | AT7: =G7 -> 28.6 | AU7: =PriceList[[#This Row],[Цена за кв.м. в CRM]] -> 371929.8 | AV7: =AK7 -> Резерв | AX7: Не для продажи | AZ7: =(PriceList[[#This Row],[Цена за кв.м. в сайт]])+$AZ$1 -> 378429.8 | BA7: =AZ7*PriceList[[#This Row],[Площадь, кв.м]] -> 10823092 | BB7: =BA7-PriceList[[#This Row],[Стоимость, руб для сбронированием]] -> 14300 | BD7: =MROUND(AZ7,100) -> 378400 | BE7: =BD7*PriceList[[#This Row],[Площадь, кв.м]] -> 10822240 | BG7: =BE7-$BG$1*PriceList[[#This Row],[Площадь, кв.м]] -> 10650640 | BH7: =BE7-BG7 -> 171600 | BI7: =BG7/PriceList[[#This Row],[Площадь, кв.м]] -> 372400 | BJ7: =BH7/BG7 -> 0.016111708
A8: 103 | B8: С1-103 | C8: 103 | D8: С1 | E8: 4 | F8: 8 | G8: 49.71 | H8: Ст | I8: Ст | J8: 13.98 | K8: =ROUND(J8*0.3,2) -> 4.19 | L8: =G8-J8 -> 35.73 | M8: =L8+K8 -> 39.92 | N8: L | O8: Угловая | P8: Правильная | Q8: Зона 3 | R8: Двор северо-восток | S8: Двор | T8: Стандарт | U8: 42 | V8: =IFERROR(VLOOKUP(H8,'Коэфф для прайса 1 оч'!$A$3:$C$6,3,0),"") -> 327000 | W8: =IFERROR(VLOOKUP(E8,'Коэфф для прайса 1 оч'!$A$10:$C$23,3,0),"") -> 0 | X8: =IFERROR(VLOOKUP(N8,'Коэфф для прайса 1 оч'!$E$25:$F$30,2,0),"") -> -0.01 | Y8: =IFERROR(VLOOKUP(O8,'Коэфф для прайса 1 оч'!$E$32:$F$34,2,0),"") -> 0.03 | Z8: =IFERROR(VLOOKUP(P8,'Коэфф для прайса 1 оч'!$E$36:$F$38,2,0),"") -> 0.03 | AA8: =IFERROR(VLOOKUP(Q8,'Коэфф для прайса 1 оч'!$E$40:$F$43,2,0),"") -> -0.005 | AB8: =IFERROR(VLOOKUP(R8,'Коэфф для прайса 1 оч'!$E$45:$F$59,2,0),"") -> -0.01 | AC8: =IFERROR(VLOOKUP(T8,'Коэфф для прайса 1 оч'!$E$61:$F$67,2,0),"") -> 0 | AD8: =IFERROR(VLOOKUP(U8,'Коэфф для прайса 1 оч'!$E$69:$F$82,2,0),"") -> -0.016 | AE8: =IFERROR(VLOOKUP(PriceList[[#This Row],[Корпус]],'Коэфф для прайса 1 оч'!$I$10:$J$15,2,0),"") -> 0 | AF8: =ROUND(V8+(V8*SUM(W8:AE8)),2) -> 333213 | AG8: =AF8*G8 -> 16564018 | AH8: 0 | AI8: =AF8+AF8*AH8 -> 333213 | AJ8: =AI8*G8 -> 16564018 | AK8: Резерв | AL8: 0.1 | AM8: =PriceList[[#This Row],[ИТОГ Цена за кв.м, руб]]*(1+PriceList[[#This Row],[Максимальная скидка]]) -> 366534.3 | AN8: =PriceList[[#This Row],[Цена за кв.м. в CRM]]*PriceList[[#This Row],[Площадь, кв.м]] -> 18220420 | AO8: 6000 | AP8: =PriceList[[#This Row],[Цена за кв.м. в CRM]]+PriceList[[#This Row],[Бронь]] -> 372534.3 | AQ8: =PriceList[[#This Row],[Цена за кв.м. в сайт]]*PriceList[[#This Row],[Площадь, кв.м]] -> 18518680 | AR8: =B8 -> С1-103 | AS8: =H8 -> Ст | AT8: =G8 -> 49.71 | AU8: =PriceList[[#This Row],[Цена за кв.м. в CRM]] -> 366534.3 | AV8: =AK8 -> Резерв | AZ8: =(PriceList[[#This Row],[Цена за кв.м. в сайт]])+$AZ$1 -> 373034.3 | BA8: =AZ8*PriceList[[#This Row],[Площадь, кв.м]] -> 18543535 | BB8: =BA8-PriceList[[#This Row],[Стоимость, руб для сбронированием]] -> 24855 | BD8: =MROUND(AZ8,100) -> 373000 | BE8: =BD8*PriceList[[#This Row],[Площадь, кв.м]] -> 18541830 | BG8: =BE8-$BG$1*PriceList[[#This Row],[Площадь, кв.м]] -> 18243570 | BH8: =BE8-BG8 -> 298260 | BI8: =BG8/PriceList[[#This Row],[Площадь, кв.м]] -> 367000 | BJ8: =BH8/BG8 -> 0.016348774
A9: 104 | B9: С1-104 | C9: 104 | D9: С1 | E9: 4 | F9: 9 | G9: 49.71 | H9: Ст | I9: Ст | J9: 13.98 | K9: =ROUND(J9*0.3,2) -> 4.19 | L9: =G9-J9 -> 35.73 | M9: =L9+K9 -> 39.92 | N9: L | O9: Угловая | P9: Правильная | Q9: Зона 3 | R9: Море | S9: Море | T9: Стандарт | U9: 42 | V9: =IFERROR(VLOOKUP(H9,'Коэфф для прайса 1 оч'!$A$3:$C$6,3,0),"") -> 327000 | W9: =IFERROR(VLOOKUP(E9,'Коэфф для прайса 1 оч'!$A$10:$C$23,3,0),"") -> 0 | X9: =IFERROR(VLOOKUP(N9,'Коэфф для прайса 1 оч'!$E$25:$F$30,2,0),"") -> -0.01 | Y9: =IFERROR(VLOOKUP(O9,'Коэфф для прайса 1 оч'!$E$32:$F$34,2,0),"") -> 0.03 | Z9: =IFERROR(VLOOKUP(P9,'Коэфф для прайса 1 оч'!$E$36:$F$38,2,0),"") -> 0.03 | AA9: =IFERROR(VLOOKUP(Q9,'Коэфф для прайса 1 оч'!$E$40:$F$43,2,0),"") -> -0.005 | AB9: =IFERROR(VLOOKUP(R9,'Коэфф для прайса 1 оч'!$E$45:$F$59,2,0),"") -> 0.07 | AC9: =IFERROR(VLOOKUP(T9,'Коэфф для прайса 1 оч'!$E$61:$F$67,2,0),"") -> 0 | AD9: =IFERROR(VLOOKUP(U9,'Коэфф для прайса 1 оч'!$E$69:$F$82,2,0),"") -> -0.016 | AE9: =IFERROR(VLOOKUP(PriceList[[#This Row],[Корпус]],'Коэфф для прайса 1 оч'!$I$10:$J$15,2,0),"") -> 0 | AF9: =ROUND(V9+(V9*SUM(W9:AE9)),2) -> 359373 | AG9: =AF9*G9 -> 17864432 | AH9: 0 | AI9: =AF9+AF9*AH9 -> 359373 | AJ9: =AI9*G9 -> 17864432 | AK9: Резерв | AL9: 0.1 | AM9: =PriceList[[#This Row],[ИТОГ Цена за кв.м, руб]]*(1+PriceList[[#This Row],[Максимальная скидка]]) -> 395310.3 | AN9: =PriceList[[#This Row],[Цена за кв.м. в CRM]]*PriceList[[#This Row],[Площадь, кв.м]] -> 19650875 | AO9: 6000 | AP9: =PriceList[[#This Row],[Цена за кв.м. в CRM]]+PriceList[[#This Row],[Бронь]] -> 401310.3 | AQ9: =PriceList[[#This Row],[Цена за кв.м. в сайт]]*PriceList[[#This Row],[Площадь, кв.м]] -> 19949135 | AR9: =B9 -> С1-104 | AS9: =H9 -> Ст | AT9: =G9 -> 49.71 | AU9: =PriceList[[#This Row],[Цена за кв.м. в CRM]] -> 395310.3 | AV9: =AK9 -> Резерв | AZ9: =(PriceList[[#This Row],[Цена за кв.м. в сайт]])+$AZ$1 -> 401810.3 | BA9: =AZ9*PriceList[[#This Row],[Площадь, кв.м]] -> 19973990 | BB9: =BA9-PriceList[[#This Row],[Стоимость, руб для сбронированием]] -> 24855 | BD9: =MROUND(AZ9,100) -> 401800 | BE9: =BD9*PriceList[[#This Row],[Площадь, кв.м]] -> 19973478 | BG9: =BE9-$BG$1*PriceList[[#This Row],[Площадь, кв.м]] -> 19675218 | BH9: =BE9-BG9 -> 298260 | BI9: =BG9/PriceList[[#This Row],[Площадь, кв.м]] -> 395800 | BJ9: =BH9/BG9 -> 0.015159171
A10: 105 | B10: С1-105 | C10: 105 | D10: С1 | E10: 4 | F10: 10 | G10: 28.6 | H10: Ст | I10: Ст | J10: 4.25 | K10: =ROUND(J10*0.3,2) -> 1.28 | L10: =G10-J10 -> 24.35 | M10: =L10+K10 -> 25.63 | N10: S | O10: Линейная | P10: Правильная | Q10: Зона 3 | R10: Море | S10: Море | T10: Стандарт | U10: 42 | V10: =IFERROR(VLOOKUP(H10,'Коэфф для прайса 1 оч'!$A$3:$C$6,3,0),"") -> 327000 | W10: =IFERROR(VLOOKUP(E10,'Коэфф для прайса 1 оч'!$A$10:$C$23,3,0),"") -> 0 | X10: =IFERROR(VLOOKUP(N10,'Коэфф для прайса 1 оч'!$E$25:$F$30,2,0),"") -> 0.04 | Y10: =IFERROR(VLOOKUP(O10,'Коэфф для прайса 1 оч'!$E$32:$F$34,2,0),"") -> 0 | Z10: =IFERROR(VLOOKUP(P10,'Коэфф для прайса 1 оч'!$E$36:$F$38,2,0),"") -> 0.03 | AA10: =IFERROR(VLOOKUP(Q10,'Коэфф для прайса 1 оч'!$E$40:$F$43,2,0),"") -> -0.005 | AB10: =IFERROR(VLOOKUP(R10,'Коэфф для прайса 1 оч'!$E$45:$F$59,2,0),"") -> 0.07 | AC10: =IFERROR(VLOOKUP(T10,'Коэфф для прайса 1 оч'!$E$61:$F$67,2,0),"") -> 0 | AD10: =IFERROR(VLOOKUP(U10,'Коэфф для прайса 1 оч'!$E$69:$F$82,2,0),"") -> -0.016 | AE10: =IFERROR(VLOOKUP(PriceList[[#This Row],[Корпус]],'Коэфф для прайса 1 оч'!$I$10:$J$15,2,0),"") -> 0 | AF10: =ROUND(V10+(V10*SUM(W10:AE10)),2) -> 365913 | AG10: =AF10*G10 -> 10465112 | AH10: 0 | AI10: =AF10+AF10*AH10 -> 365913 | AJ10: =AI10*G10 -> 10465112 | AK10: Резерв | AL10: 0.1 | AM10: =PriceList[[#This Row],[ИТОГ Цена за кв.м, руб]]*(1+PriceList[[#This Row],[Максимальная скидка]]) -> 402504.3 | AN10: =PriceList[[#This Row],[Цена за кв.м. в CRM]]*PriceList[[#This Row],[Площадь, кв.м]] -> 11511623 | AO10: 6000 | AP10: =PriceList[[#This Row],[Цена за кв.м. в CRM]]+PriceList[[#This Row],[Бронь]] -> 408504.3 | AQ10: =PriceList[[#This Row],[Цена за кв.м. в сайт]]*PriceList[[#This Row],[Площадь, кв.м]] -> 11683223 | AR10: =B10 -> С1-105 | AS10: =H10 -> Ст | AT10: =G10 -> 28.6 | AU10: =PriceList[[#This Row],[Цена за кв.м. в CRM]] -> 402504.3 | AV10: =AK10 -> Резерв | AZ10: =(PriceList[[#This Row],[Цена за кв.м. в сайт]])+$AZ$1 -> 409004.3 | BA10: =AZ10*PriceList[[#This Row],[Площадь, кв.м]] -> 11697523 | BB10: =BA10-PriceList[[#This Row],[Стоимость, руб для сбронированием]] -> 14300 | BD10: =MROUND(AZ10,100) -> 409000 | BE10: =BD10*PriceList[[#This Row],[Площадь, кв.м]] -> 11697400 | BG10: =BE10-$BG$1*PriceList[[#This Row],[Площадь, кв.м]] -> 11525800 | BH10: =BE10-BG10 -> 171600 | BI10: =BG10/PriceList[[#This Row],[Площадь, кв.м]] -> 403000 | BJ10: =BH10/BG10 -> 0.014888337
A11: 106 | B11: С1-106 | C11: 106 | D11: С1 | E11: 4 | F11: 11 | G11: 29.24 | H11: Ст | I11: Ст | J11: 4.25 | K11: =ROUND(J11*0.3,2) -> 1.28 | L11: =G11-J11 -> 24.99 | M11: =L11+K11 -> 26.27 | N11: S | O11: Линейная | P11: Правильная | Q11: Зона 3 | R11: Море | S11: Море | T11: Стандарт | U11: 42 | V11: =IFERROR(VLOOKUP(H11,'Коэфф для прайса 1 оч'!$A$3:$C$6,3,0),"") -> 327000 | W11: =IFERROR(VLOOKUP(E11,'Коэфф для прайса 1 оч'!$A$10:$C$23,3,0),"") -> 0 | X11: =IFERROR(VLOOKUP(N11,'Коэфф для прайса 1 оч'!$E$25:$F$30,2,0),"") -> 0.04 | Y11: =IFERROR(VLOOKUP(O11,'Коэфф для прайса 1 оч'!$E$32:$F$34,2,0),"") -> 0 | Z11: =IFERROR(VLOOKUP(P11,'Коэфф для прайса 1 оч'!$E$36:$F$38,2,0),"") -> 0.03 | AA11: =IFERROR(VLOOKUP(Q11,'Коэфф для прайса 1 оч'!$E$40:$F$43,2,0),"") -> -0.005 | AB11: =IFERROR(VLOOKUP(R11,'Коэфф для прайса 1 оч'!$E$45:$F$59,2,0),"") -> 0.07 | AC11: =IFERROR(VLOOKUP(T11,'Коэфф для прайса 1 оч'!$E$61:$F$67,2,0),"") -> 0 | AD11: =IFERROR(VLOOKUP(U11,'Коэфф для прайса 1 оч'!$E$69:$F$82,2,0),"") -> -0.016 | AE11: =IFERROR(VLOOKUP(PriceList[[#This Row],[Корпус]],'Коэфф для прайса 1 оч'!$I$10:$J$15,2,0),"") -> 0 | AF11: =ROUND(V11+(V11*SUM(W11:AE11)),2) -> 365913 | AG11: =AF11*G11 -> 10699296 | AH11: 0 | AI11: =AF11+AF11*AH11 -> 365913 | AJ11: =AI11*G11 -> 10699296 | AK11: Резерв | AL11: 0.1 | AM11: =PriceList[[#This Row],[ИТОГ Цена за кв.м, руб]]*(1+PriceList[[#This Row],[Максимальная скидка]]) -> 402504.3 | AN11: =PriceList[[#This Row],[Цена за кв.м. в CRM]]*PriceList[[#This Row],[Площадь, кв.м]] -> 11769226 | AO11: 6000 | AP11: =PriceList[[#This Row],[Цена за кв.м. в CRM]]+PriceList[[#This Row],[Бронь]] -> 408504.3 | AQ11: =PriceList[[#This Row],[Цена за кв.м. в сайт]]*PriceList[[#This Row],[Площадь, кв.м]] -> 11944666 | AR11: =B11 -> С1-106 | AS11: =H11 -> Ст | AT11: =G11 -> 29.24 | AU11: =PriceList[[#This Row],[Цена за кв.м. в CRM]] -> 402504.3 | AV11: =AK11 -> Резерв | AZ11: =(PriceList[[#This Row],[Цена за кв.м. в сайт]])+$AZ$1 -> 409004.3 | BA11: =AZ11*PriceList[[#This Row],[Площадь, кв.м]] -> 11959286 | BB11: =BA11-PriceList[[#This Row],[Стоимость, руб для сбронированием]] -> 14620 | BD11: =MROUND(AZ11,100) -> 409000 | BE11: =BD11*PriceList[[#This Row],[Площадь, кв.м]] -> 11959160 | BG11: =BE11-$BG$1*PriceList[[#This Row],[Площадь, кв.м]] -> 11783720 | BH11: =BE11-BG11 -> 175440 | BI11: =BG11/PriceList[[#This Row],[Площадь, кв.м]] -> 403000 | BJ11: =BH11/BG11 -> 0.014888337
A12: 107 | B12: С1-107 | C12: 107 | D12: С1 | E12: 4 | F12: 12 | G12: 29.24 | H12: Ст | I12: Ст | J12: 4.25 | K12: =ROUND(J12*0.3,2) -> 1.28 | L12: =G12-J12 -> 24.99 | M12: =L12+K12 -> 26.27 | N12: S | O12: Линейная | P12: Правильная | Q12: Зона 3 | R12: Море | S12: Море | T12: Стандарт | U12: 42 | V12: =IFERROR(VLOOKUP(H12,'Коэфф для прайса 1 оч'!$A$3:$C$6,3,0),"") -> 327000 | W12: =IFERROR(VLOOKUP(E12,'Коэфф для прайса 1 оч'!$A$10:$C$23,3,0),"") -> 0 | X12: =IFERROR(VLOOKUP(N12,'Коэфф для прайса 1 оч'!$E$25:$F$30,2,0),"") -> 0.04 | Y12: =IFERROR(VLOOKUP(O12,'Коэфф для прайса 1 оч'!$E$32:$F$34,2,0),"") -> 0 | Z12: =IFERROR(VLOOKUP(P12,'Коэфф для прайса 1 оч'!$E$36:$F$38,2,0),"") -> 0.03 | AA12: =IFERROR(VLOOKUP(Q12,'Коэфф для прайса 1 оч'!$E$40:$F$43,2,0),"") -> -0.005 | AB12: =IFERROR(VLOOKUP(R12,'Коэфф для прайса 1 оч'!$E$45:$F$59,2,0),"") -> 0.07 | AC12: =IFERROR(VLOOKUP(T12,'Коэфф для прайса 1 оч'!$E$61:$F$67,2,0),"") -> 0 | AD12: =IFERROR(VLOOKUP(U12,'Коэфф для прайса 1 оч'!$E$69:$F$82,2,0),"") -> -0.016 | AE12: =IFERROR(VLOOKUP(PriceList[[#This Row],[Корпус]],'Коэфф для прайса 1 оч'!$I$10:$J$15,2,0),"") -> 0 | AF12: =ROUND(V12+(V12*SUM(W12:AE12)),2) -> 365913 | AG12: =AF12*G12 -> 10699296 | AH12: 0 | AI12: =AF12+AF12*AH12 -> 365913 | AJ12: =AI12*G12 -> 10699296 | AK12: Резерв | AL12: 0.1 | AM12: =PriceList[[#This Row],[ИТОГ Цена за кв.м, руб]]*(1+PriceList[[#This Row],[Максимальная скидка]]) -> 402504.3 | AN12: =PriceList[[#This Row],[Цена за кв.м. в CRM]]*PriceList[[#This Row],[Площадь, кв.м]] -> 11769226 | AO12: 6000 | AP12: =PriceList[[#This Row],[Цена за кв.м. в CRM]]+PriceList[[#This Row],[Бронь]] -> 408504.3 | AQ12: =PriceList[[#This Row],[Цена за кв.м. в сайт]]*PriceList[[#This Row],[Площадь, кв.м]] -> 11944666 | AR12: =B12 -> С1-107 | AS12: =H12 -> Ст | AT12: =G12 -> 29.24 | AU12: =PriceList[[#This Row],[Цена за кв.м. в CRM]] -> 402504.3 | AV12: =AK12 -> Резерв | AZ12: =(PriceList[[#This Row],[Цена за кв.м. в сайт]])+$AZ$1 -> 409004.3 | BA12: =AZ12*PriceList[[#This Row],[Площадь, кв.м]] -> 11959286 | BB12: =BA12-PriceList[[#This Row],[Стоимость, руб для сбронированием]] -> 14620 | BD12: =MROUND(AZ12,100) -> 409000 | BE12: =BD12*PriceList[[#This Row],[Площадь, кв.м]] -> 11959160 | BG12: =BE12-$BG$1*PriceList[[#This Row],[Площадь, кв.м]] -> 11783720 | BH12: =BE12-BG12 -> 175440 | BI12: =BG12/PriceList[[#This Row],[Площадь, кв.м]] -> 403000 | BJ12: =BH12/BG12 -> 0.014888337
A13: 108 | B13: С1-108 | C13: 108 | D13: С1 | E13: 4 | F13: 13 | G13: 29.24 | H13: Ст | I13: Ст | J13: 4.25 | K13: =ROUND(J13*0.3,2) -> 1.28 | L13: =G13-J13 -> 24.99 | M13: =L13+K13 -> 26.27 | N13: S | O13: Линейная | P13: Правильная | Q13: Зона 2 | R13: Море | S13: Море | T13: Стандарт | U13: 42 | V13: =IFERROR(VLOOKUP(H13,'Коэфф для прайса 1 оч'!$A$3:$C$6,3,0),"") -> 327000 | W13: =IFERROR(VLOOKUP(E13,'Коэфф для прайса 1 оч'!$A$10:$C$23,3,0),"") -> 0 | X13: =IFERROR(VLOOKUP(N13,'Коэфф для прайса 1 оч'!$E$25:$F$30,2,0),"") -> 0.04 | Y13: =IFERROR(VLOOKUP(O13,'Коэфф для прайса 1 оч'!$E$32:$F$34,2,0),"") -> 0 | Z13: =IFERROR(VLOOKUP(P13,'Коэфф для прайса 1 оч'!$E$36:$F$38,2,0),"") -> 0.03 | AA13: =IFERROR(VLOOKUP(Q13,'Коэфф для прайса 1 оч'!$E$40:$F$43,2,0),"") -> 0 | AB13: =IFERROR(VLOOKUP(R13,'Коэфф для прайса 1 оч'!$E$45:$F$59,2,0),"") -> 0.07 | AC13: =IFERROR(VLOOKUP(T13,'Коэфф для прайса 1 оч'!$E$61:$F$67,2,0),"") -> 0 | AD13: =IFERROR(VLOOKUP(U13,'Коэфф для прайса 1 оч'!$E$69:$F$82,2,0),"") -> -0.016 | AE13: =IFERROR(VLOOKUP(PriceList[[#This Row],[Корпус]],'Коэфф для прайса 1 оч'!$I$10:$J$15,2,0),"") -> 0 | AF13: =ROUND(V13+(V13*SUM(W13:AE13)),2) -> 367548 | AG13: =AF13*G13 -> 10747104 | AH13: 0 | AI13: =AF13+AF13*AH13 -> 367548 | AJ13: =AI13*G13 -> 10747104 | AK13: Резерв | AL13: 0.1 | AM13: =PriceList[[#This Row],[ИТОГ Цена за кв.м, руб]]*(1+PriceList[[#This Row],[Максимальная скидка]]) -> 404302.8 | AN13: =PriceList[[#This Row],[Цена за кв.м. в CRM]]*PriceList[[#This Row],[Площадь, кв.м]] -> 11821814 | AO13: 6000 | AP13: =PriceList[[#This Row],[Цена за кв.м. в CRM]]+PriceList[[#This Row],[Бронь]] -> 410302.8 | AQ13: =PriceList[[#This Row],[Цена за кв.м. в сайт]]*PriceList[[#This Row],[Площадь, кв.м]] -> 11997254 | AR13: =B13 -> С1-108 | AS13: =H13 -> Ст | AT13: =G13 -> 29.24 | AU13: =PriceList[[#This Row],[Цена за кв.м. в CRM]] -> 404302.8 | AV13: =AK13 -> Резерв | AZ13: =(PriceList[[#This Row],[Цена за кв.м. в сайт]])+$AZ$1 -> 410802.8 | BA13: =AZ13*PriceList[[#This Row],[Площадь, кв.м]] -> 12011874 | BB13: =BA13-PriceList[[#This Row],[Стоимость, руб для сбронированием]] -> 14620 | BD13: =MROUND(AZ13,100) -> 410800 | BE13: =BD13*PriceList[[#This Row],[Площадь, кв.м]] -> 12011792 | BG13: =BE13-$BG$1*PriceList[[#This Row],[Площадь, кв.м]] -> 11836352 | BH13: =BE13-BG13 -> 175440 | BI13: =BG13/PriceList[[#This Row],[Площадь, кв.м]] -> 404800 | BJ13: =BH13/BG13 -> 0.014822134
A14: 109 | B14: С1-109 | C14: 109 | D14: С1 | E14: 4 | F14: 14 | G14: 29.24 | H14: Ст | I14: Ст | J14: 4.25 | K14: =ROUND(J14*0.3,2) -> 1.28 | L14: =G14-J14 -> 24.99 | M14: =L14+K14 -> 26.27 | N14: S | O14: Линейная | P14: Правильная | Q14: Зона 2 | R14: Море | S14: Море | T14: Стандарт | U14: 42 | V14: =IFERROR(VLOOKUP(H14,'Коэфф для прайса 1 оч'!$A$3:$C$6,3,0),"") -> 327000 | W14: =IFERROR(VLOOKUP(E14,'Коэфф для прайса 1 оч'!$A$10:$C$23,3,0),"") -> 0 | X14: =IFERROR(VLOOKUP(N14,'Коэфф для прайса 1 оч'!$E$25:$F$30,2,0),"") -> 0.04 | Y14: =IFERROR(VLOOKUP(O14,'Коэфф для прайса 1 оч'!$E$32:$F$34,2,0),"") -> 0 | Z14: =IFERROR(VLOOKUP(P14,'Коэфф для прайса 1 оч'!$E$36:$F$38,2,0),"") -> 0.03 | AA14: =IFERROR(VLOOKUP(Q14,'Коэфф для прайса 1 оч'!$E$40:$F$43,2,0),"") -> 0 | AB14: =IFERROR(VLOOKUP(R14,'Коэфф для прайса 1 оч'!$E$45:$F$59,2,0),"") -> 0.07 | AC14: =IFERROR(VLOOKUP(T14,'Коэфф для прайса 1 оч'!$E$61:$F$67,2,0),"") -> 0 | AD14: =IFERROR(VLOOKUP(U14,'Коэфф для прайса 1 оч'!$E$69:$F$82,2,0),"") -> -0.016 | AE14: =IFERROR(VLOOKUP(PriceList[[#This Row],[Корпус]],'Коэфф для прайса 1 оч'!$I$10:$J$15,2,0),"") -> 0 | AF14: =ROUND(V14+(V14*SUM(W14:AE14)),2) -> 367548 | AG14: =AF14*G14 -> 10747104 | AH14: 0 | AI14: =AF14+AF14*AH14 -> 367548 | AJ14: =AI14*G14 -> 10747104 | AK14: Резерв | AL14: 0.1 | AM14: =PriceList[[#This Row],[ИТОГ Цена за кв.м, руб]]*(1+PriceList[[#This Row],[Максимальная скидка]]) -> 404302.8 | AN14: =PriceList[[#This Row],[Цена за кв.м. в CRM]]*PriceList[[#This Row],[Площадь, кв.м]] -> 11821814 | AO14: 6000 | AP14: =PriceList[[#This Row],[Цена за кв.м. в CRM]]+PriceList[[#This Row],[Бронь]] -> 410302.8 | AQ14: =PriceList[[#This Row],[Цена за кв.м. в сайт]]*PriceList[[#This Row],[Площадь, кв.м]] -> 11997254 | AR14: =B14 -> С1-109 | AS14: =H14 -> Ст | AT14: =G14 -> 29.24 | AU14: =PriceList[[#This Row],[Цена за кв.м. в CRM]] -> 404302.8 | AV14: =AK14 -> Резерв | AZ14: =(PriceList[[#This Row],[Цена за кв.м. в сайт]])+$AZ$1 -> 410802.8 | BA14: =AZ14*PriceList[[#This Row],[Площадь, кв.м]] -> 12011874 | BB14: =BA14-PriceList[[#This Row],[Стоимость, руб для сбронированием]] -> 14620 | BD14: =MROUND(AZ14,100) -> 410800 | BE14: =BD14*PriceList[[#This Row],[Площадь, кв.м]] -> 12011792 | BG14: =BE14-$BG$1*PriceList[[#This Row],[Площадь, кв.м]] -> 11836352 | BH14: =BE14-BG14 -> 175440 | BI14: =BG14/PriceList[[#This Row],[Площадь, кв.м]] -> 404800 | BJ14: =BH14/BG14 -> 0.014822134
A15: 11 | B15: С1-11 | C15: 11 | D15: С1 | E15: 1 | F15: 11 | G15: 49.81 | H15: Ст | I15: Ст | J15: 10.87 | K15: =ROUND(J15*0.3,2) -> 3.26 | L15: =G15-J15 -> 38.94 | M15: =L15+K15 -> 42.2 | N15: XL | O15: Линейная | P15: Правильная | Q15: Зона 1 | R15: Двор северо-восток | S15: Двор | T15: Около/над входной группой | U15: 13 | V15: =IFERROR(VLOOKUP(H15,'Коэфф для прайса 1 оч'!$A$3:$C$6,3,0),"") -> 327000 | W15: =IFERROR(VLOOKUP(E15,'Коэфф для прайса 1 оч'!$A$10:$C$23,3,0),"") -> -0.045 | X15: =IFERROR(VLOOKUP(N15,'Коэфф для прайса 1 оч'!$E$25:$F$30,2,0),"") -> -0.02 | Y15: =IFERROR(VLOOKUP(O15,'Коэфф для прайса 1 оч'!$E$32:$F$34,2,0),"") -> 0 | Z15: =IFERROR(VLOOKUP(P15,'Коэфф для прайса 1 оч'!$E$36:$F$38,2,0),"") -> 0.03 | AA15: =IFERROR(VLOOKUP(Q15,'Коэфф для прайса 1 оч'!$E$40:$F$43,2,0),"") -> 0.005 | AB15: =IFERROR(VLOOKUP(R15,'Коэфф для прайса 1 оч'!$E$45:$F$59,2,0),"") -> -0.01 | AC15: =IFERROR(VLOOKUP(T15,'Коэфф для прайса 1 оч'!$E$61:$F$67,2,0),"") -> -0.01 | AD15: =IFERROR(VLOOKUP(U15,'Коэфф для прайса 1 оч'!$E$69:$F$82,2,0),"") -> 0.013 | AE15: =IFERROR(VLOOKUP(PriceList[[#This Row],[Корпус]],'Коэфф для прайса 1 оч'!$I$10:$J$15,2,0),"") -> 0 | AF15: =ROUND(V15+(V15*SUM(W15:AE15)),2) -> 314901 | AG15: =AF15*G15 -> 15685219 | AH15: 0 | AI15: =AF15+AF15*AH15 -> 314901 | AJ15: =AI15*G15 -> 15685219 | AK15: Резерв | AL15: 0.1 | AM15: =PriceList[[#This Row],[ИТОГ Цена за кв.м, руб]]*(1+PriceList[[#This Row],[Максимальная скидка]]) -> 346391.1 | AN15: =PriceList[[#This Row],[Цена за кв.м. в CRM]]*PriceList[[#This Row],[Площадь, кв.м]] -> 17253741 | AO15: 6000 | AP15: =PriceList[[#This Row],[Цена за кв.м. в CRM]]+PriceList[[#This Row],[Бронь]] -> 352391.1 | AQ15: =PriceList[[#This Row],[Цена за кв.м. в сайт]]*PriceList[[#This Row],[Площадь, кв.м]] -> 17552601 | AR15: =B15 -> С1-11 | AS15: =H15 -> Ст | AT15: =G15 -> 49.81 | AU15: =PriceList[[#This Row],[Цена за кв.м. в CRM]] -> 346391.1 | AV15: =AK15 -> Резерв | AZ15: =(PriceList[[#This Row],[Цена за кв.м. в сайт]])+$AZ$1 -> 352891.1 | BA15: =AZ15*PriceList[[#This Row],[Площадь, кв.м]] -> 17577506 | BB15: =BA15-PriceList[[#This Row],[Стоимость, руб для сбронированием]] -> 24905 | BD15: =MROUND(AZ15,100) -> 352900 | BE15: =BD15*PriceList[[#This Row],[Площадь, кв.м]] -> 17577949 | BG15: =BE15-$BG$1*PriceList[[#This Row],[Площадь, кв.м]] -> 17279089 | BH15: =BE15-BG15 -> 298860 | BI15: =BG15/PriceList[[#This Row],[Площадь, кв.м]] -> 346900 | BJ15: =BH15/BG15 -> 0.017296051
A16: 110 | B16: С1-110 | C16: 110 | D16: С1 | E16: 4 | F16: 15 | G16: 53.23 | H16: 1К | I16: 1АЕ | J16: 4.76 | K16: =ROUND(J16*0.3,2) -> 1.43 | L16: =G16-J16 -> 48.47 | M16: =L16+K16 -> 49.9 | N16: L | O16: Линейная | P16: Правильная | Q16: Зона 2 | R16: Море | S16: Море | T16: Стандарт | U16: 42 | V16: =IFERROR(VLOOKUP(H16,'Коэфф для прайса 1 оч'!$A$3:$C$6,3,0),"") -> 313920 | W16: =IFERROR(VLOOKUP(E16,'Коэфф для прайса 1 оч'!$A$10:$C$23,3,0),"") -> 0 | X16: =IFERROR(VLOOKUP(N16,'Коэфф для прайса 1 оч'!$E$25:$F$30,2,0),"") -> -0.01 | Y16: =IFERROR(VLOOKUP(O16,'Коэфф для прайса 1 оч'!$E$32:$F$34,2,0),"") -> 0 | Z16: =IFERROR(VLOOKUP(P16,'Коэфф для прайса 1 оч'!$E$36:$F$38,2,0),"") -> 0.03 | AA16: =IFERROR(VLOOKUP(Q16,'Коэфф для прайса 1 оч'!$E$40:$F$43,2,0),"") -> 0 | AB16: =IFERROR(VLOOKUP(R16,'Коэфф для прайса 1 оч'!$E$45:$F$59,2,0),"") -> 0.07 | AC16: =IFERROR(VLOOKUP(T16,'Коэфф для прайса 1 оч'!$E$61:$F$67,2,0),"") -> 0 | AD16: =IFERROR(VLOOKUP(U16,'Коэфф для прайса 1 оч'!$E$69:$F$82,2,0),"") -> -0.016 | AE16: =IFERROR(VLOOKUP(PriceList[[#This Row],[Корпус]],'Коэфф для прайса 1 оч'!$I$10:$J$15,2,0),"") -> 0 | AF16: =ROUND(V16+(V16*SUM(W16:AE16)),2) -> 337150.08 | AG16: =AF16*G16 -> 17946499 | AH16: 0 | AI16: =AF16+AF16*AH16 -> 337150.08 | AJ16: =AI16*G16 -> 17946499 | AK16: Резерв | AL16: 0.1 | AM16: =PriceList[[#This Row],[ИТОГ Цена за кв.м, руб]]*(1+PriceList[[#This Row],[Максимальная скидка]]) -> 370865.09 | AN16: =PriceList[[#This Row],[Цена за кв.м. в CRM]]*PriceList[[#This Row],[Площадь, кв.м]] -> 19741149 | AO16: 6000 | AP16: =PriceList[[#This Row],[Цена за кв.м. в CRM]]+PriceList[[#This Row],[Бронь]] -> 376865.09 | AQ16: =PriceList[[#This Row],[Цена за кв.м. в сайт]]*PriceList[[#This Row],[Площадь, кв.м]] -> 20060529 | AR16: =B16 -> С1-110 | AS16: =H16 -> 1К | AT16: =G16 -> 53.23 | AU16: =PriceList[[#This Row],[Цена за кв.м. в CRM]] -> 370865.09 | AV16: =AK16 -> Резерв | AZ16: =(PriceList[[#This Row],[Цена за кв.м. в сайт]])+$AZ$1 -> 377365.09 | BA16: =AZ16*PriceList[[#This Row],[Площадь, кв.м]] -> 20087144 | BB16: =BA16-PriceList[[#This Row],[Стоимость, руб для сбронированием]] -> 26615 | BD16: =MROUND(AZ16,100) -> 377400 | BE16: =BD16*PriceList[[#This Row],[Площадь, кв.м]] -> 20089002 | BG16: =BE16-$BG$1*PriceList[[#This Row],[Площадь, кв.м]] -> 19769622 | BH16: =BE16-BG16 -> 319380 | BI16: =BG16/PriceList[[#This Row],[Площадь, кв.м]] -> 371400 | BJ16: =BH16/BG16 -> 0.016155089
A17: 111 | B17: С1-111 | C17: 111 | D17: С1 | E17: 4 | F17: 16 | G17: 30.71 | H17: Ст | I17: Ст | J17: 5.97 | K17: =ROUND(J17*0.3,2) -> 1.79 | L17: =G17-J17 -> 24.74 | M17: =L17+K17 -> 26.53 | N17: S | O17: Линейная | P17: Правильная | Q17: Зона 1 | R17: Море | S17: Море | T17: Стандарт | U17: 42 | V17: =IFERROR(VLOOKUP(H17,'Коэфф для прайса 1 оч'!$A$3:$C$6,3,0),"") -> 327000 | W17: =IFERROR(VLOOKUP(E17,'Коэфф для прайса 1 оч'!$A$10:$C$23,3,0),"") -> 0 | X17: =IFERROR(VLOOKUP(N17,'Коэфф для прайса 1 оч'!$E$25:$F$30,2,0),"") -> 0.04 | Y17: =IFERROR(VLOOKUP(O17,'Коэфф для прайса 1 оч'!$E$32:$F$34,2,0),"") -> 0 | Z17: =IFERROR(VLOOKUP(P17,'Коэфф для прайса 1 оч'!$E$36:$F$38,2,0),"") -> 0.03 | AA17: =IFERROR(VLOOKUP(Q17,'Коэфф для прайса 1 оч'!$E$40:$F$43,2,0),"") -> 0.005 | AB17: =IFERROR(VLOOKUP(R17,'Коэфф для прайса 1 оч'!$E$45:$F$59,2,0),"") -> 0.07 | AC17: =IFERROR(VLOOKUP(T17,'Коэфф для прайса 1 оч'!$E$61:$F$67,2,0),"") -> 0 | AD17: =IFERROR(VLOOKUP(U17,'Коэфф для прайса 1 оч'!$E$69:$F$82,2,0),"") -> -0.016 | AE17: =IFERROR(VLOOKUP(PriceList[[#This Row],[Корпус]],'Коэфф для прайса 1 оч'!$I$10:$J$15,2,0),"") -> 0 | AF17: =ROUND(V17+(V17*SUM(W17:AE17)),2) -> 369183 | AG17: =AF17*G17 -> 11337610 | AH17: 0 | AI17: =AF17+AF17*AH17 -> 369183 | AJ17: =AI17*G17 -> 11337610 | AK17: Резерв | AL17: 0.1 | AM17: =PriceList[[#This Row],[ИТОГ Цена за кв.м, руб]]*(1+PriceList[[#This Row],[Максимальная скидка]]) -> 406101.3 | AN17: =PriceList[[#This Row],[Цена за кв.м. в CRM]]*PriceList[[#This Row],[Площадь, кв.м]] -> 12471371 | AO17: 6000 | AP17: =PriceList[[#This Row],[Цена за кв.м. в CRM]]+PriceList[[#This Row],[Бронь]] -> 412101.3 | AQ17: =PriceList[[#This Row],[Цена за кв.м. в сайт]]*PriceList[[#This Row],[Площадь, кв.м]] -> 12655631 | AR17: =B17 -> С1-111 | AS17: =H17 -> Ст | AT17: =G17 -> 30.71 | AU17: =PriceList[[#This Row],[Цена за кв.м. в CRM]] -> 406101.3 | AV17: =AK17 -> Резерв | AZ17: =(PriceList[[#This Row],[Цена за кв.м. в сайт]])+$AZ$1 -> 412601.3 | BA17: =AZ17*PriceList[[#This Row],[Площадь, кв.м]] -> 12670986 | BB17: =BA17-PriceList[[#This Row],[Стоимость, руб для сбронированием]] -> 15355 | BD17: =MROUND(AZ17,100) -> 412600 | BE17: =BD17*PriceList[[#This Row],[Площадь, кв.м]] -> 12670946 | BG17: =BE17-$BG$1*PriceList[[#This Row],[Площадь, кв.м]] -> 12486686 | BH17: =BE17-BG17 -> 184260 | BI17: =BG17/PriceList[[#This Row],[Площадь, кв.м]] -> 406600 | BJ17: =BH17/BG17 -> 0.014756517
A18: 112 | B18: С1-112 | C18: 112 | D18: С1 | E18: 4 | F18: 17 | G18: 30.47 | H18: Ст | I18: Ст | J18: 5.73 | K18: =ROUND(J18*0.3,2) -> 1.72 | L18: =G18-J18 -> 24.74 | M18: =L18+K18 -> 26.46 | N18: S | O18: Линейная | P18: Правильная | Q18: Зона 1 | R18: Море | S18: Море | T18: Стандарт | U18: 42 | V18: =IFERROR(VLOOKUP(H18,'Коэфф для прайса 1 оч'!$A$3:$C$6,3,0),"") -> 327000 | W18: =IFERROR(VLOOKUP(E18,'Коэфф для прайса 1 оч'!$A$10:$C$23,3,0),"") -> 0 | X18: =IFERROR(VLOOKUP(N18,'Коэфф для прайса 1 оч'!$E$25:$F$30,2,0),"") -> 0.04 | Y18: =IFERROR(VLOOKUP(O18,'Коэфф для прайса 1 оч'!$E$32:$F$34,2,0),"") -> 0 | Z18: =IFERROR(VLOOKUP(P18,'Коэфф для прайса 1 оч'!$E$36:$F$38,2,0),"") -> 0.03 | AA18: =IFERROR(VLOOKUP(Q18,'Коэфф для прайса 1 оч'!$E$40:$F$43,2,0),"") -> 0.005 | AB18: =IFERROR(VLOOKUP(R18,'Коэфф для прайса 1 оч'!$E$45:$F$59,2,0),"") -> 0.07 | AC18: =IFERROR(VLOOKUP(T18,'Коэфф для прайса 1 оч'!$E$61:$F$67,2,0),"") -> 0 | AD18: =IFERROR(VLOOKUP(U18,'Коэфф для прайса 1 оч'!$E$69:$F$82,2,0),"") -> -0.016 | AE18: =IFERROR(VLOOKUP(PriceList[[#This Row],[Корпус]],'Коэфф для прайса 1 оч'!$I$10:$J$15,2,0),"") -> 0 | AF18: =ROUND(V18+(V18*SUM(W18:AE18)),2) -> 369183 | AG18: =AF18*G18 -> 11249006 | AH18: 0 | AI18: =AF18+AF18*AH18 -> 369183 | AJ18: =AI18*G18 -> 11249006 | AK18: Резерв | AL18: 0.1 | AM18: =PriceList[[#This Row],[ИТОГ Цена за кв.м, руб]]*(1+PriceList[[#This Row],[Максимальная скидка]]) -> 406101.3 | AN18: =PriceList[[#This Row],[Цена за кв.м. в CRM]]*PriceList[[#This Row],[Площадь, кв.м]] -> 12373907 | AO18: 6000 | AP18: =PriceList[[#This Row],[Цена за кв.м. в CRM]]+PriceList[[#This Row],[Бронь]] -> 412101.3 | AQ18: =PriceList[[#This Row],[Цена за кв.м. в сайт]]*PriceList[[#This Row],[Площадь, кв.м]] -> 12556727 | AR18: =B18 -> С1-112 | AS18: =H18 -> Ст | AT18: =G18 -> 30.47 | AU18: =PriceList[[#This Row],[Цена за кв.м. в CRM]] -> 406101.3 | AV18: =AK18 -> Резерв | AZ18: =(PriceList[[#This Row],[Цена за кв.м. в сайт]])+$AZ$1 -> 412601.3 | BA18: =AZ18*PriceList[[#This Row],[Площадь, кв.м]] -> 12571962 | BB18: =BA18-PriceList[[#This Row],[Стоимость, руб для сбронированием]] -> 15235 | BD18: =MROUND(AZ18,100) -> 412600 | BE18: =BD18*PriceList[[#This Row],[Площадь, кв.м]] -> 12571922 | BG18: =BE18-$BG$1*PriceList[[#This Row],[Площадь, кв.м]] -> 12389102 | BH18: =BE18-BG18 -> 182820 | BI18: =BG18/PriceList[[#This Row],[Площадь, кв.м]] -> 406600 | BJ18: =BH18/BG18 -> 0.014756517
A19: 113 | B19: С1-113 | C19: 113 | D19: С1 | E19: 4 | F19: 18 | G19: 43.85 | H19: Ст | I19: Ст | J19: 7.62 | K19: =ROUND(J19*0.3,2) -> 2.29 | L19: =G19-J19 -> 36.23 | M19: =L19+K19 -> 38.52 | N19: L | O19: Линейная | P19: Правильная | Q19: Зона 1 | R19: Море | S19: Море | T19: Стандарт | U19: 42 | V19: =IFERROR(VLOOKUP(H19,'Коэфф для прайса 1 оч'!$A$3:$C$6,3,0),"") -> 327000 | W19: =IFERROR(VLOOKUP(E19,'Коэфф для прайса 1 оч'!$A$10:$C$23,3,0),"") -> 0 | X19: =IFERROR(VLOOKUP(N19,'Коэфф для прайса 1 оч'!$E$25:$F$30,2,0),"") -> -0.01 | Y19: =IFERROR(VLOOKUP(O19,'Коэфф для прайса 1 оч'!$E$32:$F$34,2,0),"") -> 0 | Z19: =IFERROR(VLOOKUP(P19,'Коэфф для прайса 1 оч'!$E$36:$F$38,2,0),"") -> 0.03 | AA19: =IFERROR(VLOOKUP(Q19,'Коэфф для прайса 1 оч'!$E$40:$F$43,2,0),"") -> 0.005 | AB19: =IFERROR(VLOOKUP(R19,'Коэфф для прайса 1 оч'!$E$45:$F$59,2,0),"") -> 0.07 | AC19: =IFERROR(VLOOKUP(T19,'Коэфф для прайса 1 оч'!$E$61:$F$67,2,0),"") -> 0 | AD19: =IFERROR(VLOOKUP(U19,'Коэфф для прайса 1 оч'!$E$69:$F$82,2,0),"") -> -0.016 | AE19: =IFERROR(VLOOKUP(PriceList[[#This Row],[Корпус]],'Коэфф для прайса 1 оч'!$I$10:$J$15,2,0),"") -> 0 | AF19: =ROUND(V19+(V19*SUM(W19:AE19)),2) -> 352833 | AG19: =AF19*G19 -> 15471727 | AH19: 0 | AI19: =AF19+AF19*AH19 -> 352833 | AJ19: =AI19*G19 -> 15471727 | AK19: Резерв | AL19: 0.1 | AM19: =PriceList[[#This Row],[ИТОГ Цена за кв.м, руб]]*(1+PriceList[[#This Row],[Максимальная скидка]]) -> 388116.3 | AN19: =PriceList[[#This Row],[Цена за кв.м. в CRM]]*PriceList[[#This Row],[Площадь, кв.м]] -> 17018900 | AO19: 6000 | AP19: =PriceList[[#This Row],[Цена за кв.м. в CRM]]+PriceList[[#This Row],[Бронь]] -> 394116.3 | AQ19: =PriceList[[#This Row],[Цена за кв.м. в сайт]]*PriceList[[#This Row],[Площадь, кв.м]] -> 17282000 | AR19: =B19 -> С1-113 | AS19: =H19 -> Ст | AT19: =G19 -> 43.85 | AU19: =PriceList[[#This Row],[Цена за кв.м. в CRM]] -> 388116.3 | AV19: =AK19 -> Резерв | AZ19: =(PriceList[[#This Row],[Цена за кв.м. в сайт]])+$AZ$1 -> 394616.3 | BA19: =AZ19*PriceList[[#This Row],[Площадь, кв.м]] -> 17303925 | BB19: =BA19-PriceList[[#This Row],[Стоимость, руб для сбронированием]] -> 21925 | BD19: =MROUND(AZ19,100) -> 394600 | BE19: =BD19*PriceList[[#This Row],[Площадь, кв.м]] -> 17303210 | BG19: =BE19-$BG$1*PriceList[[#This Row],[Площадь, кв.м]] -> 17040110 | BH19: =BE19-BG19 -> 263100 | BI19: =BG19/PriceList[[#This Row],[Площадь, кв.м]] -> 388600 | BJ19: =BH19/BG19 -> 0.015440041
... A328: 99 | B328: С1-99 | C328: 99 | D328: С1 | E328: 4 | F328: 4 | G328: 29.24 | H328: Ст | I328: Ст | J328: 4.25 | K328: =ROUND(J328*0.3,2) -> 1.28 | L328: =G328-J328 -> 24.99 | M328: =L328+K328 -> 26.27 | N328: S | O328: Линейная | P328: Правильная | Q328: Зона 2 | R328: Двор север | S328: Двор | T328: Стандарт | U328: 42 | V328: =IFERROR(VLOOKUP(H328,'Коэфф для прайса 1 оч'!$A$3:$C$6,3,0),"") -> 327000 | W328: =IFERROR(VLOOKUP(E328,'Коэфф для прайса 1 оч'!$A$10:$C$23,3,0),"") -> 0 | X328: =IFERROR(VLOOKUP(N328,'Коэфф для прайса 1 оч'!$E$25:$F$30,2,0),"") -> 0.04 | Y328: =IFERROR(VLOOKUP(O328,'Коэфф для прайса 1 оч'!$E$32:$F$34,2,0),"") -> 0 | Z328: =IFERROR(VLOOKUP(P328,'Коэфф для прайса 1 оч'!$E$36:$F$38,2,0),"") -> 0.03 | AA328: =IFERROR(VLOOKUP(Q328,'Коэфф для прайса 1 оч'!$E$40:$F$43,2,0),"") -> 0 | AB328: =IFERROR(VLOOKUP(R328,'Коэфф для прайса 1 оч'!$E$45:$F$59,2,0),"") -> -0.015 | AC328: =IFERROR(VLOOKUP(T328,'Коэфф для прайса 1 оч'!$E$61:$F$67,2,0),"") -> 0 | AD328: =IFERROR(VLOOKUP(U328,'Коэфф для прайса 1 оч'!$E$69:$F$82,2,0),"") -> -0.016 | AE328: =IFERROR(VLOOKUP(PriceList[[#This Row],[Корпус]],'Коэфф для прайса 1 оч'!$I$10:$J$15,2,0),"") -> 0 | AF328: =ROUND(V328+(V328*SUM(W328:AE328)),2) -> 339753 | AG328: =AF328*G328 -> 9934377.7 | AH328: 0 | AI328: =AF328+AF328*AH328 -> 339753 | AJ328: =AI328*G328 -> 9934377.7 | AK328: Резерв | AL328: 0.1 | AM328: =PriceList[[#This Row],[ИТОГ Цена за кв.м, руб]]*(1+PriceList[[#This Row],[Максимальная скидка]]) -> 373728.3 | AN328: =PriceList[[#This Row],[Цена за кв.м. в CRM]]*PriceList[[#This Row],[Площадь, кв.м]] -> 10927815 | AO328: 6000 | AP328: =PriceList[[#This Row],[Цена за кв.м. в CRM]]+PriceList[[#This Row],[Бронь]] -> 379728.3 | AQ328: =PriceList[[#This Row],[Цена за кв.м. в сайт]]*PriceList[[#This Row],[Площадь, кв.м]] -> 11103255 | AR328: =B328 -> С1-99 | AS328: =H328 -> Ст | AT328: =G328 -> 29.24 | AU328: =PriceList[[#This Row],[Цена за кв.м. в CRM]] -> 373728.3 | AV328: =AK328 -> Резерв | AZ328: =(PriceList[[#This Row],[Цена за кв.м. в сайт]])+$AZ$1 -> 380228.3 | BA328: =AZ328*PriceList[[#This Row],[Площадь, кв.м]] -> 11117875 | BB328: =BA328-PriceList[[#This Row],[Стоимость, руб для сбронированием]] -> 14620 | BD328: =MROUND(AZ328,100) -> 380200 | BE328: =BD328*PriceList[[#This Row],[Площадь, кв.м]] -> 11117048 | BG328: =BE328-$BG$1*PriceList[[#This Row],[Площадь, кв.м]] -> 10941608 | BH328: =BE328-BG328 -> 175440 | BI328: =BG328/PriceList[[#This Row],[Площадь, кв.м]] -> 374200 | BJ328: =BH328/BG328 -> 0.016034206
A329: 327 | B329: С2-1 | C329: 1 | D329: С2 | E329: 1 | F329: 1 | G329: 37.48 | H329: Ст | I329: Ст | J329: 7.24 | K329: =ROUND(J329*0.3,2) -> 2.17 | L329: =G329-J329 -> 30.24 | M329: =L329+K329 -> 32.41 | N329: M | O329: Линейная | P329: Правильная | Q329: Зона 1 | R329: Улица северо-восток | S329: ул.Морская | T329: Около/над входной группой | U329: 34 | V329: =IFERROR(VLOOKUP(H329,'Коэфф для прайса 1 оч'!$A$3:$C$6,3,0),"") -> 327000 | W329: =IFERROR(VLOOKUP(E329,'Коэфф для прайса 1 оч'!$A$10:$C$23,3,0),"") -> -0.045 | X329: =IFERROR(VLOOKUP(N329,'Коэфф для прайса 1 оч'!$E$25:$F$30,2,0),"") -> 0 | Y329: =IFERROR(VLOOKUP(O329,'Коэфф для прайса 1 оч'!$E$32:$F$34,2,0),"") -> 0 | Z329: =IFERROR(VLOOKUP(P329,'Коэфф для прайса 1 оч'!$E$36:$F$38,2,0),"") -> 0.03 | AA329: =IFERROR(VLOOKUP(Q329,'Коэфф для прайса 1 оч'!$E$40:$F$43,2,0),"") -> 0.005 | AB329: =IFERROR(VLOOKUP(R329,'Коэфф для прайса 1 оч'!$E$45:$F$59,2,0),"") -> -0.02 | AC329: =IFERROR(VLOOKUP(T329,'Коэфф для прайса 1 оч'!$E$61:$F$67,2,0),"") -> -0.01 | AD329: =IFERROR(VLOOKUP(U329,'Коэфф для прайса 1 оч'!$E$69:$F$82,2,0),"") -> -0.008 | AE329: =IFERROR(VLOOKUP(PriceList[[#This Row],[Корпус]],'Коэфф для прайса 1 оч'!$I$10:$J$15,2,0),"") -> 0.12 | AF329: =ROUND(V329+(V329*SUM(W329:AE329)),2) -> 350544 | AG329: =AF329*G329 -> 13138389 | AH329: 0 | AK329: Не для продажи | AL329: 0.1 | AM329: =PriceList[[#This Row],[ИТОГ Цена за кв.м, руб]]*(1+PriceList[[#This Row],[Максимальная скидка]]) -> 0 | AN329: =PriceList[[#This Row],[Цена за кв.м. в CRM]]*PriceList[[#This Row],[Площадь, кв.м]] -> 0 | AO329: 6000 | AP329: =PriceList[[#This Row],[Цена за кв.м. в CRM]]+PriceList[[#This Row],[Бронь]] -> 6000 | AQ329: =PriceList[[#This Row],[Цена за кв.м. в сайт]]*PriceList[[#This Row],[Площадь, кв.м]] -> 224880 | AR329: =B329 -> С2-1 | AS329: =H329 -> Ст | AT329: =G329 -> 37.48 | AU329: =PriceList[[#This Row],[Цена за кв.м. в CRM]] -> 0 | AV329: =AK329 -> Не для продажи | AW329: Детский центр | BD329: =MROUND(AZ329,100) -> 0 | BE329: =BD329*PriceList[[#This Row],[Площадь, кв.м]] -> 0 | BH329: =BE329-BG329 -> 0 | BI329: =BG329/PriceList[[#This Row],[Площадь, кв.м]] -> 0 | BJ329: =BH329/BG329 -> #DIV/0!
A330: 336 | B330: С2-10 | C330: 10 | D330: С2 | E330: 1 | F330: 10 | G330: 32.29 | H330: Ст | I330: Ст | J330: 7.55 | K330: =ROUND(J330*0.3,2) -> 2.27 | L330: =G330-J330 -> 24.74 | M330: =L330+K330 -> 27.01 | N330: S | O330: Линейная | P330: Правильная | Q330: Зона 1 | R330: Двор юго-запад | S330: Двор | T330: Стандарт | U330: 34 | V330: =IFERROR(VLOOKUP(H330,'Коэфф для прайса 1 оч'!$A$3:$C$6,3,0),"") -> 327000 | W330: =IFERROR(VLOOKUP(E330,'Коэфф для прайса 1 оч'!$A$10:$C$23,3,0),"") -> -0.045 | X330: =IFERROR(VLOOKUP(N330,'Коэфф для прайса 1 оч'!$E$25:$F$30,2,0),"") -> 0.04 | Y330: =IFERROR(VLOOKUP(O330,'Коэфф для прайса 1 оч'!$E$32:$F$34,2,0),"") -> 0 | Z330: =IFERROR(VLOOKUP(P330,'Коэфф для прайса 1 оч'!$E$36:$F$38,2,0),"") -> 0.03 | AA330: =IFERROR(VLOOKUP(Q330,'Коэфф для прайса 1 оч'!$E$40:$F$43,2,0),"") -> 0.005 | AB330: =IFERROR(VLOOKUP(R330,'Коэфф для прайса 1 оч'!$E$45:$F$59,2,0),"") -> 0.02 | AC330: =IFERROR(VLOOKUP(T330,'Коэфф для прайса 1 оч'!$E$61:$F$67,2,0),"") -> 0 | AD330: =IFERROR(VLOOKUP(U330,'Коэфф для прайса 1 оч'!$E$69:$F$82,2,0),"") -> -0.008 | AE330: =IFERROR(VLOOKUP(PriceList[[#This Row],[Корпус]],'Коэфф для прайса 1 оч'!$I$10:$J$15,2,0),"") -> 0.12 | AF330: =ROUND(V330+(V330*SUM(W330:AE330)),2) -> 379974 | AG330: =AF330*G330 -> 12269360 | AH330: 0 | AI330: =AF330+AF330*AH330 -> 379974 | AJ330: =AI330*G330 -> 12269360 | AK330: Резерв | AL330: 0.1 | AM330: =PriceList[[#This Row],[ИТОГ Цена за кв.м, руб]]*(1+PriceList[[#This Row],[Максимальная скидка]]) -> 417971.4 | AN330: =PriceList[[#This Row],[Цена за кв.м. в CRM]]*PriceList[[#This Row],[Площадь, кв.м]] -> 13496297 | AO330: 6000 | AP330: =PriceList[[#This Row],[Цена за кв.м. в CRM]]+PriceList[[#This Row],[Бронь]] -> 423971.4 | AQ330: =PriceList[[#This Row],[Цена за кв.м. в сайт]]*PriceList[[#This Row],[Площадь, кв.м]] -> 13690037 | AR330: =B330 -> С2-10 | AS330: =H330 -> Ст | AT330: =G330 -> 32.29 | AU330: =PriceList[[#This Row],[Цена за кв.м. в CRM]] -> 417971.4 | AV330: =AK330 -> Резерв | AZ330: =(PriceList[[#This Row],[Цена за кв.м. в сайт]])+$AZ$1 -> 424471.4 | BA330: =AZ330*PriceList[[#This Row],[Площадь, кв.м]] -> 13706182 | BB330: =BA330-PriceList[[#This Row],[Стоимость, руб для сбронированием]] -> 16145 | BD330: =MROUND(AZ330,100) -> 424500 | BE330: =BD330*PriceList[[#This Row],[Площадь, кв.м]] -> 13707105 | BG330: =BE330-$BG$1*PriceList[[#This Row],[Площадь, кв.м]] -> 13513365 | BH330: =BE330-BG330 -> 193740 | BI330: =BG330/PriceList[[#This Row],[Площадь, кв.м]] -> 418500 | BJ330: =BH330/BG330 -> 0.014336918 | BL330: =BI330-10%*BI330 -> 376650 | BM330: =BL330*G330 -> 12162028
A331: 426 | B331: С2-100 | C331: 100 | D331: С2 | E331: 3 | F331: 28 | G331: 29.27 | H331: Ст | I331: Ст | J331: 4.29 | K331: =ROUND(J331*0.3,2) -> 1.29 | L331: =G331-J331 -> 24.98 | M331: =L331+K331 -> 26.27 | N331: S | O331: Линейная | P331: Правильная | Q331: Зона 3 | R331: Озеро | S331: Озеро | T331: Стандарт | U331: 40 | V331: =IFERROR(VLOOKUP(H331,'Коэфф для прайса 1 оч'!$A$3:$C$6,3,0),"") -> 327000 | W331: =IFERROR(VLOOKUP(E331,'Коэфф для прайса 1 оч'!$A$10:$C$23,3,0),"") -> -0.005 | X331: =IFERROR(VLOOKUP(N331,'Коэфф для прайса 1 оч'!$E$25:$F$30,2,0),"") -> 0.04 | Y331: =IFERROR(VLOOKUP(O331,'Коэфф для прайса 1 оч'!$E$32:$F$34,2,0),"") -> 0 | Z331: =IFERROR(VLOOKUP(P331,'Коэфф для прайса 1 оч'!$E$36:$F$38,2,0),"") -> 0.03 | AA331: =IFERROR(VLOOKUP(Q331,'Коэфф для прайса 1 оч'!$E$40:$F$43,2,0),"") -> -0.005 | AB331: =IFERROR(VLOOKUP(R331,'Коэфф для прайса 1 оч'!$E$45:$F$59,2,0),"") -> 0.03 | AC331: =IFERROR(VLOOKUP(T331,'Коэфф для прайса 1 оч'!$E$61:$F$67,2,0),"") -> 0 | AD331: =IFERROR(VLOOKUP(U331,'Коэфф для прайса 1 оч'!$E$69:$F$82,2,0),"") -> -0.014 | AE331: =IFERROR(VLOOKUP(PriceList[[#This Row],[Корпус]],'Коэфф для прайса 1 оч'!$I$10:$J$15,2,0),"") -> 0.12 | AF331: =ROUND(V331+(V331*SUM(W331:AE331)),2) -> 391092 | AG331: =AF331*G331 -> 11447263 | AH331: 0 | AI331: =AF331+AF331*AH331 -> 391092 | AJ331: =AI331*G331 -> 11447263 | AK331: Резерв | AL331: 0.1 | AM331: =PriceList[[#This Row],[ИТОГ Цена за кв.м, руб]]*(1+PriceList[[#This Row],[Максимальная скидка]]) -> 430201.2 | AN331: =PriceList[[#This Row],[Цена за кв.м. в CRM]]*PriceList[[#This Row],[Площадь, кв.м]] -> 12591989 | AO331: 6000 | AP331: =PriceList[[#This Row],[Цена за кв.м. в CRM]]+PriceList[[#This Row],[Бронь]] -> 436201.2 | AQ331: =PriceList[[#This Row],[Цена за кв.м. в сайт]]*PriceList[[#This Row],[Площадь, кв.м]] -> 12767609 | AR331: =B331 -> С2-100 | AS331: =H331 -> Ст | AT331: =G331 -> 29.27 | AU331: =PriceList[[#This Row],[Цена за кв.м. в CRM]] -> 430201.2 | AV331: =AK331 -> Резерв | AZ331: =(PriceList[[#This Row],[Цена за кв.м. в сайт]])+$AZ$1 -> 436701.2 | BA331: =AZ331*PriceList[[#This Row],[Площадь, кв.м]] -> 12782244 | BB331: =BA331-PriceList[[#This Row],[Стоимость, руб для сбронированием]] -> 14635 | BD331: =MROUND(AZ331,100) -> 436700 | BE331: =BD331*PriceList[[#This Row],[Площадь, кв.м]] -> 12782209 | BG331: =BE331-$BG$1*PriceList[[#This Row],[Площадь, кв.м]] -> 12606589 | BH331: =BE331-BG331 -> 175620 | BI331: =BG331/PriceList[[#This Row],[Площадь, кв.м]] -> 430700 | BJ331: =BH331/BG331 -> 0.01393081 | BL331: =BI331-10%*BI331 -> 387630 | BM331: =BL331*G331 -> 11345930
A332: 427 | B332: С2-101 | C332: 101 | D332: С2 | E332: 3 | F332: 29 | G332: 29.27 | H332: Ст | I332: Ст | J332: 4.29 | K332: =ROUND(J332*0.3,2) -> 1.29 | L332: =G332-J332 -> 24.98 | M332: =L332+K332 -> 26.27 | N332: S | O332: Линейная | P332: Правильная | Q332: Зона 3 | R332: Озеро | S332: Озеро | T332: Стандарт | U332: 40 | V332: =IFERROR(VLOOKUP(H332,'Коэфф для прайса 1 оч'!$A$3:$C$6,3,0),"") -> 327000 | W332: =IFERROR(VLOOKUP(E332,'Коэфф для прайса 1 оч'!$A$10:$C$23,3,0),"") -> -0.005 | X332: =IFERROR(VLOOKUP(N332,'Коэфф для прайса 1 оч'!$E$25:$F$30,2,0),"") -> 0.04 | Y332: =IFERROR(VLOOKUP(O332,'Коэфф для прайса 1 оч'!$E$32:$F$34,2,0),"") -> 0 | Z332: =IFERROR(VLOOKUP(P332,'Коэфф для прайса 1 оч'!$E$36:$F$38,2,0),"") -> 0.03 | AA332: =IFERROR(VLOOKUP(Q332,'Коэфф для прайса 1 оч'!$E$40:$F$43,2,0),"") -> -0.005 | AB332: =IFERROR(VLOOKUP(R332,'Коэфф для прайса 1 оч'!$E$45:$F$59,2,0),"") -> 0.03 | AC332: =IFERROR(VLOOKUP(T332,'Коэфф для прайса 1 оч'!$E$61:$F$67,2,0),"") -> 0 | AD332: =IFERROR(VLOOKUP(U332,'Коэфф для прайса 1 оч'!$E$69:$F$82,2,0),"") -> -0.014 | AE332: =IFERROR(VLOOKUP(PriceList[[#This Row],[Корпус]],'Коэфф для прайса 1 оч'!$I$10:$J$15,2,0),"") -> 0.12 | AF332: =ROUND(V332+(V332*SUM(W332:AE332)),2) -> 391092 | AG332: =AF332*G332 -> 11447263 | AH332: 0 | AI332: =AF332+AF332*AH332 -> 391092 | AJ332: =AI332*G332 -> 11447263 | AK332: Резерв | AL332: 0.1 | AM332: =PriceList[[#This Row],[ИТОГ Цена за кв.м, руб]]*(1+PriceList[[#This Row],[Максимальная скидка]]) -> 430201.2 | AN332: =PriceList[[#This Row],[Цена за кв.м. в CRM]]*PriceList[[#This Row],[Площадь, кв.м]] -> 12591989 | AO332: 6000 | AP332: =PriceList[[#This Row],[Цена за кв.м. в CRM]]+PriceList[[#This Row],[Бронь]] -> 436201.2 | AQ332: =PriceList[[#This Row],[Цена за кв.м. в сайт]]*PriceList[[#This Row],[Площадь, кв.м]] -> 12767609 | AR332: =B332 -> С2-101 | AS332: =H332 -> Ст | AT332: =G332 -> 29.27 | AU332: =PriceList[[#This Row],[Цена за кв.м. в CRM]] -> 430201.2 | AV332: =AK332 -> Резерв | AZ332: =(PriceList[[#This Row],[Цена за кв.м. в сайт]])+$AZ$1 -> 436701.2 | BA332: =AZ332*PriceList[[#This Row],[Площадь, кв.м]] -> 12782244 | BB332: =BA332-PriceList[[#This Row],[Стоимость, руб для сбронированием]] -> 14635 | BD332: =MROUND(AZ332,100) -> 436700 | BE332: =BD332*PriceList[[#This Row],[Площадь, кв.м]] -> 12782209 | BG332: =BE332-$BG$1*PriceList[[#This Row],[Площадь, кв.м]] -> 12606589 | BH332: =BE332-BG332 -> 175620 | BI332: =BG332/PriceList[[#This Row],[Площадь, кв.м]] -> 430700 | BJ332: =BH332/BG332 -> 0.01393081 | BL332: =BI332-10%*BI332 -> 387630 | BM332: =BL332*G332 -> 11345930
A333: 428 | B333: С2-102 | C333: 102 | D333: С2 | E333: 3 | F333: 30 | G333: 29.46 | H333: Ст | I333: Ст | J333: 4.66 | K333: =ROUND(J333*0.3,2) -> 1.4 | L333: =G333-J333 -> 24.8 | M333: =L333+K333 -> 26.2 | N333: S | O333: Линейная | P333: Правильная | Q333: Зона 3 | R333: Озеро | S333: Озеро | T333: Стандарт | U333: 40 | V333: =IFERROR(VLOOKUP(H333,'Коэфф для прайса 1 оч'!$A$3:$C$6,3,0),"") -> 327000 | W333: =IFERROR(VLOOKUP(E333,'Коэфф для прайса 1 оч'!$A$10:$C$23,3,0),"") -> -0.005 | X333: =IFERROR(VLOOKUP(N333,'Коэфф для прайса 1 оч'!$E$25:$F$30,2,0),"") -> 0.04 | Y333: =IFERROR(VLOOKUP(O333,'Коэфф для прайса 1 оч'!$E$32:$F$34,2,0),"") -> 0 | Z333: =IFERROR(VLOOKUP(P333,'Коэфф для прайса 1 оч'!$E$36:$F$38,2,0),"") -> 0.03 | AA333: =IFERROR(VLOOKUP(Q333,'Коэфф для прайса 1 оч'!$E$40:$F$43,2,0),"") -> -0.005 | AB333: =IFERROR(VLOOKUP(R333,'Коэфф для прайса 1 оч'!$E$45:$F$59,2,0),"") -> 0.03 | AC333: =IFERROR(VLOOKUP(T333,'Коэфф для прайса 1 оч'!$E$61:$F$67,2,0),"") -> 0 | AD333: =IFERROR(VLOOKUP(U333,'Коэфф для прайса 1 оч'!$E$69:$F$82,2,0),"") -> -0.014 | AE333: =IFERROR(VLOOKUP(PriceList[[#This Row],[Корпус]],'Коэфф для прайса 1 оч'!$I$10:$J$15,2,0),"") -> 0.12 | AF333: =ROUND(V333+(V333*SUM(W333:AE333)),2) -> 391092 | AG333: =AF333*G333 -> 11521570 | AH333: 0 | AI333: =AF333+AF333*AH333 -> 391092 | AJ333: =AI333*G333 -> 11521570 | AK333: Резерв | AL333: 0.1 | AM333: =PriceList[[#This Row],[ИТОГ Цена за кв.м, руб]]*(1+PriceList[[#This Row],[Максимальная скидка]]) -> 430201.2 | AN333: =PriceList[[#This Row],[Цена за кв.м. в CRM]]*PriceList[[#This Row],[Площадь, кв.м]] -> 12673727 | AO333: 6000 | AP333: =PriceList[[#This Row],[Цена за кв.м. в CRM]]+PriceList[[#This Row],[Бронь]] -> 436201.2 | AQ333: =PriceList[[#This Row],[Цена за кв.м. в сайт]]*PriceList[[#This Row],[Площадь, кв.м]] -> 12850487 | AR333: =B333 -> С2-102 | AS333: =H333 -> Ст | AT333: =G333 -> 29.46 | AU333: =PriceList[[#This Row],[Цена за кв.м. в CRM]] -> 430201.2 | AV333: =AK333 -> Резерв | AZ333: =(PriceList[[#This Row],[Цена за кв.м. в сайт]])+$AZ$1 -> 436701.2 | BA333: =AZ333*PriceList[[#This Row],[Площадь, кв.м]] -> 12865217 | BB333: =BA333-PriceList[[#This Row],[Стоимость, руб для сбронированием]] -> 14730 | BD333: =MROUND(AZ333,100) -> 436700 | BE333: =BD333*PriceList[[#This Row],[Площадь, кв.м]] -> 12865182 | BG333: =BE333-$BG$1*PriceList[[#This Row],[Площадь, кв.м]] -> 12688422 | BH333: =BE333-BG333 -> 176760 | BI333: =BG333/PriceList[[#This Row],[Площадь, кв.м]] -> 430700 | BJ333: =BH333/BG333 -> 0.01393081 | BL333: =BI333-10%*BI333 -> 387630 | BM333: =BL333*G333 -> 11419580
A334: 429 | B334: С2-103 | C334: 103 | D334: С2 | E334: 3 | F334: 31 | G334: 34.43 | H334: Ст | I334: Ст | J334: 5.49 | K334: =ROUND(J334*0.3,2) -> 1.65 | L334: =G334-J334 -> 28.94 | M334: =L334+K334 -> 30.59 | N334: M | O334: Линейная | P334: Правильная | Q334: Зона 3 | R334: Озеро | S334: Озеро | T334: Стандарт | U334: 40 | V334: =IFERROR(VLOOKUP(H334,'Коэфф для прайса 1 оч'!$A$3:$C$6,3,0),"") -> 327000 | W334: =IFERROR(VLOOKUP(E334,'Коэфф для прайса 1 оч'!$A$10:$C$23,3,0),"") -> -0.005 | X334: =IFERROR(VLOOKUP(N334,'Коэфф для прайса 1 оч'!$E$25:$F$30,2,0),"") -> 0 | Y334: =IFERROR(VLOOKUP(O334,'Коэфф для прайса 1 оч'!$E$32:$F$34,2,0),"") -> 0 | Z334: =IFERROR(VLOOKUP(P334,'Коэфф для прайса 1 оч'!$E$36:$F$38,2,0),"") -> 0.03 | AA334: =IFERROR(VLOOKUP(Q334,'Коэфф для прайса 1 оч'!$E$40:$F$43,2,0),"") -> -0.005 | AB334: =IFERROR(VLOOKUP(R334,'Коэфф для прайса 1 оч'!$E$45:$F$59,2,0),"") -> 0.03 | AC334: =IFERROR(VLOOKUP(T334,'Коэфф для прайса 1 оч'!$E$61:$F$67,2,0),"") -> 0 | AD334: =IFERROR(VLOOKUP(U334,'Коэфф для прайса 1 оч'!$E$69:$F$82,2,0),"") -> -0.014 | AE334: =IFERROR(VLOOKUP(PriceList[[#This Row],[Корпус]],'Коэфф для прайса 1 оч'!$I$10:$J$15,2,0),"") -> 0.12 | AF334: =ROUND(V334+(V334*SUM(W334:AE334)),2) -> 378012 | AG334: =AF334*G334 -> 13014953 | AH334: 0 | AI334: =AF334+AF334*AH334 -> 378012 | AJ334: =AI334*G334 -> 13014953 | AK334: Резерв | AL334: 0.1 | AM334: =PriceList[[#This Row],[ИТОГ Цена за кв.м, руб]]*(1+PriceList[[#This Row],[Максимальная скидка]]) -> 415813.2 | AN334: =PriceList[[#This Row],[Цена за кв.м. в CRM]]*PriceList[[#This Row],[Площадь, кв.м]] -> 14316448 | AO334: 6000 | AP334: =PriceList[[#This Row],[Цена за кв.м. в CRM]]+PriceList[[#This Row],[Бронь]] -> 421813.2 | AQ334: =PriceList[[#This Row],[Цена за кв.м. в сайт]]*PriceList[[#This Row],[Площадь, кв.м]] -> 14523028 | AR334: =B334 -> С2-103 | AS334: =H334 -> Ст | AT334: =G334 -> 34.43 | AU334: =PriceList[[#This Row],[Цена за кв.м. в CRM]] -> 415813.2 | AV334: =AK334 -> Резерв | AZ334: =(PriceList[[#This Row],[Цена за кв.м. в сайт]])+$AZ$1 -> 422313.2 | BA334: =AZ334*PriceList[[#This Row],[Площадь, кв.м]] -> 14540243 | BB334: =BA334-PriceList[[#This Row],[Стоимость, руб для сбронированием]] -> 17215 | BD334: =MROUND(AZ334,100) -> 422300 | BE334: =BD334*PriceList[[#This Row],[Площадь, кв.м]] -> 14539789 | BG334: =BE334-$BG$1*PriceList[[#This Row],[Площадь, кв.м]] -> 14333209 | BH334: =BE334-BG334 -> 206580 | BI334: =BG334/PriceList[[#This Row],[Площадь, кв.м]] -> 416300 | BJ334: =BH334/BG334 -> 0.014412683 | BL334: =BI334-10%*BI334 -> 374670 | BM334: =BL334*G334 -> 12899888
A335: 430 | B335: С2-104 | C335: 104 | D335: С2 | E335: 3 | F335: 32 | G335: 29.27 | H335: Ст | I335: Ст | J335: 4.29 | K335: =ROUND(J335*0.3,2) -> 1.29 | L335: =G335-J335 -> 24.98 | M335: =L335+K335 -> 26.27 | N335: S | O335: Линейная | P335: Правильная | Q335: Зона 3 | R335: Озеро | S335: Озеро | T335: Стандарт | U335: 40 | V335: =IFERROR(VLOOKUP(H335,'Коэфф для прайса 1 оч'!$A$3:$C$6,3,0),"") -> 327000 | W335: =IFERROR(VLOOKUP(E335,'Коэфф для прайса 1 оч'!$A$10:$C$23,3,0),"") -> -0.005 | X335: =IFERROR(VLOOKUP(N335,'Коэфф для прайса 1 оч'!$E$25:$F$30,2,0),"") -> 0.04 | Y335: =IFERROR(VLOOKUP(O335,'Коэфф для прайса 1 оч'!$E$32:$F$34,2,0),"") -> 0 | Z335: =IFERROR(VLOOKUP(P335,'Коэфф для прайса 1 оч'!$E$36:$F$38,2,0),"") -> 0.03 | AA335: =IFERROR(VLOOKUP(Q335,'Коэфф для прайса 1 оч'!$E$40:$F$43,2,0),"") -> -0.005 | AB335: =IFERROR(VLOOKUP(R335,'Коэфф для прайса 1 оч'!$E$45:$F$59,2,0),"") -> 0.03 | AC335: =IFERROR(VLOOKUP(T335,'Коэфф для прайса 1 оч'!$E$61:$F$67,2,0),"") -> 0 | AD335: =IFERROR(VLOOKUP(U335,'Коэфф для прайса 1 оч'!$E$69:$F$82,2,0),"") -> -0.014 | AE335: =IFERROR(VLOOKUP(PriceList[[#This Row],[Корпус]],'Коэфф для прайса 1 оч'!$I$10:$J$15,2,0),"") -> 0.12 | AF335: =ROUND(V335+(V335*SUM(W335:AE335)),2) -> 391092 | AG335: =AF335*G335 -> 11447263 | AH335: 0 | AI335: =AF335+AF335*AH335 -> 391092 | AJ335: =AI335*G335 -> 11447263 | AK335: Резерв | AL335: 0.1 | AM335: =PriceList[[#This Row],[ИТОГ Цена за кв.м, руб]]*(1+PriceList[[#This Row],[Максимальная скидка]]) -> 430201.2 | AN335: =PriceList[[#This Row],[Цена за кв.м. в CRM]]*PriceList[[#This Row],[Площадь, кв.м]] -> 12591989 | AO335: 6000 | AP335: =PriceList[[#This Row],[Цена за кв.м. в CRM]]+PriceList[[#This Row],[Бронь]] -> 436201.2 | AQ335: =PriceList[[#This Row],[Цена за кв.м. в сайт]]*PriceList[[#This Row],[Площадь, кв.м]] -> 12767609 | AR335: =B335 -> С2-104 | AS335: =H335 -> Ст | AT335: =G335 -> 29.27 | AU335: =PriceList[[#This Row],[Цена за кв.м. в CRM]] -> 430201.2 | AV335: =AK335 -> Резерв | AZ335: =(PriceList[[#This Row],[Цена за кв.м. в сайт]])+$AZ$1 -> 436701.2 | BA335: =AZ335*PriceList[[#This Row],[Площадь, кв.м]] -> 12782244 | BB335: =BA335-PriceList[[#This Row],[Стоимость, руб для сбронированием]] -> 14635 | BD335: =MROUND(AZ335,100) -> 436700 | BE335: =BD335*PriceList[[#This Row],[Площадь, кв.м]] -> 12782209 | BG335: =BE335-$BG$1*PriceList[[#This Row],[Площадь, кв.м]] -> 12606589 | BH335: =BE335-BG335 -> 175620 | BI335: =BG335/PriceList[[#This Row],[Площадь, кв.м]] -> 430700 | BJ335: =BH335/BG335 -> 0.01393081 | BL335: =BI335-10%*BI335 -> 387630 | BM335: =BL335*G335 -> 11345930
A336: 431 | B336: С2-105 | C336: 105 | D336: С2 | E336: 3 | F336: 33 | G336: 29.27 | H336: Ст | I336: Ст | J336: 4.29 | K336: =ROUND(J336*0.3,2) -> 1.29 | L336: =G336-J336 -> 24.98 | M336: =L336+K336 -> 26.27 | N336: S | O336: Линейная | P336: Правильная | Q336: Зона 2 | R336: Озеро | S336: Озеро | T336: Стандарт | U336: 40 | V336: =IFERROR(VLOOKUP(H336,'Коэфф для прайса 1 оч'!$A$3:$C$6,3,0),"") -> 327000 | W336: =IFERROR(VLOOKUP(E336,'Коэфф для прайса 1 оч'!$A$10:$C$23,3,0),"") -> -0.005 | X336: =IFERROR(VLOOKUP(N336,'Коэфф для прайса 1 оч'!$E$25:$F$30,2,0),"") -> 0.04 | Y336: =IFERROR(VLOOKUP(O336,'Коэфф для прайса 1 оч'!$E$32:$F$34,2,0),"") -> 0 | Z336: =IFERROR(VLOOKUP(P336,'Коэфф для прайса 1 оч'!$E$36:$F$38,2,0),"") -> 0.03 | AA336: =IFERROR(VLOOKUP(Q336,'Коэфф для прайса 1 оч'!$E$40:$F$43,2,0),"") -> 0 | AB336: =IFERROR(VLOOKUP(R336,'Коэфф для прайса 1 оч'!$E$45:$F$59,2,0),"") -> 0.03 | AC336: =IFERROR(VLOOKUP(T336,'Коэфф для прайса 1 оч'!$E$61:$F$67,2,0),"") -> 0 | AD336: =IFERROR(VLOOKUP(U336,'Коэфф для прайса 1 оч'!$E$69:$F$82,2,0),"") -> -0.014 | AE336: =IFERROR(VLOOKUP(PriceList[[#This Row],[Корпус]],'Коэфф для прайса 1 оч'!$I$10:$J$15,2,0),"") -> 0.12 | AF336: =ROUND(V336+(V336*SUM(W336:AE336)),2) -> 392727 | AG336: =AF336*G336 -> 11495119 | AH336: 0 | AI336: =AF336+AF336*AH336 -> 392727 | AJ336: =AI336*G336 -> 11495119 | AK336: Резерв | AL336: 0.1 | AM336: =PriceList[[#This Row],[ИТОГ Цена за кв.м, руб]]*(1+PriceList[[#This Row],[Максимальная скидка]]) -> 431999.7 | AN336: =PriceList[[#This Row],[Цена за кв.м. в CRM]]*PriceList[[#This Row],[Площадь, кв.м]] -> 12644631 | AO336: 6000 | AP336: =PriceList[[#This Row],[Цена за кв.м. в CRM]]+PriceList[[#This Row],[Бронь]] -> 437999.7 | AQ336: =PriceList[[#This Row],[Цена за кв.м. в сайт]]*PriceList[[#This Row],[Площадь, кв.м]] -> 12820251 | AR336: =B336 -> С2-105 | AS336: =H336 -> Ст | AT336: =G336 -> 29.27 | AU336: =PriceList[[#This Row],[Цена за кв.м. в CRM]] -> 431999.7 | AV336: =AK336 -> Резерв | AZ336: =(PriceList[[#This Row],[Цена за кв.м. в сайт]])+$AZ$1 -> 438499.7 | BA336: =AZ336*PriceList[[#This Row],[Площадь, кв.м]] -> 12834886 | BB336: =BA336-PriceList[[#This Row],[Стоимость, руб для сбронированием]] -> 14635 | BD336: =MROUND(AZ336,100) -> 438500 | BE336: =BD336*PriceList[[#This Row],[Площадь, кв.м]] -> 12834895 | BG336: =BE336-$BG$1*PriceList[[#This Row],[Площадь, кв.м]] -> 12659275 | BH336: =BE336-BG336 -> 175620 | BI336: =BG336/PriceList[[#This Row],[Площадь, кв.м]] -> 432500 | BJ336: =BH336/BG336 -> 0.013872832 | BL336: =BI336-10%*BI336 -> 389250 | BM336: =BL336*G336 -> 11393348
A337: 432 | B337: С2-106 | C337: 106 | D337: С2 | E337: 3 | F337: 34 | G337: 29.27 | H337: Ст | I337: Ст | J337: 4.29 | K337: =ROUND(J337*0.3,2) -> 1.29 | L337: =G337-J337 -> 24.98 | M337: =L337+K337 -> 26.27 | N337: S | O337: Линейная | P337: Правильная | Q337: Зона 2 | R337: Озеро | S337: Озеро | T337: Стандарт | U337: 40 | V337: =IFERROR(VLOOKUP(H337,'Коэфф для прайса 1 оч'!$A$3:$C$6,3,0),"") -> 327000 | W337: =IFERROR(VLOOKUP(E337,'Коэфф для прайса 1 оч'!$A$10:$C$23,3,0),"") -> -0.005 | X337: =IFERROR(VLOOKUP(N337,'Коэфф для прайса 1 оч'!$E$25:$F$30,2,0),"") -> 0.04 | Y337: =IFERROR(VLOOKUP(O337,'Коэфф для прайса 1 оч'!$E$32:$F$34,2,0),"") -> 0 | Z337: =IFERROR(VLOOKUP(P337,'Коэфф для прайса 1 оч'!$E$36:$F$38,2,0),"") -> 0.03 | AA337: =IFERROR(VLOOKUP(Q337,'Коэфф для прайса 1 оч'!$E$40:$F$43,2,0),"") -> 0 | AB337: =IFERROR(VLOOKUP(R337,'Коэфф для прайса 1 оч'!$E$45:$F$59,2,0),"") -> 0.03 | AC337: =IFERROR(VLOOKUP(T337,'Коэфф для прайса 1 оч'!$E$61:$F$67,2,0),"") -> 0 | AD337: =IFERROR(VLOOKUP(U337,'Коэфф для прайса 1 оч'!$E$69:$F$82,2,0),"") -> -0.014 | AE337: =IFERROR(VLOOKUP(PriceList[[#This Row],[Корпус]],'Коэфф для прайса 1 оч'!$I$10:$J$15,2,0),"") -> 0.12 | AF337: =ROUND(V337+(V337*SUM(W337:AE337)),2) -> 392727 | AG337: =AF337*G337 -> 11495119 | AH337: 0 | AI337: =AF337+AF337*AH337 -> 392727 | AJ337: =AI337*G337 -> 11495119 | AK337: Резерв | AL337: 0.1 | AM337: =PriceList[[#This Row],[ИТОГ Цена за кв.м, руб]]*(1+PriceList[[#This Row],[Максимальная скидка]]) -> 431999.7 | AN337: =PriceList[[#This Row],[Цена за кв.м. в CRM]]*PriceList[[#This Row],[Площадь, кв.м]] -> 12644631 | AO337: 6000 | AP337: =PriceList[[#This Row],[Цена за кв.м. в CRM]]+PriceList[[#This Row],[Бронь]] -> 437999.7 | AQ337: =PriceList[[#This Row],[Цена за кв.м. в сайт]]*PriceList[[#This Row],[Площадь, кв.м]] -> 12820251 | AR337: =B337 -> С2-106 | AS337: =H337 -> Ст | AT337: =G337 -> 29.27 | AU337: =PriceList[[#This Row],[Цена за кв.м. в CRM]] -> 431999.7 | AV337: =AK337 -> Резерв | AZ337: =(PriceList[[#This Row],[Цена за кв.м. в сайт]])+$AZ$1 -> 438499.7 | BA337: =AZ337*PriceList[[#This Row],[Площадь, кв.м]] -> 12834886 | BB337: =BA337-PriceList[[#This Row],[Стоимость, руб для сбронированием]] -> 14635 | BD337: =MROUND(AZ337,100) -> 438500 | BE337: =BD337*PriceList[[#This Row],[Площадь, кв.м]] -> 12834895 | BG337: =BE337-$BG$1*PriceList[[#This Row],[Площадь, кв.м]] -> 12659275 | BH337: =BE337-BG337 -> 175620 | BI337: =BG337/PriceList[[#This Row],[Площадь, кв.м]] -> 432500 | BJ337: =BH337/BG337 -> 0.013872832 | BL337: =BI337-10%*BI337 -> 389250 | BM337: =BL337*G337 -> 11393348
A338: 433 | B338: С2-107 | C338: 107 | D338: С2 | E338: 3 | F338: 35 | G338: 29.27 | H338: Ст | I338: Ст | J338: 4.29 | K338: =ROUND(J338*0.3,2) -> 1.29 | L338: =G338-J338 -> 24.98 | M338: =L338+K338 -> 26.27 | N338: S | O338: Линейная | P338: Правильная | Q338: Зона 2 | R338: Озеро | S338: Озеро | T338: Стандарт | U338: 40 | V338: =IFERROR(VLOOKUP(H338,'Коэфф для прайса 1 оч'!$A$3:$C$6,3,0),"") -> 327000 | W338: =IFERROR(VLOOKUP(E338,'Коэфф для прайса 1 оч'!$A$10:$C$23,3,0),"") -> -0.005 | X338: =IFERROR(VLOOKUP(N338,'Коэфф для прайса 1 оч'!$E$25:$F$30,2,0),"") -> 0.04 | Y338: =IFERROR(VLOOKUP(O338,'Коэфф для прайса 1 оч'!$E$32:$F$34,2,0),"") -> 0 | Z338: =IFERROR(VLOOKUP(P338,'Коэфф для прайса 1 оч'!$E$36:$F$38,2,0),"") -> 0.03 | AA338: =IFERROR(VLOOKUP(Q338,'Коэфф для прайса 1 оч'!$E$40:$F$43,2,0),"") -> 0 | AB338: =IFERROR(VLOOKUP(R338,'Коэфф для прайса 1 оч'!$E$45:$F$59,2,0),"") -> 0.03 | AC338: =IFERROR(VLOOKUP(T338,'Коэфф для прайса 1 оч'!$E$61:$F$67,2,0),"") -> 0 | AD338: =IFERROR(VLOOKUP(U338,'Коэфф для прайса 1 оч'!$E$69:$F$82,2,0),"") -> -0.014 | AE338: =IFERROR(VLOOKUP(PriceList[[#This Row],[Корпус]],'Коэфф для прайса 1 оч'!$I$10:$J$15,2,0),"") -> 0.12 | AF338: =ROUND(V338+(V338*SUM(W338:AE338)),2) -> 392727 | AG338: =AF338*G338 -> 11495119 | AH338: 0 | AI338: =AF338+AF338*AH338 -> 392727 | AJ338: =AI338*G338 -> 11495119 | AK338: Резерв | AL338: 0.1 | AM338: =PriceList[[#This Row],[ИТОГ Цена за кв.м, руб]]*(1+PriceList[[#This Row],[Максимальная скидка]]) -> 431999.7 | AN338: =PriceList[[#This Row],[Цена за кв.м. в CRM]]*PriceList[[#This Row],[Площадь, кв.м]] -> 12644631 | AO338: 6000 | AP338: =PriceList[[#This Row],[Цена за кв.м. в CRM]]+PriceList[[#This Row],[Бронь]] -> 437999.7 | AQ338: =PriceList[[#This Row],[Цена за кв.м. в сайт]]*PriceList[[#This Row],[Площадь, кв.м]] -> 12820251 | AR338: =B338 -> С2-107 | AS338: =H338 -> Ст | AT338: =G338 -> 29.27 | AU338: =PriceList[[#This Row],[Цена за кв.м. в CRM]] -> 431999.7 | AV338: =AK338 -> Резерв | AZ338: =(PriceList[[#This Row],[Цена за кв.м. в сайт]])+$AZ$1 -> 438499.7 | BA338: =AZ338*PriceList[[#This Row],[Площадь, кв.м]] -> 12834886 | BB338: =BA338-PriceList[[#This Row],[Стоимость, руб для сбронированием]] -> 14635 | BD338: =MROUND(AZ338,100) -> 438500 | BE338: =BD338*PriceList[[#This Row],[Площадь, кв.м]] -> 12834895 | BG338: =BE338-$BG$1*PriceList[[#This Row],[Площадь, кв.м]] -> 12659275 | BH338: =BE338-BG338 -> 175620 | BI338: =BG338/PriceList[[#This Row],[Площадь, кв.м]] -> 432500 | BJ338: =BH338/BG338 -> 0.013872832 | BL338: =BI338-10%*BI338 -> 389250 | BM338: =BL338*G338 -> 11393348
A339: 434 | B339: С2-108 | C339: 108 | D339: С2 | E339: 3 | F339: 36 | G339: 63.41 | H339: 1К | I339: 1АЕ | J339: 12.85 | K339: =ROUND(J339*0.3,2) -> 3.86 | L339: =G339-J339 -> 50.56 | M339: =L339+K339 -> 54.42 | N339: XL | O339: Линейная | P339: Неправильная | Q339: Зона 2 | R339: Озеро | S339: Озеро | T339: Стандарт | U339: 40 | V339: =IFERROR(VLOOKUP(H339,'Коэфф для прайса 1 оч'!$A$3:$C$6,3,0),"") -> 313920 | W339: =IFERROR(VLOOKUP(E339,'Коэфф для прайса 1 оч'!$A$10:$C$23,3,0),"") -> -0.005 | X339: =IFERROR(VLOOKUP(N339,'Коэфф для прайса 1 оч'!$E$25:$F$30,2,0),"") -> -0.02 | Y339: =IFERROR(VLOOKUP(O339,'Коэфф для прайса 1 оч'!$E$32:$F$34,2,0),"") -> 0 | Z339: =IFERROR(VLOOKUP(P339,'Коэфф для прайса 1 оч'!$E$36:$F$38,2,0),"") -> 0 | AA339: =IFERROR(VLOOKUP(Q339,'Коэфф для прайса 1 оч'!$E$40:$F$43,2,0),"") -> 0 | AB339: =IFERROR(VLOOKUP(R339,'Коэфф для прайса 1 оч'!$E$45:$F$59,2,0),"") -> 0.03 | AC339: =IFERROR(VLOOKUP(T339,'Коэфф для прайса 1 оч'!$E$61:$F$67,2,0),"") -> 0 | AD339: =IFERROR(VLOOKUP(U339,'Коэфф для прайса 1 оч'!$E$69:$F$82,2,0),"") -> -0.014 | AE339: =IFERROR(VLOOKUP(PriceList[[#This Row],[Корпус]],'Коэфф для прайса 1 оч'!$I$10:$J$15,2,0),"") -> 0.12 | AF339: =ROUND(V339+(V339*SUM(W339:AE339)),2) -> 348765.12 | AG339: =AF339*G339 -> 22115196 | AH339: 0 | AI339: =AF339+AF339*AH339 -> 348765.12 | AJ339: =AI339*G339 -> 22115196 | AK339: Резерв | AL339: 0.1 | AM339: =PriceList[[#This Row],[ИТОГ Цена за кв.м, руб]]*(1+PriceList[[#This Row],[Максимальная скидка]]) -> 383641.63 | AN339: =PriceList[[#This Row],[Цена за кв.м. в CRM]]*PriceList[[#This Row],[Площадь, кв.м]] -> 24326716 | AO339: 6000 | AP339: =PriceList[[#This Row],[Цена за кв.м. в CRM]]+PriceList[[#This Row],[Бронь]] -> 389641.63 | AQ339: =PriceList[[#This Row],[Цена за кв.м. в сайт]]*PriceList[[#This Row],[Площадь, кв.м]] -> 24707176 | AR339: =B339 -> С2-108 | AS339: =H339 -> 1К | AT339: =G339 -> 63.41 | AU339: =PriceList[[#This Row],[Цена за кв.м. в CRM]] -> 383641.63 | AV339: =AK339 -> Резерв | AZ339: =(PriceList[[#This Row],[Цена за кв.м. в сайт]])+$AZ$1 -> 390141.63 | BA339: =AZ339*PriceList[[#This Row],[Площадь, кв.м]] -> 24738881 | BB339: =BA339-PriceList[[#This Row],[Стоимость, руб для сбронированием]] -> 31705 | BD339: =MROUND(AZ339,100) -> 390100 | BE339: =BD339*PriceList[[#This Row],[Площадь, кв.м]] -> 24736241 | BG339: =BE339-$BG$1*PriceList[[#This Row],[Площадь, кв.м]] -> 24355781 | BH339: =BE339-BG339 -> 380460 | BI339: =BG339/PriceList[[#This Row],[Площадь, кв.м]] -> 384100 | BJ339: =BH339/BG339 -> 0.015620932 | BL339: =BI339-10%*BI339 -> 345690 | BM339: =BL339*G339 -> 21920203
A340: 435 | B340: С2-109 | C340: 109 | D340: С2 | E340: 3 | F340: 37 | G340: 28.87 | H340: Ст | I340: Ст | J340: 4.13 | K340: =ROUND(J340*0.3,2) -> 1.24 | L340: =G340-J340 -> 24.74 | M340: =L340+K340 -> 25.98 | N340: S | O340: Линейная | P340: Правильная | Q340: Зона 1 | R340: Озеро | S340: Озеро | T340: Стандарт | U340: 40 | V340: =IFERROR(VLOOKUP(H340,'Коэфф для прайса 1 оч'!$A$3:$C$6,3,0),"") -> 327000 | W340: =IFERROR(VLOOKUP(E340,'Коэфф для прайса 1 оч'!$A$10:$C$23,3,0),"") -> -0.005 | X340: =IFERROR(VLOOKUP(N340,'Коэфф для прайса 1 оч'!$E$25:$F$30,2,0),"") -> 0.04 | Y340: =IFERROR(VLOOKUP(O340,'Коэфф для прайса 1 оч'!$E$32:$F$34,2,0),"") -> 0 | Z340: =IFERROR(VLOOKUP(P340,'Коэфф для прайса 1 оч'!$E$36:$F$38,2,0),"") -> 0.03 | AA340: =IFERROR(VLOOKUP(Q340,'Коэфф для прайса 1 оч'!$E$40:$F$43,2,0),"") -> 0.005 | AB340: =IFERROR(VLOOKUP(R340,'Коэфф для прайса 1 оч'!$E$45:$F$59,2,0),"") -> 0.03 | AC340: =IFERROR(VLOOKUP(T340,'Коэфф для прайса 1 оч'!$E$61:$F$67,2,0),"") -> 0 | AD340: =IFERROR(VLOOKUP(U340,'Коэфф для прайса 1 оч'!$E$69:$F$82,2,0),"") -> -0.014 | AE340: =IFERROR(VLOOKUP(PriceList[[#This Row],[Корпус]],'Коэфф для прайса 1 оч'!$I$10:$J$15,2,0),"") -> 0.12 | AF340: =ROUND(V340+(V340*SUM(W340:AE340)),2) -> 394362 | AG340: =AF340*G340 -> 11385231 | AH340: 0 | AI340: =AF340+AF340*AH340 -> 394362 | AJ340: =AI340*G340 -> 11385231 | AK340: Резерв | AL340: 0.1 | AM340: =PriceList[[#This Row],[ИТОГ Цена за кв.м, руб]]*(1+PriceList[[#This Row],[Максимальная скидка]]) -> 433798.2 | AN340: =PriceList[[#This Row],[Цена за кв.м. в CRM]]*PriceList[[#This Row],[Площадь, кв.м]] -> 12523754 | AO340: 6000 | AP340: =PriceList[[#This Row],[Цена за кв.м. в CRM]]+PriceList[[#This Row],[Бронь]] -> 439798.2 | AQ340: =PriceList[[#This Row],[Цена за кв.м. в сайт]]*PriceList[[#This Row],[Площадь, кв.м]] -> 12696974 | AR340: =B340 -> С2-109 | AS340: =H340 -> Ст | AT340: =G340 -> 28.87 | AU340: =PriceList[[#This Row],[Цена за кв.м. в CRM]] -> 433798.2 | AV340: =AK340 -> Резерв | AZ340: =(PriceList[[#This Row],[Цена за кв.м. в сайт]])+$AZ$1 -> 440298.2 | BA340: =AZ340*PriceList[[#This Row],[Площадь, кв.м]] -> 12711409 | BB340: =BA340-PriceList[[#This Row],[Стоимость, руб для сбронированием]] -> 14435 | BD340: =MROUND(AZ340,100) -> 440300 | BE340: =BD340*PriceList[[#This Row],[Площадь, кв.м]] -> 12711461 | BG340: =BE340-$BG$1*PriceList[[#This Row],[Площадь, кв.м]] -> 12538241 | BH340: =BE340-BG340 -> 173220 | BI340: =BG340/PriceList[[#This Row],[Площадь, кв.м]] -> 434300 | BJ340: =BH340/BG340 -> 0.013815335 | BL340: =BI340-10%*BI340 -> 390870 | BM340: =BL340*G340 -> 11284417
A341: 337 | B341: С2-11 | C341: 11 | D341: С2 | E341: 1 | F341: 11 | G341: 36.32 | H341: Ст | I341: Ст | J341: 6.16 | K341: =ROUND(J341*0.3,2) -> 1.85 | L341: =G341-J341 -> 30.16 | M341: =L341+K341 -> 32.01 | N341: M | O341: Линейная | P341: Правильная | Q341: Зона 1 | R341: Двор юго-запад | S341: Двор | T341: Внутренний угол | U341: 34 | V341: =IFERROR(VLOOKUP(H341,'Коэфф для прайса 1 оч'!$A$3:$C$6,3,0),"") -> 327000 | W341: =IFERROR(VLOOKUP(E341,'Коэфф для прайса 1 оч'!$A$10:$C$23,3,0),"") -> -0.045 | X341: =IFERROR(VLOOKUP(N341,'Коэфф для прайса 1 оч'!$E$25:$F$30,2,0),"") -> 0 | Y341: =IFERROR(VLOOKUP(O341,'Коэфф для прайса 1 оч'!$E$32:$F$34,2,0),"") -> 0 | Z341: =IFERROR(VLOOKUP(P341,'Коэфф для прайса 1 оч'!$E$36:$F$38,2,0),"") -> 0.03 | AA341: =IFERROR(VLOOKUP(Q341,'Коэфф для прайса 1 оч'!$E$40:$F$43,2,0),"") -> 0.005 | AB341: =IFERROR(VLOOKUP(R341,'Коэфф для прайса 1 оч'!$E$45:$F$59,2,0),"") -> 0.02 | AC341: =IFERROR(VLOOKUP(T341,'Коэфф для прайса 1 оч'!$E$61:$F$67,2,0),"") -> -0.01 | AD341: =IFERROR(VLOOKUP(U341,'Коэфф для прайса 1 оч'!$E$69:$F$82,2,0),"") -> -0.008 | AE341: =IFERROR(VLOOKUP(PriceList[[#This Row],[Корпус]],'Коэфф для прайса 1 оч'!$I$10:$J$15,2,0),"") -> 0.12 | AF341: =ROUND(V341+(V341*SUM(W341:AE341)),2) -> 363624 | AG341: =AF341*G341 -> 13206824 | AH341: 0 | AI341: =AF341+AF341*AH341 -> 363624 | AJ341: =AI341*G341 -> 13206824 | AK341: Резерв | AL341: 0.1 | AM341: =PriceList[[#This Row],[ИТОГ Цена за кв.м, руб]]*(1+PriceList[[#This Row],[Максимальная скидка]]) -> 399986.4 | AN341: =PriceList[[#This Row],[Цена за кв.м. в CRM]]*PriceList[[#This Row],[Площадь, кв.м]] -> 14527506 | AO341: 6000 | AP341: =PriceList[[#This Row],[Цена за кв.м. в CRM]]+PriceList[[#This Row],[Бронь]] -> 405986.4 | AQ341: =PriceList[[#This Row],[Цена за кв.м. в сайт]]*PriceList[[#This Row],[Площадь, кв.м]] -> 14745426 | AR341: =B341 -> С2-11 | AS341: =H341 -> Ст | AT341: =G341 -> 36.32 | AU341: =PriceList[[#This Row],[Цена за кв.м. в CRM]] -> 399986.4 | AV341: =AK341 -> Резерв | AZ341: =(PriceList[[#This Row],[Цена за кв.м. в сайт]])+$AZ$1 -> 406486.4 | BA341: =AZ341*PriceList[[#This Row],[Площадь, кв.м]] -> 14763586 | BB341: =BA341-PriceList[[#This Row],[Стоимость, руб для сбронированием]] -> 18160 | BD341: =MROUND(AZ341,100) -> 406500 | BE341: =BD341*PriceList[[#This Row],[Площадь, кв.м]] -> 14764080 | BG341: =BE341-$BG$1*PriceList[[#This Row],[Площадь, кв.м]] -> 14546160 | BH341: =BE341-BG341 -> 217920 | BI341: =BG341/PriceList[[#This Row],[Площадь, кв.м]] -> 400500 | BJ341: =BH341/BG341 -> 0.014981273 | BL341: =BI341-10%*BI341 -> 360450 | BM341: =BL341*G341 -> 13091544
... A343: 437 | B343: С2-111 | C343: 111 | D343: С2 | E343: 3 | F343: 39 | G343: 28.42 | H343: Ст | I343: Ст | J343: 3.69 | K343: =ROUND(J343*0.3,2) -> 1.11 | L343: =G343-J343 -> 24.73 | M343: =L343+K343 -> 25.84 | N343: S | O343: Линейная | P343: Правильная | Q343: Зона 1 | R343: Озеро | S343: Озеро | T343: Стандарт | U343: 40 | V343: =IFERROR(VLOOKUP(H343,'Коэфф для прайса 1 оч'!$A$3:$C$6,3,0),"") -> 327000 | W343: =IFERROR(VLOOKUP(E343,'Коэфф для прайса 1 оч'!$A$10:$C$23,3,0),"") -> -0.005 | X343: =IFERROR(VLOOKUP(N343,'Коэфф для прайса 1 оч'!$E$25:$F$30,2,0),"") -> 0.04 | Y343: =IFERROR(VLOOKUP(O343,'Коэфф для прайса 1 оч'!$E$32:$F$34,2,0),"") -> 0 | Z343: =IFERROR(VLOOKUP(P343,'Коэфф для прайса 1 оч'!$E$36:$F$38,2,0),"") -> 0.03 | AA343: =IFERROR(VLOOKUP(Q343,'Коэфф для прайса 1 оч'!$E$40:$F$43,2,0),"") -> 0.005 | AB343: =IFERROR(VLOOKUP(R343,'Коэфф для прайса 1 оч'!$E$45:$F$59,2,0),"") -> 0.03 | AC343: =IFERROR(VLOOKUP(T343,'Коэфф для прайса 1 оч'!$E$61:$F$67,2,0),"") -> 0 | AD343: =IFERROR(VLOOKUP(U343,'Коэфф для прайса 1 оч'!$E$69:$F$82,2,0),"") -> -0.014 | AE343: =IFERROR(VLOOKUP(PriceList[[#This Row],[Корпус]],'Коэфф для прайса 1 оч'!$I$10:$J$15,2,0),"") -> 0.12 | AF343: =ROUND(V343+(V343*SUM(W343:AE343)),2) -> 394362 | AG343: =AF343*G343 -> 11207768 | AH343: 0 | AI343: =AF343+AF343*AH343 -> 394362 | AJ343: =AI343*G343 -> 11207768 | AK343: Резерв | AL343: 0.1 | AM343: =PriceList[[#This Row],[ИТОГ Цена за кв.м, руб]]*(1+PriceList[[#This Row],[Максимальная скидка]]) -> 433798.2 | AN343: =PriceList[[#This Row],[Цена за кв.м. в CRM]]*PriceList[[#This Row],[Площадь, кв.м]] -> 12328545 | AO343: 6000 | AP343: =PriceList[[#This Row],[Цена за кв.м. в CRM]]+PriceList[[#This Row],[Бронь]] -> 439798.2 | AQ343: =PriceList[[#This Row],[Цена за кв.м. в сайт]]*PriceList[[#This Row],[Площадь, кв.м]] -> 12499065 | AR343: =B343 -> С2-111 | AS343: =H343 -> Ст | AT343: =G343 -> 28.42 | AU343: =PriceList[[#This Row],[Цена за кв.м. в CRM]] -> 433798.2 | AV343: =AK343 -> Резерв | AZ343: =(PriceList[[#This Row],[Цена за кв.м. в сайт]])+$AZ$1 -> 440298.2 | BA343: =AZ343*PriceList[[#This Row],[Площадь, кв.м]] -> 12513275 | BB343: =BA343-PriceList[[#This Row],[Стоимость, руб для сбронированием]] -> 14210 | BD343: =MROUND(AZ343,100) -> 440300 | BE343: =BD343*PriceList[[#This Row],[Площадь, кв.м]] -> 12513326 | BG343: =BE343-$BG$1*PriceList[[#This Row],[Площадь, кв.м]] -> 12342806 | BH343: =BE343-BG343 -> 170520 | BI343: =BG343/PriceList[[#This Row],[Площадь, кв.м]] -> 434300 | BJ343: =BH343/BG343 -> 0.013815335 | BL343: =BI343-10%*BI343 -> 390870 | BM343: =BL343*G343 -> 11108525
A344: 438 | B344: С2-112 | C344: 112 | D344: С2 | E344: 3 | F344: 40 | G344: 28.72 | H344: Ст | I344: Ст | J344: 4.13 | K344: =ROUND(J344*0.3,2) -> 1.24 | L344: =G344-J344 -> 24.59 | M344: =L344+K344 -> 25.83 | N344: S | O344: Линейная | P344: Правильная | Q344: Зона 1 | R344: Озеро | S344: Озеро | T344: Стандарт | U344: 40 | V344: =IFERROR(VLOOKUP(H344,'Коэфф для прайса 1 оч'!$A$3:$C$6,3,0),"") -> 327000 | W344: =IFERROR(VLOOKUP(E344,'Коэфф для прайса 1 оч'!$A$10:$C$23,3,0),"") -> -0.005 | X344: =IFERROR(VLOOKUP(N344,'Коэфф для прайса 1 оч'!$E$25:$F$30,2,0),"") -> 0.04 | Y344: =IFERROR(VLOOKUP(O344,'Коэфф для прайса 1 оч'!$E$32:$F$34,2,0),"") -> 0 | Z344: =IFERROR(VLOOKUP(P344,'Коэфф для прайса 1 оч'!$E$36:$F$38,2,0),"") -> 0.03 | AA344: =IFERROR(VLOOKUP(Q344,'Коэфф для прайса 1 оч'!$E$40:$F$43,2,0),"") -> 0.005 | AB344: =IFERROR(VLOOKUP(R344,'Коэфф для прайса 1 оч'!$E$45:$F$59,2,0),"") -> 0.03 | AC344: =IFERROR(VLOOKUP(T344,'Коэфф для прайса 1 оч'!$E$61:$F$67,2,0),"") -> 0 | AD344: =IFERROR(VLOOKUP(U344,'Коэфф для прайса 1 оч'!$E$69:$F$82,2,0),"") -> -0.014 | AE344: =IFERROR(VLOOKUP(PriceList[[#This Row],[Корпус]],'Коэфф для прайса 1 оч'!$I$10:$J$15,2,0),"") -> 0.12 | AF344: =ROUND(V344+(V344*SUM(W344:AE344)),2) -> 394362 | AG344: =AF344*G344 -> 11326077 | AH344: 0 | AK344: Не для продажи | AL344: 0.1 | AM344: =PriceList[[#This Row],[ИТОГ Цена за кв.м, руб]]*(1+PriceList[[#This Row],[Максимальная скидка]]) -> 0 | AN344: =PriceList[[#This Row],[Цена за кв.м. в CRM]]*PriceList[[#This Row],[Площадь, кв.м]] -> 0 | AO344: 6000 | AP344: =PriceList[[#This Row],[Цена за кв.м. в CRM]]+PriceList[[#This Row],[Бронь]] -> 6000 | AQ344: =PriceList[[#This Row],[Цена за кв.м. в сайт]]*PriceList[[#This Row],[Площадь, кв.м]] -> 172320 | AR344: =B344 -> С2-112 | AS344: =H344 -> Ст | AT344: =G344 -> 28.72 | AU344: =PriceList[[#This Row],[Цена за кв.м. в CRM]] -> 0 | AV344: =AK344 -> Не для продажи | BD344: =MROUND(AZ344,100) -> 0 | BE344: =BD344*PriceList[[#This Row],[Площадь, кв.м]] -> 0 | BH344: =BE344-BG344 -> 0 | BI344: =BG344/PriceList[[#This Row],[Площадь, кв.м]] -> 0 | BJ344: =BH344/BG344 -> #DIV/0! | BL344: =BI344-10%*BI344 -> 0 | BM344: =BL344*G344 -> 0
A345: 439 | B345: С2-113 | C345: 113 | D345: С2 | E345: 4 | F345: 1 | G345: 37.46 | H345: Ст | I345: Ст | J345: 7.24 | K345: =ROUND(J345*0.3,2) -> 2.17 | L345: =G345-J345 -> 30.22 | M345: =L345+K345 -> 32.39 | N345: M | O345: Линейная | P345: Правильная | Q345: Зона 1 | R345: Озеро | S345: Озеро | T345: Стандарт | U345: 40 | V345: =IFERROR(VLOOKUP(H345,'Коэфф для прайса 1 оч'!$A$3:$C$6,3,0),"") -> 327000 | W345: =IFERROR(VLOOKUP(E345,'Коэфф для прайса 1 оч'!$A$10:$C$23,3,0),"") -> 0 | X345: =IFERROR(VLOOKUP(N345,'Коэфф для прайса 1 оч'!$E$25:$F$30,2,0),"") -> 0 | Y345: =IFERROR(VLOOKUP(O345,'Коэфф для прайса 1 оч'!$E$32:$F$34,2,0),"") -> 0 | Z345: =IFERROR(VLOOKUP(P345,'Коэфф для прайса 1 оч'!$E$36:$F$38,2,0),"") -> 0.03 | AA345: =IFERROR(VLOOKUP(Q345,'Коэфф для прайса 1 оч'!$E$40:$F$43,2,0),"") -> 0.005 | AB345: =IFERROR(VLOOKUP(R345,'Коэфф для прайса 1 оч'!$E$45:$F$59,2,0),"") -> 0.03 | AC345: =IFERROR(VLOOKUP(T345,'Коэфф для прайса 1 оч'!$E$61:$F$67,2,0),"") -> 0 | AD345: =IFERROR(VLOOKUP(U345,'Коэфф для прайса 1 оч'!$E$69:$F$82,2,0),"") -> -0.014 | AE345: =IFERROR(VLOOKUP(PriceList[[#This Row],[Корпус]],'Коэфф для прайса 1 оч'!$I$10:$J$15,2,0),"") -> 0.12 | AF345: =ROUND(V345+(V345*SUM(W345:AE345)),2) -> 382917 | AG345: =AF345*G345 -> 14344071 | AH345: 0 | AI345: =AF345+AF345*AH345 -> 382917 | AJ345: =AI345*G345 -> 14344071 | AK345: Свободно | AL345: 0.1 | AM345: =PriceList[[#This Row],[ИТОГ Цена за кв.м, руб]]*(1+PriceList[[#This Row],[Максимальная скидка]]) -> 421208.7 | AN345: =PriceList[[#This Row],[Цена за кв.м. в CRM]]*PriceList[[#This Row],[Площадь, кв.м]] -> 15778478 | AO345: 6000 | AP345: =PriceList[[#This Row],[Цена за кв.м. в CRM]]+PriceList[[#This Row],[Бронь]] -> 427208.7 | AQ345: =PriceList[[#This Row],[Цена за кв.м. в сайт]]*PriceList[[#This Row],[Площадь, кв.м]] -> 16003238 | AR345: =B345 -> С2-113 | AS345: =H345 -> Ст | AT345: =G345 -> 37.46 | AU345: =PriceList[[#This Row],[Цена за кв.м. в CRM]] -> 421208.7 | AV345: =AK345 -> Свободно | AZ345: =(PriceList[[#This Row],[Цена за кв.м. в сайт]])+$AZ$1 -> 427708.7 | BA345: =AZ345*PriceList[[#This Row],[Площадь, кв.м]] -> 16021968 | BB345: =BA345-PriceList[[#This Row],[Стоимость, руб для сбронированием]] -> 18730 | BD345: =MROUND(AZ345,100) -> 427700 | BE345: =BD345*PriceList[[#This Row],[Площадь, кв.м]] -> 16021642 | BG345: =BE345-$BG$1*PriceList[[#This Row],[Площадь, кв.м]] -> 15796882 | BH345: =BE345-BG345 -> 224760 | BI345: =BG345/PriceList[[#This Row],[Площадь, кв.м]] -> 421700 | BJ345: =BH345/BG345 -> 0.014228124 | BL345: =BI345-10%*BI345 -> 379530 | BM345: =BL345*G345 -> 14217194
A346: 440 | B346: С2-114 | C346: 114 | D346: С2 | E346: 4 | F346: 2 | G346: 28.98 | H346: Ст | I346: Ст | J346: 4.25 | K346: =ROUND(J346*0.3,2) -> 1.28 | L346: =G346-J346 -> 24.73 | M346: =L346+K346 -> 26.01 | N346: S | O346: Линейная | P346: Правильная | Q346: Зона 1 | R346: Озеро | S346: Озеро | T346: Стандарт | U346: 40 | V346: =IFERROR(VLOOKUP(H346,'Коэфф для прайса 1 оч'!$A$3:$C$6,3,0),"") -> 327000 | W346: =IFERROR(VLOOKUP(E346,'Коэфф для прайса 1 оч'!$A$10:$C$23,3,0),"") -> 0 | X346: =IFERROR(VLOOKUP(N346,'Коэфф для прайса 1 оч'!$E$25:$F$30,2,0),"") -> 0.04 | Y346: =IFERROR(VLOOKUP(O346,'Коэфф для прайса 1 оч'!$E$32:$F$34,2,0),"") -> 0 | Z346: =IFERROR(VLOOKUP(P346,'Коэфф для прайса 1 оч'!$E$36:$F$38,2,0),"") -> 0.03 | AA346: =IFERROR(VLOOKUP(Q346,'Коэфф для прайса 1 оч'!$E$40:$F$43,2,0),"") -> 0.005 | AB346: =IFERROR(VLOOKUP(R346,'Коэфф для прайса 1 оч'!$E$45:$F$59,2,0),"") -> 0.03 | AC346: =IFERROR(VLOOKUP(T346,'Коэфф для прайса 1 оч'!$E$61:$F$67,2,0),"") -> 0 | AD346: =IFERROR(VLOOKUP(U346,'Коэфф для прайса 1 оч'!$E$69:$F$82,2,0),"") -> -0.014 | AE346: =IFERROR(VLOOKUP(PriceList[[#This Row],[Корпус]],'Коэфф для прайса 1 оч'!$I$10:$J$15,2,0),"") -> 0.12 | AF346: =ROUND(V346+(V346*SUM(W346:AE346)),2) -> 395997 | AG346: =AF346*G346 -> 11475993 | AH346: 0 | AI346: =AF346+AF346*AH346 -> 395997 | AJ346: =AI346*G346 -> 11475993 | AK346: Свободно | AL346: 0.1 | AM346: =PriceList[[#This Row],[ИТОГ Цена за кв.м, руб]]*(1+PriceList[[#This Row],[Максимальная скидка]]) -> 435596.7 | AN346: =PriceList[[#This Row],[Цена за кв.м. в CRM]]*PriceList[[#This Row],[Площадь, кв.м]] -> 12623592 | AO346: 6000 | AP346: =PriceList[[#This Row],[Цена за кв.м. в CRM]]+PriceList[[#This Row],[Бронь]] -> 441596.7 | AQ346: =PriceList[[#This Row],[Цена за кв.м. в сайт]]*PriceList[[#This Row],[Площадь, кв.м]] -> 12797472 | AR346: =B346 -> С2-114 | AS346: =H346 -> Ст | AT346: =G346 -> 28.98 | AU346: =PriceList[[#This Row],[Цена за кв.м. в CRM]] -> 435596.7 | AV346: =AK346 -> Свободно | AZ346: =(PriceList[[#This Row],[Цена за кв.м. в сайт]])+$AZ$1 -> 442096.7 | BA346: =AZ346*PriceList[[#This Row],[Площадь, кв.м]] -> 12811962 | BB346: =BA346-PriceList[[#This Row],[Стоимость, руб для сбронированием]] -> 14490 | BD346: =MROUND(AZ346,100) -> 442100 | BE346: =BD346*PriceList[[#This Row],[Площадь, кв.м]] -> 12812058 | BG346: =BE346-$BG$1*PriceList[[#This Row],[Площадь, кв.м]] -> 12638178 | BH346: =BE346-BG346 -> 173880 | BI346: =BG346/PriceList[[#This Row],[Площадь, кв.м]] -> 436100 | BJ346: =BH346/BG346 -> 0.013758312 | BL346: =BI346-10%*BI346 -> 392490 | BM346: =BL346*G346 -> 11374360
A347: 441 | B347: С2-115 | C347: 115 | D347: С2 | E347: 4 | F347: 3 | G347: 28.52 | H347: Ст | I347: Ст | J347: 4.25 | K347: =ROUND(J347*0.3,2) -> 1.28 | L347: =G347-J347 -> 24.27 | M347: =L347+K347 -> 25.55 | N347: S | O347: Линейная | P347: Правильная | Q347: Зона 1 | R347: Озеро | S347: Озеро | T347: Стандарт | U347: 40 | V347: =IFERROR(VLOOKUP(H347,'Коэфф для прайса 1 оч'!$A$3:$C$6,3,0),"") -> 327000 | W347: =IFERROR(VLOOKUP(E347,'Коэфф для прайса 1 оч'!$A$10:$C$23,3,0),"") -> 0 | X347: =IFERROR(VLOOKUP(N347,'Коэфф для прайса 1 оч'!$E$25:$F$30,2,0),"") -> 0.04 | Y347: =IFERROR(VLOOKUP(O347,'Коэфф для прайса 1 оч'!$E$32:$F$34,2,0),"") -> 0 | Z347: =IFERROR(VLOOKUP(P347,'Коэфф для прайса 1 оч'!$E$36:$F$38,2,0),"") -> 0.03 | AA347: =IFERROR(VLOOKUP(Q347,'Коэфф для прайса 1 оч'!$E$40:$F$43,2,0),"") -> 0.005 | AB347: =IFERROR(VLOOKUP(R347,'Коэфф для прайса 1 оч'!$E$45:$F$59,2,0),"") -> 0.03 | AC347: =IFERROR(VLOOKUP(T347,'Коэфф для прайса 1 оч'!$E$61:$F$67,2,0),"") -> 0 | AD347: =IFERROR(VLOOKUP(U347,'Коэфф для прайса 1 оч'!$E$69:$F$82,2,0),"") -> -0.014 | AE347: =IFERROR(VLOOKUP(PriceList[[#This Row],[Корпус]],'Коэфф для прайса 1 оч'!$I$10:$J$15,2,0),"") -> 0.12 | AF347: =ROUND(V347+(V347*SUM(W347:AE347)),2) -> 395997 | AG347: =AF347*G347 -> 11293834 | AH347: 0 | AI347: =AF347+AF347*AH347 -> 395997 | AJ347: =AI347*G347 -> 11293834 | AK347: Свободно | AL347: 0.1 | AM347: =PriceList[[#This Row],[ИТОГ Цена за кв.м, руб]]*(1+PriceList[[#This Row],[Максимальная скидка]]) -> 435596.7 | AN347: =PriceList[[#This Row],[Цена за кв.м. в CRM]]*PriceList[[#This Row],[Площадь, кв.м]] -> 12423218 | AO347: 6000 | AP347: =PriceList[[#This Row],[Цена за кв.м. в CRM]]+PriceList[[#This Row],[Бронь]] -> 441596.7 | AQ347: =PriceList[[#This Row],[Цена за кв.м. в сайт]]*PriceList[[#This Row],[Площадь, кв.м]] -> 12594338 | AR347: =B347 -> С2-115 | AS347: =H347 -> Ст | AT347: =G347 -> 28.52 | AU347: =PriceList[[#This Row],[Цена за кв.м. в CRM]] -> 435596.7 | AV347: =AK347 -> Свободно | AZ347: =(PriceList[[#This Row],[Цена за кв.м. в сайт]])+$AZ$1 -> 442096.7 | BA347: =AZ347*PriceList[[#This Row],[Площадь, кв.м]] -> 12608598 | BB347: =BA347-PriceList[[#This Row],[Стоимость, руб для сбронированием]] -> 14260 | BD347: =MROUND(AZ347,100) -> 442100 | BE347: =BD347*PriceList[[#This Row],[Площадь, кв.м]] -> 12608692 | BG347: =BE347-$BG$1*PriceList[[#This Row],[Площадь, кв.м]] -> 12437572 | BH347: =BE347-BG347 -> 171120 | BI347: =BG347/PriceList[[#This Row],[Площадь, кв.м]] -> 436100 | BJ347: =BH347/BG347 -> 0.013758312 | BL347: =BI347-10%*BI347 -> 392490 | BM347: =BL347*G347 -> 11193815
A348: 442 | B348: С2-116 | C348: 116 | D348: С2 | E348: 4 | F348: 4 | G348: 32.45 | H348: Ст | I348: Ст | J348: 4.39 | K348: =ROUND(J348*0.3,2) -> 1.32 | L348: =G348-J348 -> 28.06 | M348: =L348+K348 -> 29.38 | N348: S | O348: Угловая | P348: Правильная | Q348: Зона 1 | R348: Озеро | S348: Озеро | T348: Стандарт | U348: 40 | V348: =IFERROR(VLOOKUP(H348,'Коэфф для прайса 1 оч'!$A$3:$C$6,3,0),"") -> 327000 | W348: =IFERROR(VLOOKUP(E348,'Коэфф для прайса 1 оч'!$A$10:$C$23,3,0),"") -> 0 | X348: =IFERROR(VLOOKUP(N348,'Коэфф для прайса 1 оч'!$E$25:$F$30,2,0),"") -> 0.04 | Y348: =IFERROR(VLOOKUP(O348,'Коэфф для прайса 1 оч'!$E$32:$F$34,2,0),"") -> 0.03 | Z348: =IFERROR(VLOOKUP(P348,'Коэфф для прайса 1 оч'!$E$36:$F$38,2,0),"") -> 0.03 | AA348: =IFERROR(VLOOKUP(Q348,'Коэфф для прайса 1 оч'!$E$40:$F$43,2,0),"") -> 0.005 | AB348: =IFERROR(VLOOKUP(R348,'Коэфф для прайса 1 оч'!$E$45:$F$59,2,0),"") -> 0.03 | AC348: =IFERROR(VLOOKUP(T348,'Коэфф для прайса 1 оч'!$E$61:$F$67,2,0),"") -> 0 | AD348: =IFERROR(VLOOKUP(U348,'Коэфф для прайса 1 оч'!$E$69:$F$82,2,0),"") -> -0.014 | AE348: =IFERROR(VLOOKUP(PriceList[[#This Row],[Корпус]],'Коэфф для прайса 1 оч'!$I$10:$J$15,2,0),"") -> 0.12 | AF348: =ROUND(V348+(V348*SUM(W348:AE348)),2) -> 405807 | AG348: =AF348*G348 -> 13168437 | AH348: 0 | AI348: =AF348+AF348*AH348 -> 405807 | AJ348: =AI348*G348 -> 13168437 | AK348: Резерв | AL348: 0.1 | AM348: =PriceList[[#This Row],[ИТОГ Цена за кв.м, руб]]*(1+PriceList[[#This Row],[Максимальная скидка]]) -> 446387.7 | AN348: =PriceList[[#This Row],[Цена за кв.м. в CRM]]*PriceList[[#This Row],[Площадь, кв.м]] -> 14485281 | AO348: 6000 | AP348: =PriceList[[#This Row],[Цена за кв.м. в CRM]]+PriceList[[#This Row],[Бронь]] -> 452387.7 | AQ348: =PriceList[[#This Row],[Цена за кв.м. в сайт]]*PriceList[[#This Row],[Площадь, кв.м]] -> 14679981 | AR348: =B348 -> С2-116 | AS348: =H348 -> Ст | AT348: =G348 -> 32.45 | AU348: =PriceList[[#This Row],[Цена за кв.м. в CRM]] -> 446387.7 | AV348: =AK348 -> Резерв | AZ348: =(PriceList[[#This Row],[Цена за кв.м. в сайт]])+$AZ$1 -> 452887.7 | BA348: =AZ348*PriceList[[#This Row],[Площадь, кв.м]] -> 14696206 | BB348: =BA348-PriceList[[#This Row],[Стоимость, руб для сбронированием]] -> 16225 | BD348: =MROUND(AZ348,100) -> 452900 | BE348: =BD348*PriceList[[#This Row],[Площадь, кв.м]] -> 14696605 | BG348: =BE348-$BG$1*PriceList[[#This Row],[Площадь, кв.м]] -> 14501905 | BH348: =BE348-BG348 -> 194700 | BI348: =BG348/PriceList[[#This Row],[Площадь, кв.м]] -> 446900 | BJ348: =BH348/BG348 -> 0.013425822 | BL348: =BI348-10%*BI348 -> 402210 | BM348: =BL348*G348 -> 13051715
A349: 443 | B349: С2-117 | C349: 117 | D349: С2 | E349: 4 | F349: 5 | G349: 32.43 | H349: Ст | I349: Ст | J349: 4.39 | K349: =ROUND(J349*0.3,2) -> 1.32 | L349: =G349-J349 -> 28.04 | M349: =L349+K349 -> 29.36 | N349: S | O349: Угловая | P349: Правильная | Q349: Зона 1 | R349: Двор юг | S349: Двор | T349: Стандарт | U349: 40 | V349: =IFERROR(VLOOKUP(H349,'Коэфф для прайса 1 оч'!$A$3:$C$6,3,0),"") -> 327000 | W349: =IFERROR(VLOOKUP(E349,'Коэфф для прайса 1 оч'!$A$10:$C$23,3,0),"") -> 0 | X349: =IFERROR(VLOOKUP(N349,'Коэфф для прайса 1 оч'!$E$25:$F$30,2,0),"") -> 0.04 | Y349: =IFERROR(VLOOKUP(O349,'Коэфф для прайса 1 оч'!$E$32:$F$34,2,0),"") -> 0.03 | Z349: =IFERROR(VLOOKUP(P349,'Коэфф для прайса 1 оч'!$E$36:$F$38,2,0),"") -> 0.03 | AA349: =IFERROR(VLOOKUP(Q349,'Коэфф для прайса 1 оч'!$E$40:$F$43,2,0),"") -> 0.005 | AB349: =IFERROR(VLOOKUP(R349,'Коэфф для прайса 1 оч'!$E$45:$F$59,2,0),"") -> 0 | AC349: =IFERROR(VLOOKUP(T349,'Коэфф для прайса 1 оч'!$E$61:$F$67,2,0),"") -> 0 | AD349: =IFERROR(VLOOKUP(U349,'Коэфф для прайса 1 оч'!$E$69:$F$82,2,0),"") -> -0.014 | AE349: =IFERROR(VLOOKUP(PriceList[[#This Row],[Корпус]],'Коэфф для прайса 1 оч'!$I$10:$J$15,2,0),"") -> 0.12 | AF349: =ROUND(V349+(V349*SUM(W349:AE349)),2) -> 395997 | AG349: =AF349*G349 -> 12842183 | AH349: 0 | AI349: =AF349+AF349*AH349 -> 395997 | AJ349: =AI349*G349 -> 12842183 | AK349: Резерв | AL349: 0.1 | AM349: =PriceList[[#This Row],[ИТОГ Цена за кв.м, руб]]*(1+PriceList[[#This Row],[Максимальная скидка]]) -> 435596.7 | AN349: =PriceList[[#This Row],[Цена за кв.м. в CRM]]*PriceList[[#This Row],[Площадь, кв.м]] -> 14126401 | AO349: 6000 | AP349: =PriceList[[#This Row],[Цена за кв.м. в CRM]]+PriceList[[#This Row],[Бронь]] -> 441596.7 | AQ349: =PriceList[[#This Row],[Цена за кв.м. в сайт]]*PriceList[[#This Row],[Площадь, кв.м]] -> 14320981 | AR349: =B349 -> С2-117 | AS349: =H349 -> Ст | AT349: =G349 -> 32.43 | AU349: =PriceList[[#This Row],[Цена за кв.м. в CRM]] -> 435596.7 | AV349: =AK349 -> Резерв | AZ349: =(PriceList[[#This Row],[Цена за кв.м. в сайт]])+$AZ$1 -> 442096.7 | BA349: =AZ349*PriceList[[#This Row],[Площадь, кв.м]] -> 14337196 | BB349: =BA349-PriceList[[#This Row],[Стоимость, руб для сбронированием]] -> 16215 | BD349: =MROUND(AZ349,100) -> 442100 | BE349: =BD349*PriceList[[#This Row],[Площадь, кв.м]] -> 14337303 | BG349: =BE349-$BG$1*PriceList[[#This Row],[Площадь, кв.м]] -> 14142723 | BH349: =BE349-BG349 -> 194580 | BI349: =BG349/PriceList[[#This Row],[Площадь, кв.м]] -> 436100 | BJ349: =BH349/BG349 -> 0.013758312 | BL349: =BI349-10%*BI349 -> 392490 | BM349: =BL349*G349 -> 12728451
A350: 444 | B350: С2-118 | C350: 118 | D350: С2 | E350: 4 | F350: 6 | G350: 28.52 | H350: Ст | I350: Ст | J350: 4.25 | K350: =ROUND(J350*0.3,2) -> 1.28 | L350: =G350-J350 -> 24.27 | M350: =L350+K350 -> 25.55 | N350: S | O350: Линейная | P350: Правильная | Q350: Зона 1 | R350: Двор юго-запад | S350: Двор | T350: Стандарт | U350: 40 | V350: =IFERROR(VLOOKUP(H350,'Коэфф для прайса 1 оч'!$A$3:$C$6,3,0),"") -> 327000 | W350: =IFERROR(VLOOKUP(E350,'Коэфф для прайса 1 оч'!$A$10:$C$23,3,0),"") -> 0 | X350: =IFERROR(VLOOKUP(N350,'Коэфф для прайса 1 оч'!$E$25:$F$30,2,0),"") -> 0.04 | Y350: =IFERROR(VLOOKUP(O350,'Коэфф для прайса 1 оч'!$E$32:$F$34,2,0),"") -> 0 | Z350: =IFERROR(VLOOKUP(P350,'Коэфф для прайса 1 оч'!$E$36:$F$38,2,0),"") -> 0.03 | AA350: =IFERROR(VLOOKUP(Q350,'Коэфф для прайса 1 оч'!$E$40:$F$43,2,0),"") -> 0.005 | AB350: =IFERROR(VLOOKUP(R350,'Коэфф для прайса 1 оч'!$E$45:$F$59,2,0),"") -> 0.02 | AC350: =IFERROR(VLOOKUP(T350,'Коэфф для прайса 1 оч'!$E$61:$F$67,2,0),"") -> 0 | AD350: =IFERROR(VLOOKUP(U350,'Коэфф для прайса 1 оч'!$E$69:$F$82,2,0),"") -> -0.014 | AE350: =IFERROR(VLOOKUP(PriceList[[#This Row],[Корпус]],'Коэфф для прайса 1 оч'!$I$10:$J$15,2,0),"") -> 0.12 | AF350: =ROUND(V350+(V350*SUM(W350:AE350)),2) -> 392727 | AG350: =AF350*G350 -> 11200574 | AH350: 0 | AI350: =AF350+AF350*AH350 -> 392727 | AJ350: =AI350*G350 -> 11200574 | AK350: Резерв | AL350: 0.1 | AM350: =PriceList[[#This Row],[ИТОГ Цена за кв.м, руб]]*(1+PriceList[[#This Row],[Максимальная скидка]]) -> 431999.7 | AN350: =PriceList[[#This Row],[Цена за кв.м. в CRM]]*PriceList[[#This Row],[Площадь, кв.м]] -> 12320631 | AO350: 6000 | AP350: =PriceList[[#This Row],[Цена за кв.м. в CRM]]+PriceList[[#This Row],[Бронь]] -> 437999.7 | AQ350: =PriceList[[#This Row],[Цена за кв.м. в сайт]]*PriceList[[#This Row],[Площадь, кв.м]] -> 12491751 | AR350: =B350 -> С2-118 | AS350: =H350 -> Ст | AT350: =G350 -> 28.52 | AU350: =PriceList[[#This Row],[Цена за кв.м. в CRM]] -> 431999.7 | AV350: =AK350 -> Резерв | AZ350: =(PriceList[[#This Row],[Цена за кв.м. в сайт]])+$AZ$1 -> 438499.7 | BA350: =AZ350*PriceList[[#This Row],[Площадь, кв.м]] -> 12506011 | BB350: =BA350-PriceList[[#This Row],[Стоимость, руб для сбронированием]] -> 14260 | BD350: =MROUND(AZ350,100) -> 438500 | BE350: =BD350*PriceList[[#This Row],[Площадь, кв.м]] -> 12506020 | BG350: =BE350-$BG$1*PriceList[[#This Row],[Площадь, кв.м]] -> 12334900 | BH350: =BE350-BG350 -> 171120 | BI350: =BG350/PriceList[[#This Row],[Площадь, кв.м]] -> 432500 | BJ350: =BH350/BG350 -> 0.013872832 | BL350: =BI350-10%*BI350 -> 389250 | BM350: =BL350*G350 -> 11101410
A351: 445 | B351: С2-119 | C351: 119 | D351: С2 | E351: 4 | F351: 7 | G351: 28.99 | H351: Ст | I351: Ст | J351: 4.25 | K351: =ROUND(J351*0.3,2) -> 1.28 | L351: =G351-J351 -> 24.74 | M351: =L351+K351 -> 26.02 | N351: S | O351: Линейная | P351: Правильная | Q351: Зона 1 | R351: Двор юго-запад | S351: Двор | T351: Стандарт | U351: 40 | V351: =IFERROR(VLOOKUP(H351,'Коэфф для прайса 1 оч'!$A$3:$C$6,3,0),"") -> 327000 | W351: =IFERROR(VLOOKUP(E351,'Коэфф для прайса 1 оч'!$A$10:$C$23,3,0),"") -> 0 | X351: =IFERROR(VLOOKUP(N351,'Коэфф для прайса 1 оч'!$E$25:$F$30,2,0),"") -> 0.04 | Y351: =IFERROR(VLOOKUP(O351,'Коэфф для прайса 1 оч'!$E$32:$F$34,2,0),"") -> 0 | Z351: =IFERROR(VLOOKUP(P351,'Коэфф для прайса 1 оч'!$E$36:$F$38,2,0),"") -> 0.03 | AA351: =IFERROR(VLOOKUP(Q351,'Коэфф для прайса 1 оч'!$E$40:$F$43,2,0),"") -> 0.005 | AB351: =IFERROR(VLOOKUP(R351,'Коэфф для прайса 1 оч'!$E$45:$F$59,2,0),"") -> 0.02 | AC351: =IFERROR(VLOOKUP(T351,'Коэфф для прайса 1 оч'!$E$61:$F$67,2,0),"") -> 0 | AD351: =IFERROR(VLOOKUP(U351,'Коэфф для прайса 1 оч'!$E$69:$F$82,2,0),"") -> -0.014 | AE351: =IFERROR(VLOOKUP(PriceList[[#This Row],[Корпус]],'Коэфф для прайса 1 оч'!$I$10:$J$15,2,0),"") -> 0.12 | AF351: =ROUND(V351+(V351*SUM(W351:AE351)),2) -> 392727 | AG351: =AF351*G351 -> 11385156 | AH351: 0 | AI351: =AF351+AF351*AH351 -> 392727 | AJ351: =AI351*G351 -> 11385156 | AK351: Резерв | AL351: 0.1 | AM351: =PriceList[[#This Row],[ИТОГ Цена за кв.м, руб]]*(1+PriceList[[#This Row],[Максимальная скидка]]) -> 431999.7 | AN351: =PriceList[[#This Row],[Цена за кв.м. в CRM]]*PriceList[[#This Row],[Площадь, кв.м]] -> 12523671 | AO351: 6000 | AP351: =PriceList[[#This Row],[Цена за кв.м. в CRM]]+PriceList[[#This Row],[Бронь]] -> 437999.7 | AQ351: =PriceList[[#This Row],[Цена за кв.м. в сайт]]*PriceList[[#This Row],[Площадь, кв.м]] -> 12697611 | AR351: =B351 -> С2-119 | AS351: =H351 -> Ст | AT351: =G351 -> 28.99 | AU351: =PriceList[[#This Row],[Цена за кв.м. в CRM]] -> 431999.7 | AV351: =AK351 -> Резерв | AZ351: =(PriceList[[#This Row],[Цена за кв.м. в сайт]])+$AZ$1 -> 438499.7 | BA351: =AZ351*PriceList[[#This Row],[Площадь, кв.м]] -> 12712106 | BB351: =BA351-PriceList[[#This Row],[Стоимость, руб для сбронированием]] -> 14495 | BD351: =MROUND(AZ351,100) -> 438500 | BE351: =BD351*PriceList[[#This Row],[Площадь, кв.м]] -> 12712115 | BG351: =BE351-$BG$1*PriceList[[#This Row],[Площадь, кв.м]] -> 12538175 | BH351: =BE351-BG351 -> 173940 | BI351: =BG351/PriceList[[#This Row],[Площадь, кв.м]] -> 432500 | BJ351: =BH351/BG351 -> 0.013872832 | BL351: =BI351-10%*BI351 -> 389250 | BM351: =BL351*G351 -> 11284358
A352: 338 | B352: С2-12 | C352: 12 | D352: С2 | E352: 1 | F352: 12 | G352: 43.32 | H352: Ст | I352: Ст | J352: 4.3 | K352: =ROUND(J352*0.3,2) -> 1.29 | L352: =G352-J352 -> 39.02 | M352: =L352+K352 -> 40.31 | N352: XL | O352: Линейная | P352: Неправильная | Q352: Зона 1 | R352: Двор юг | S352: Двор | T352: Внутренний угол | U352: 34 | V352: =IFERROR(VLOOKUP(H352,'Коэфф для прайса 1 оч'!$A$3:$C$6,3,0),"") -> 327000 | W352: =IFERROR(VLOOKUP(E352,'Коэфф для прайса 1 оч'!$A$10:$C$23,3,0),"") -> -0.045 | X352: =IFERROR(VLOOKUP(N352,'Коэфф для прайса 1 оч'!$E$25:$F$30,2,0),"") -> -0.02 | Y352: =IFERROR(VLOOKUP(O352,'Коэфф для прайса 1 оч'!$E$32:$F$34,2,0),"") -> 0 | Z352: =IFERROR(VLOOKUP(P352,'Коэфф для прайса 1 оч'!$E$36:$F$38,2,0),"") -> 0 | AA352: =IFERROR(VLOOKUP(Q352,'Коэфф для прайса 1 оч'!$E$40:$F$43,2,0),"") -> 0.005 | AB352: =IFERROR(VLOOKUP(R352,'Коэфф для прайса 1 оч'!$E$45:$F$59,2,0),"") -> 0 | AC352: =IFERROR(VLOOKUP(T352,'Коэфф для прайса 1 оч'!$E$61:$F$67,2,0),"") -> -0.01 | AD352: =IFERROR(VLOOKUP(U352,'Коэфф для прайса 1 оч'!$E$69:$F$82,2,0),"") -> -0.008 | AE352: =IFERROR(VLOOKUP(PriceList[[#This Row],[Корпус]],'Коэфф для прайса 1 оч'!$I$10:$J$15,2,0),"") -> 0.12 | AF352: =ROUND(V352+(V352*SUM(W352:AE352)),2) -> 340734 | AG352: =AF352*G352 -> 14760597 | AH352: 0 | AI352: =AF352+AF352*AH352 -> 340734 | AJ352: =AI352*G352 -> 14760597 | AK352: Свободно | AL352: 0.1 | AM352: =PriceList[[#This Row],[ИТОГ Цена за кв.м, руб]]*(1+PriceList[[#This Row],[Максимальная скидка]]) -> 374807.4 | AN352: =PriceList[[#This Row],[Цена за кв.м. в CRM]]*PriceList[[#This Row],[Площадь, кв.м]] -> 16236657 | AO352: 6000 | AP352: =PriceList[[#This Row],[Цена за кв.м. в CRM]]+PriceList[[#This Row],[Бронь]] -> 380807.4 | AQ352: =PriceList[[#This Row],[Цена за кв.м. в сайт]]*PriceList[[#This Row],[Площадь, кв.м]] -> 16496577 | AR352: =B352 -> С2-12 | AS352: =H352 -> Ст | AT352: =G352 -> 43.32 | AU352: =PriceList[[#This Row],[Цена за кв.м. в CRM]] -> 374807.4 | AV352: =AK352 -> Свободно | AZ352: =(PriceList[[#This Row],[Цена за кв.м. в сайт]])+$AZ$1 -> 381307.4 | BA352: =AZ352*PriceList[[#This Row],[Площадь, кв.м]] -> 16518237 | BB352: =BA352-PriceList[[#This Row],[Стоимость, руб для сбронированием]] -> 21660 | BD352: =MROUND(AZ352,100) -> 381300 | BE352: =BD352*PriceList[[#This Row],[Площадь, кв.м]] -> 16517916 | BG352: =BE352-$BG$1*PriceList[[#This Row],[Площадь, кв.м]] -> 16257996 | BH352: =BE352-BG352 -> 259920 | BI352: =BG352/PriceList[[#This Row],[Площадь, кв.м]] -> 375300 | BJ352: =BH352/BG352 -> 0.01598721 | BL352: =BI352-10%*BI352 -> 337770 | BM352: =BL352*G352 -> 14632196
A353: 446 | B353: С2-120 | C353: 120 | D353: С2 | E353: 4 | F353: 8 | G353: 28.53 | H353: Ст | I353: Ст | J353: 3.79 | K353: =ROUND(J353*0.3,2) -> 1.14 | L353: =G353-J353 -> 24.74 | M353: =L353+K353 -> 25.88 | N353: S | O353: Линейная | P353: Правильная | Q353: Зона 1 | R353: Двор юго-запад | S353: Двор | T353: Стандарт | U353: 40 | V353: =IFERROR(VLOOKUP(H353,'Коэфф для прайса 1 оч'!$A$3:$C$6,3,0),"") -> 327000 | W353: =IFERROR(VLOOKUP(E353,'Коэфф для прайса 1 оч'!$A$10:$C$23,3,0),"") -> 0 | X353: =IFERROR(VLOOKUP(N353,'Коэфф для прайса 1 оч'!$E$25:$F$30,2,0),"") -> 0.04 | Y353: =IFERROR(VLOOKUP(O353,'Коэфф для прайса 1 оч'!$E$32:$F$34,2,0),"") -> 0 | Z353: =IFERROR(VLOOKUP(P353,'Коэфф для прайса 1 оч'!$E$36:$F$38,2,0),"") -> 0.03 | AA353: =IFERROR(VLOOKUP(Q353,'Коэфф для прайса 1 оч'!$E$40:$F$43,2,0),"") -> 0.005 | AB353: =IFERROR(VLOOKUP(R353,'Коэфф для прайса 1 оч'!$E$45:$F$59,2,0),"") -> 0.02 | AC353: =IFERROR(VLOOKUP(T353,'Коэфф для прайса 1 оч'!$E$61:$F$67,2,0),"") -> 0 | AD353: =IFERROR(VLOOKUP(U353,'Коэфф для прайса 1 оч'!$E$69:$F$82,2,0),"") -> -0.014 | AE353: =IFERROR(VLOOKUP(PriceList[[#This Row],[Корпус]],'Коэфф для прайса 1 оч'!$I$10:$J$15,2,0),"") -> 0.12 | AF353: =ROUND(V353+(V353*SUM(W353:AE353)),2) -> 392727 | AG353: =AF353*G353 -> 11204501 | AH353: 0 | AI353: =AF353+AF353*AH353 -> 392727 | AJ353: =AI353*G353 -> 11204501 | AK353: Свободно | AL353: 0.1 | AM353: =PriceList[[#This Row],[ИТОГ Цена за кв.м, руб]]*(1+PriceList[[#This Row],[Максимальная скидка]]) -> 431999.7 | AN353: =PriceList[[#This Row],[Цена за кв.м. в CRM]]*PriceList[[#This Row],[Площадь, кв.м]] -> 12324951 | AO353: 6000 | AP353: =PriceList[[#This Row],[Цена за кв.м. в CRM]]+PriceList[[#This Row],[Бронь]] -> 437999.7 | AQ353: =PriceList[[#This Row],[Цена за кв.м. в сайт]]*PriceList[[#This Row],[Площадь, кв.м]] -> 12496131 | AR353: =B353 -> С2-120 | AS353: =H353 -> Ст | AT353: =G353 -> 28.53 | AU353: =PriceList[[#This Row],[Цена за кв.м. в CRM]] -> 431999.7 | AV353: =AK353 -> Свободно | AZ353: =(PriceList[[#This Row],[Цена за кв.м. в сайт]])+$AZ$1 -> 438499.7 | BA353: =AZ353*PriceList[[#This Row],[Площадь, кв.м]] -> 12510396 | BB353: =BA353-PriceList[[#This Row],[Стоимость, руб для сбронированием]] -> 14265 | BD353: =MROUND(AZ353,100) -> 438500 | BE353: =BD353*PriceList[[#This Row],[Площадь, кв.м]] -> 12510405 | BG353: =BE353-$BG$1*PriceList[[#This Row],[Площадь, кв.м]] -> 12339225 | BH353: =BE353-BG353 -> 171180 | BI353: =BG353/PriceList[[#This Row],[Площадь, кв.м]] -> 432500 | BJ353: =BH353/BG353 -> 0.013872832 | BL353: =BI353-10%*BI353 -> 389250 | BM353: =BL353*G353 -> 11105302
A354: 447 | B354: С2-121 | C354: 121 | D354: С2 | E354: 4 | F354: 9 | G354: 28.99 | H354: Ст | I354: Ст | J354: 4.25 | K354: =ROUND(J354*0.3,2) -> 1.28 | L354: =G354-J354 -> 24.74 | M354: =L354+K354 -> 26.02 | N354: S | O354: Линейная | P354: Правильная | Q354: Зона 1 | R354: Двор юго-запад | S354: Двор | T354: У входа в лифтовый холл | U354: 40 | V354: =IFERROR(VLOOKUP(H354,'Коэфф для прайса 1 оч'!$A$3:$C$6,3,0),"") -> 327000 | W354: =IFERROR(VLOOKUP(E354,'Коэфф для прайса 1 оч'!$A$10:$C$23,3,0),"") -> 0 | X354: =IFERROR(VLOOKUP(N354,'Коэфф для прайса 1 оч'!$E$25:$F$30,2,0),"") -> 0.04 | Y354: =IFERROR(VLOOKUP(O354,'Коэфф для прайса 1 оч'!$E$32:$F$34,2,0),"") -> 0 | Z354: =IFERROR(VLOOKUP(P354,'Коэфф для прайса 1 оч'!$E$36:$F$38,2,0),"") -> 0.03 | AA354: =IFERROR(VLOOKUP(Q354,'Коэфф для прайса 1 оч'!$E$40:$F$43,2,0),"") -> 0.005 | AB354: =IFERROR(VLOOKUP(R354,'Коэфф для прайса 1 оч'!$E$45:$F$59,2,0),"") -> 0.02 | AC354: =IFERROR(VLOOKUP(T354,'Коэфф для прайса 1 оч'!$E$61:$F$67,2,0),"") -> -0.01 | AD354: =IFERROR(VLOOKUP(U354,'Коэфф для прайса 1 оч'!$E$69:$F$82,2,0),"") -> -0.014 | AE354: =IFERROR(VLOOKUP(PriceList[[#This Row],[Корпус]],'Коэфф для прайса 1 оч'!$I$10:$J$15,2,0),"") -> 0.12 | AF354: =ROUND(V354+(V354*SUM(W354:AE354)),2) -> 389457 | AG354: =AF354*G354 -> 11290358 | AH354: 0 | AI354: =AF354+AF354*AH354 -> 389457 | AJ354: =AI354*G354 -> 11290358 | AK354: Свободно | AL354: 0.1 | AM354: =PriceList[[#This Row],[ИТОГ Цена за кв.м, руб]]*(1+PriceList[[#This Row],[Максимальная скидка]]) -> 428402.7 | AN354: =PriceList[[#This Row],[Цена за кв.м. в CRM]]*PriceList[[#This Row],[Площадь, кв.м]] -> 12419394 | AO354: 6000 | AP354: =PriceList[[#This Row],[Цена за кв.м. в CRM]]+PriceList[[#This Row],[Бронь]] -> 434402.7 | AQ354: =PriceList[[#This Row],[Цена за кв.м. в сайт]]*PriceList[[#This Row],[Площадь, кв.м]] -> 12593334 | AR354: =B354 -> С2-121 | AS354: =H354 -> Ст | AT354: =G354 -> 28.99 | AU354: =PriceList[[#This Row],[Цена за кв.м. в CRM]] -> 428402.7 | AV354: =AK354 -> Свободно | AZ354: =(PriceList[[#This Row],[Цена за кв.м. в сайт]])+$AZ$1 -> 434902.7 | BA354: =AZ354*PriceList[[#This Row],[Площадь, кв.м]] -> 12607829 | BB354: =BA354-PriceList[[#This Row],[Стоимость, руб для сбронированием]] -> 14495 | BD354: =MROUND(AZ354,100) -> 434900 | BE354: =BD354*PriceList[[#This Row],[Площадь, кв.м]] -> 12607751 | BG354: =BE354-$BG$1*PriceList[[#This Row],[Площадь, кв.м]] -> 12433811 | BH354: =BE354-BG354 -> 173940 | BI354: =BG354/PriceList[[#This Row],[Площадь, кв.м]] -> 428900 | BJ354: =BH354/BG354 -> 0.013989275 | BL354: =BI354-10%*BI354 -> 386010 | BM354: =BL354*G354 -> 11190430
A355: 448 | B355: С2-122 | C355: 122 | D355: С2 | E355: 4 | F355: 10 | G355: 28.99 | H355: Ст | I355: Ст | J355: 4.25 | K355: =ROUND(J355*0.3,2) -> 1.28 | L355: =G355-J355 -> 24.74 | M355: =L355+K355 -> 26.02 | N355: S | O355: Линейная | P355: Правильная | Q355: Зона 1 | R355: Двор юго-запад | S355: Двор | T355: У входа в лифтовый холл | U355: 40 | V355: =IFERROR(VLOOKUP(H355,'Коэфф для прайса 1 оч'!$A$3:$C$6,3,0),"") -> 327000 | W355: =IFERROR(VLOOKUP(E355,'Коэфф для прайса 1 оч'!$A$10:$C$23,3,0),"") -> 0 | X355: =IFERROR(VLOOKUP(N355,'Коэфф для прайса 1 оч'!$E$25:$F$30,2,0),"") -> 0.04 | Y355: =IFERROR(VLOOKUP(O355,'Коэфф для прайса 1 оч'!$E$32:$F$34,2,0),"") -> 0 | Z355: =IFERROR(VLOOKUP(P355,'Коэфф для прайса 1 оч'!$E$36:$F$38,2,0),"") -> 0.03 | AA355: =IFERROR(VLOOKUP(Q355,'Коэфф для прайса 1 оч'!$E$40:$F$43,2,0),"") -> 0.005 | AB355: =IFERROR(VLOOKUP(R355,'Коэфф для прайса 1 оч'!$E$45:$F$59,2,0),"") -> 0.02 | AC355: =IFERROR(VLOOKUP(T355,'Коэфф для прайса 1 оч'!$E$61:$F$67,2,0),"") -> -0.01 | AD355: =IFERROR(VLOOKUP(U355,'Коэфф для прайса 1 оч'!$E$69:$F$82,2,0),"") -> -0.014 | AE355: =IFERROR(VLOOKUP(PriceList[[#This Row],[Корпус]],'Коэфф для прайса 1 оч'!$I$10:$J$15,2,0),"") -> 0.12 | AF355: =ROUND(V355+(V355*SUM(W355:AE355)),2) -> 389457 | AG355: =AF355*G355 -> 11290358 | AH355: 0 | AI355: =AF355+AF355*AH355 -> 389457 | AJ355: =AI355*G355 -> 11290358 | AK355: Свободно | AL355: 0.1 | AM355: =PriceList[[#This Row],[ИТОГ Цена за кв.м, руб]]*(1+PriceList[[#This Row],[Максимальная скидка]]) -> 428402.7 | AN355: =PriceList[[#This Row],[Цена за кв.м. в CRM]]*PriceList[[#This Row],[Площадь, кв.м]] -> 12419394 | AO355: 6000 | AP355: =PriceList[[#This Row],[Цена за кв.м. в CRM]]+PriceList[[#This Row],[Бронь]] -> 434402.7 | AQ355: =PriceList[[#This Row],[Цена за кв.м. в сайт]]*PriceList[[#This Row],[Площадь, кв.м]] -> 12593334 | AR355: =B355 -> С2-122 | AS355: =H355 -> Ст | AT355: =G355 -> 28.99 | AU355: =PriceList[[#This Row],[Цена за кв.м. в CRM]] -> 428402.7 | AV355: =AK355 -> Свободно | AZ355: =(PriceList[[#This Row],[Цена за кв.м. в сайт]])+$AZ$1 -> 434902.7 | BA355: =AZ355*PriceList[[#This Row],[Площадь, кв.м]] -> 12607829 | BB355: =BA355-PriceList[[#This Row],[Стоимость, руб для сбронированием]] -> 14495 | BD355: =MROUND(AZ355,100) -> 434900 | BE355: =BD355*PriceList[[#This Row],[Площадь, кв.м]] -> 12607751 | BG355: =BE355-$BG$1*PriceList[[#This Row],[Площадь, кв.м]] -> 12433811 | BH355: =BE355-BG355 -> 173940 | BI355: =BG355/PriceList[[#This Row],[Площадь, кв.м]] -> 428900 | BJ355: =BH355/BG355 -> 0.013989275 | BL355: =BI355-10%*BI355 -> 386010 | BM355: =BL355*G355 -> 11190430
A356: 449 | B356: С2-123 | C356: 123 | D356: С2 | E356: 4 | F356: 11 | G356: 28.99 | H356: Ст | I356: Ст | J356: 4.25 | K356: =ROUND(J356*0.3,2) -> 1.28 | L356: =G356-J356 -> 24.74 | M356: =L356+K356 -> 26.02 | N356: S | O356: Линейная | P356: Правильная | Q356: Зона 1 | R356: Двор юго-запад | S356: Двор | T356: Стандарт | U356: 40 | V356: =IFERROR(VLOOKUP(H356,'Коэфф для прайса 1 оч'!$A$3:$C$6,3,0),"") -> 327000 | W356: =IFERROR(VLOOKUP(E356,'Коэфф для прайса 1 оч'!$A$10:$C$23,3,0),"") -> 0 | X356: =IFERROR(VLOOKUP(N356,'Коэфф для прайса 1 оч'!$E$25:$F$30,2,0),"") -> 0.04 | Y356: =IFERROR(VLOOKUP(O356,'Коэфф для прайса 1 оч'!$E$32:$F$34,2,0),"") -> 0 | Z356: =IFERROR(VLOOKUP(P356,'Коэфф для прайса 1 оч'!$E$36:$F$38,2,0),"") -> 0.03 | AA356: =IFERROR(VLOOKUP(Q356,'Коэфф для прайса 1 оч'!$E$40:$F$43,2,0),"") -> 0.005 | AB356: =IFERROR(VLOOKUP(R356,'Коэфф для прайса 1 оч'!$E$45:$F$59,2,0),"") -> 0.02 | AC356: =IFERROR(VLOOKUP(T356,'Коэфф для прайса 1 оч'!$E$61:$F$67,2,0),"") -> 0 | AD356: =IFERROR(VLOOKUP(U356,'Коэфф для прайса 1 оч'!$E$69:$F$82,2,0),"") -> -0.014 | AE356: =IFERROR(VLOOKUP(PriceList[[#This Row],[Корпус]],'Коэфф для прайса 1 оч'!$I$10:$J$15,2,0),"") -> 0.12 | AF356: =ROUND(V356+(V356*SUM(W356:AE356)),2) -> 392727 | AG356: =AF356*G356 -> 11385156 | AH356: 0 | AI356: =AF356+AF356*AH356 -> 392727 | AJ356: =AI356*G356 -> 11385156 | AK356: Свободно | AL356: 0.1 | AM356: =PriceList[[#This Row],[ИТОГ Цена за кв.м, руб]]*(1+PriceList[[#This Row],[Максимальная скидка]]) -> 431999.7 | AN356: =PriceList[[#This Row],[Цена за кв.м. в CRM]]*PriceList[[#This Row],[Площадь, кв.м]] -> 12523671 | AO356: 6000 | AP356: =PriceList[[#This Row],[Цена за кв.м. в CRM]]+PriceList[[#This Row],[Бронь]] -> 437999.7 | AQ356: =PriceList[[#This Row],[Цена за кв.м. в сайт]]*PriceList[[#This Row],[Площадь, кв.м]] -> 12697611 | AR356: =B356 -> С2-123 | AS356: =H356 -> Ст | AT356: =G356 -> 28.99 | AU356: =PriceList[[#This Row],[Цена за кв.м. в CRM]] -> 431999.7 | AV356: =AK356 -> Свободно | AZ356: =(PriceList[[#This Row],[Цена за кв.м. в сайт]])+$AZ$1 -> 438499.7 | BA356: =AZ356*PriceList[[#This Row],[Площадь, кв.м]] -> 12712106 | BB356: =BA356-PriceList[[#This Row],[Стоимость, руб для сбронированием]] -> 14495 | BD356: =MROUND(AZ356,100) -> 438500 | BE356: =BD356*PriceList[[#This Row],[Площадь, кв.м]] -> 12712115 | BG356: =BE356-$BG$1*PriceList[[#This Row],[Площадь, кв.м]] -> 12538175 | BH356: =BE356-BG356 -> 173940 | BI356: =BG356/PriceList[[#This Row],[Площадь, кв.м]] -> 432500 | BJ356: =BH356/BG356 -> 0.013872832 | BL356: =BI356-10%*BI356 -> 389250 | BM356: =BL356*G356 -> 11284358
... A387: 477 | B387: С2-151 | C387: 151 | D387: С2 | E387: 4 | F387: 39 | G387: 28.41 | H387: Ст | I387: Ст | J387: 3.68 | K387: =ROUND(J387*0.3,2) -> 1.1 | L387: =G387-J387 -> 24.73 | M387: =L387+K387 -> 25.83 | N387: S | O387: Линейная | P387: Правильная | Q387: Зона 1 | R387: Озеро | S387: Озеро | T387: Стандарт | U387: 40 | V387: =IFERROR(VLOOKUP(H387,'Коэфф для прайса 1 оч'!$A$3:$C$6,3,0),"") -> 327000 | W387: =IFERROR(VLOOKUP(E387,'Коэфф для прайса 1 оч'!$A$10:$C$23,3,0),"") -> 0 | X387: =IFERROR(VLOOKUP(N387,'Коэфф для прайса 1 оч'!$E$25:$F$30,2,0),"") -> 0.04 | Y387: =IFERROR(VLOOKUP(O387,'Коэфф для прайса 1 оч'!$E$32:$F$34,2,0),"") -> 0 | Z387: =IFERROR(VLOOKUP(P387,'Коэфф для прайса 1 оч'!$E$36:$F$38,2,0),"") -> 0.03 | AA387: =IFERROR(VLOOKUP(Q387,'Коэфф для прайса 1 оч'!$E$40:$F$43,2,0),"") -> 0.005 | AB387: =IFERROR(VLOOKUP(R387,'Коэфф для прайса 1 оч'!$E$45:$F$59,2,0),"") -> 0.03 | AC387: =IFERROR(VLOOKUP(T387,'Коэфф для прайса 1 оч'!$E$61:$F$67,2,0),"") -> 0 | AD387: =IFERROR(VLOOKUP(U387,'Коэфф для прайса 1 оч'!$E$69:$F$82,2,0),"") -> -0.014 | AE387: =IFERROR(VLOOKUP(PriceList[[#This Row],[Корпус]],'Коэфф для прайса 1 оч'!$I$10:$J$15,2,0),"") -> 0.12 | AF387: =ROUND(V387+(V387*SUM(W387:AE387)),2) -> 395997 | AG387: =AF387*G387 -> 11250275 | AH387: 0 | AI387: =AF387+AF387*AH387 -> 395997 | AJ387: =AI387*G387 -> 11250275 | AK387: Свободно | AL387: 0.1 | AM387: =PriceList[[#This Row],[ИТОГ Цена за кв.м, руб]]*(1+PriceList[[#This Row],[Максимальная скидка]]) -> 435596.7 | AN387: =PriceList[[#This Row],[Цена за кв.м. в CRM]]*PriceList[[#This Row],[Площадь, кв.м]] -> 12375302 | AO387: 6000 | AP387: =PriceList[[#This Row],[Цена за кв.м. в CRM]]+PriceList[[#This Row],[Бронь]] -> 441596.7 | AQ387: =PriceList[[#This Row],[Цена за кв.м. в сайт]]*PriceList[[#This Row],[Площадь, кв.м]] -> 12545762 | AR387: =B387 -> С2-151 | AS387: =H387 -> Ст | AT387: =G387 -> 28.41 | AU387: =PriceList[[#This Row],[Цена за кв.м. в CRM]] -> 435596.7 | AV387: =AK387 -> Свободно | AZ387: =(PriceList[[#This Row],[Цена за кв.м. в сайт]])+$AZ$1 -> 442096.7 | BA387: =AZ387*PriceList[[#This Row],[Площадь, кв.м]] -> 12559967 | BB387: =BA387-PriceList[[#This Row],[Стоимость, руб для сбронированием]] -> 14205 | BD387: =MROUND(AZ387,100) -> 442100 | BE387: =BD387*PriceList[[#This Row],[Площадь, кв.м]] -> 12560061 | BG387: =BE387-$BG$1*PriceList[[#This Row],[Площадь, кв.м]] -> 12389601 | BH387: =BE387-BG387 -> 170460 | BI387: =BG387/PriceList[[#This Row],[Площадь, кв.м]] -> 436100 | BJ387: =BH387/BG387 -> 0.013758312 | BL387: =BI387-10%*BI387 -> 392490 | BM387: =BL387*G387 -> 11150641
A388: 478 | B388: С2-152 | C388: 152 | D388: С2 | E388: 4 | F388: 40 | G388: 28.7 | H388: Ст | I388: Ст | J388: 4.11 | K388: =ROUND(J388*0.3,2) -> 1.23 | L388: =G388-J388 -> 24.59 | M388: =L388+K388 -> 25.82 | N388: S | O388: Линейная | P388: Правильная | Q388: Зона 1 | R388: Озеро | S388: Озеро | T388: Стандарт | U388: 40 | V388: =IFERROR(VLOOKUP(H388,'Коэфф для прайса 1 оч'!$A$3:$C$6,3,0),"") -> 327000 | W388: =IFERROR(VLOOKUP(E388,'Коэфф для прайса 1 оч'!$A$10:$C$23,3,0),"") -> 0 | X388: =IFERROR(VLOOKUP(N388,'Коэфф для прайса 1 оч'!$E$25:$F$30,2,0),"") -> 0.04 | Y388: =IFERROR(VLOOKUP(O388,'Коэфф для прайса 1 оч'!$E$32:$F$34,2,0),"") -> 0 | Z388: =IFERROR(VLOOKUP(P388,'Коэфф для прайса 1 оч'!$E$36:$F$38,2,0),"") -> 0.03 | AA388: =IFERROR(VLOOKUP(Q388,'Коэфф для прайса 1 оч'!$E$40:$F$43,2,0),"") -> 0.005 | AB388: =IFERROR(VLOOKUP(R388,'Коэфф для прайса 1 оч'!$E$45:$F$59,2,0),"") -> 0.03 | AC388: =IFERROR(VLOOKUP(T388,'Коэфф для прайса 1 оч'!$E$61:$F$67,2,0),"") -> 0 | AD388: =IFERROR(VLOOKUP(U388,'Коэфф для прайса 1 оч'!$E$69:$F$82,2,0),"") -> -0.014 | AE388: =IFERROR(VLOOKUP(PriceList[[#This Row],[Корпус]],'Коэфф для прайса 1 оч'!$I$10:$J$15,2,0),"") -> 0.12 | AF388: =ROUND(V388+(V388*SUM(W388:AE388)),2) -> 395997 | AG388: =AF388*G388 -> 11365114 | AH388: 0 | AK388: Не для продажи | AL388: 0.1 | AM388: =PriceList[[#This Row],[ИТОГ Цена за кв.м, руб]]*(1+PriceList[[#This Row],[Максимальная скидка]]) -> 0 | AN388: =PriceList[[#This Row],[Цена за кв.м. в CRM]]*PriceList[[#This Row],[Площадь, кв.м]] -> 0 | AO388: 6000 | AP388: =PriceList[[#This Row],[Цена за кв.м. в CRM]]+PriceList[[#This Row],[Бронь]] -> 6000 | AQ388: =PriceList[[#This Row],[Цена за кв.м. в сайт]]*PriceList[[#This Row],[Площадь, кв.м]] -> 172200 | AR388: =B388 -> С2-152 | AS388: =H388 -> Ст | AT388: =G388 -> 28.7 | AU388: =PriceList[[#This Row],[Цена за кв.м. в CRM]] -> 0 | AV388: =AK388 -> Не для продажи | BD388: =MROUND(AZ388,100) -> 0 | BE388: =BD388*PriceList[[#This Row],[Площадь, кв.м]] -> 0 | BH388: =BE388-BG388 -> 0 | BI388: =BG388/PriceList[[#This Row],[Площадь, кв.м]] -> 0 | BJ388: =BH388/BG388 -> #DIV/0! | BL388: =BI388-10%*BI388 -> 0 | BM388: =BL388*G388 -> 0
A389: 479 | B389: С2-153 | C389: 153 | D389: С2 | E389: 5 | F389: 1 | G389: 37.46 | H389: Ст | I389: Ст | J389: 7.24 | K389: =ROUND(J389*0.3,2) -> 2.17 | L389: =G389-J389 -> 30.22 | M389: =L389+K389 -> 32.39 | N389: M | O389: Линейная | P389: Правильная | Q389: Зона 1 | R389: Озеро | S389: Озеро | T389: Стандарт | U389: 40 | V389: =IFERROR(VLOOKUP(H389,'Коэфф для прайса 1 оч'!$A$3:$C$6,3,0),"") -> 327000 | W389: =IFERROR(VLOOKUP(E389,'Коэфф для прайса 1 оч'!$A$10:$C$23,3,0),"") -> 0.005 | X389: =IFERROR(VLOOKUP(N389,'Коэфф для прайса 1 оч'!$E$25:$F$30,2,0),"") -> 0 | Y389: =IFERROR(VLOOKUP(O389,'Коэфф для прайса 1 оч'!$E$32:$F$34,2,0),"") -> 0 | Z389: =IFERROR(VLOOKUP(P389,'Коэфф для прайса 1 оч'!$E$36:$F$38,2,0),"") -> 0.03 | AA389: =IFERROR(VLOOKUP(Q389,'Коэфф для прайса 1 оч'!$E$40:$F$43,2,0),"") -> 0.005 | AB389: =IFERROR(VLOOKUP(R389,'Коэфф для прайса 1 оч'!$E$45:$F$59,2,0),"") -> 0.03 | AC389: =IFERROR(VLOOKUP(T389,'Коэфф для прайса 1 оч'!$E$61:$F$67,2,0),"") -> 0 | AD389: =IFERROR(VLOOKUP(U389,'Коэфф для прайса 1 оч'!$E$69:$F$82,2,0),"") -> -0.014 | AE389: =IFERROR(VLOOKUP(PriceList[[#This Row],[Корпус]],'Коэфф для прайса 1 оч'!$I$10:$J$15,2,0),"") -> 0.12 | AF389: =ROUND(V389+(V389*SUM(W389:AE389)),2) -> 384552 | AG389: =AF389*G389 -> 14405318 | AH389: 0 | AI389: =AF389+AF389*AH389 -> 384552 | AJ389: =AI389*G389 -> 14405318 | AK389: Резерв | AL389: 0.1 | AM389: =PriceList[[#This Row],[ИТОГ Цена за кв.м, руб]]*(1+PriceList[[#This Row],[Максимальная скидка]]) -> 423007.2 | AN389: =PriceList[[#This Row],[Цена за кв.м. в CRM]]*PriceList[[#This Row],[Площадь, кв.м]] -> 15845850 | AO389: 6000 | AP389: =PriceList[[#This Row],[Цена за кв.м. в CRM]]+PriceList[[#This Row],[Бронь]] -> 429007.2 | AQ389: =PriceList[[#This Row],[Цена за кв.м. в сайт]]*PriceList[[#This Row],[Площадь, кв.м]] -> 16070610 | AR389: =B389 -> С2-153 | AS389: =H389 -> Ст | AT389: =G389 -> 37.46 | AU389: =PriceList[[#This Row],[Цена за кв.м. в CRM]] -> 423007.2 | AV389: =AK389 -> Резерв | AZ389: =(PriceList[[#This Row],[Цена за кв.м. в сайт]])+$AZ$1 -> 429507.2 | BA389: =AZ389*PriceList[[#This Row],[Площадь, кв.м]] -> 16089340 | BB389: =BA389-PriceList[[#This Row],[Стоимость, руб для сбронированием]] -> 18730 | BD389: =MROUND(AZ389,100) -> 429500 | BE389: =BD389*PriceList[[#This Row],[Площадь, кв.м]] -> 16089070 | BG389: =BE389-$BG$1*PriceList[[#This Row],[Площадь, кв.м]] -> 15864310 | BH389: =BE389-BG389 -> 224760 | BI389: =BG389/PriceList[[#This Row],[Площадь, кв.м]] -> 423500 | BJ389: =BH389/BG389 -> 0.014167651 | BL389: =BI389-10%*BI389 -> 381150 | BM389: =BL389*G389 -> 14277879
A390: 480 | B390: С2-154 | C390: 154 | D390: С2 | E390: 5 | F390: 2 | G390: 28.98 | H390: Ст | I390: Ст | J390: 4.25 | K390: =ROUND(J390*0.3,2) -> 1.28 | L390: =G390-J390 -> 24.73 | M390: =L390+K390 -> 26.01 | N390: S | O390: Линейная | P390: Правильная | Q390: Зона 1 | R390: Озеро | S390: Озеро | T390: Стандарт | U390: 40 | V390: =IFERROR(VLOOKUP(H390,'Коэфф для прайса 1 оч'!$A$3:$C$6,3,0),"") -> 327000 | W390: =IFERROR(VLOOKUP(E390,'Коэфф для прайса 1 оч'!$A$10:$C$23,3,0),"") -> 0.005 | X390: =IFERROR(VLOOKUP(N390,'Коэфф для прайса 1 оч'!$E$25:$F$30,2,0),"") -> 0.04 | Y390: =IFERROR(VLOOKUP(O390,'Коэфф для прайса 1 оч'!$E$32:$F$34,2,0),"") -> 0 | Z390: =IFERROR(VLOOKUP(P390,'Коэфф для прайса 1 оч'!$E$36:$F$38,2,0),"") -> 0.03 | AA390: =IFERROR(VLOOKUP(Q390,'Коэфф для прайса 1 оч'!$E$40:$F$43,2,0),"") -> 0.005 | AB390: =IFERROR(VLOOKUP(R390,'Коэфф для прайса 1 оч'!$E$45:$F$59,2,0),"") -> 0.03 | AC390: =IFERROR(VLOOKUP(T390,'Коэфф для прайса 1 оч'!$E$61:$F$67,2,0),"") -> 0 | AD390: =IFERROR(VLOOKUP(U390,'Коэфф для прайса 1 оч'!$E$69:$F$82,2,0),"") -> -0.014 | AE390: =IFERROR(VLOOKUP(PriceList[[#This Row],[Корпус]],'Коэфф для прайса 1 оч'!$I$10:$J$15,2,0),"") -> 0.12 | AF390: =ROUND(V390+(V390*SUM(W390:AE390)),2) -> 397632 | AG390: =AF390*G390 -> 11523375 | AH390: 0 | AI390: =AF390+AF390*AH390 -> 397632 | AJ390: =AI390*G390 -> 11523375 | AK390: Резерв | AL390: 0.1 | AM390: =PriceList[[#This Row],[ИТОГ Цена за кв.м, руб]]*(1+PriceList[[#This Row],[Максимальная скидка]]) -> 437395.2 | AN390: =PriceList[[#This Row],[Цена за кв.м. в CRM]]*PriceList[[#This Row],[Площадь, кв.м]] -> 12675713 | AO390: 6000 | AP390: =PriceList[[#This Row],[Цена за кв.м. в CRM]]+PriceList[[#This Row],[Бронь]] -> 443395.2 | AQ390: =PriceList[[#This Row],[Цена за кв.м. в сайт]]*PriceList[[#This Row],[Площадь, кв.м]] -> 12849593 | AR390: =B390 -> С2-154 | AS390: =H390 -> Ст | AT390: =G390 -> 28.98 | AU390: =PriceList[[#This Row],[Цена за кв.м. в CRM]] -> 437395.2 | AV390: =AK390 -> Резерв | AZ390: =(PriceList[[#This Row],[Цена за кв.м. в сайт]])+$AZ$1 -> 443895.2 | BA390: =AZ390*PriceList[[#This Row],[Площадь, кв.м]] -> 12864083 | BB390: =BA390-PriceList[[#This Row],[Стоимость, руб для сбронированием]] -> 14490 | BD390: =MROUND(AZ390,100) -> 443900 | BE390: =BD390*PriceList[[#This Row],[Площадь, кв.м]] -> 12864222 | BG390: =BE390-$BG$1*PriceList[[#This Row],[Площадь, кв.м]] -> 12690342 | BH390: =BE390-BG390 -> 173880 | BI390: =BG390/PriceList[[#This Row],[Площадь, кв.м]] -> 437900 | BJ390: =BH390/BG390 -> 0.013701758 | BL390: =BI390-10%*BI390 -> 394110 | BM390: =BL390*G390 -> 11421308
A391: 481 | B391: С2-155 | C391: 155 | D391: С2 | E391: 5 | F391: 3 | G391: 28.52 | H391: Ст | I391: Ст | J391: 4.25 | K391: =ROUND(J391*0.3,2) -> 1.28 | L391: =G391-J391 -> 24.27 | M391: =L391+K391 -> 25.55 | N391: S | O391: Линейная | P391: Правильная | Q391: Зона 1 | R391: Озеро | S391: Озеро | T391: Стандарт | U391: 40 | V391: =IFERROR(VLOOKUP(H391,'Коэфф для прайса 1 оч'!$A$3:$C$6,3,0),"") -> 327000 | W391: =IFERROR(VLOOKUP(E391,'Коэфф для прайса 1 оч'!$A$10:$C$23,3,0),"") -> 0.005 | X391: =IFERROR(VLOOKUP(N391,'Коэфф для прайса 1 оч'!$E$25:$F$30,2,0),"") -> 0.04 | Y391: =IFERROR(VLOOKUP(O391,'Коэфф для прайса 1 оч'!$E$32:$F$34,2,0),"") -> 0 | Z391: =IFERROR(VLOOKUP(P391,'Коэфф для прайса 1 оч'!$E$36:$F$38,2,0),"") -> 0.03 | AA391: =IFERROR(VLOOKUP(Q391,'Коэфф для прайса 1 оч'!$E$40:$F$43,2,0),"") -> 0.005 | AB391: =IFERROR(VLOOKUP(R391,'Коэфф для прайса 1 оч'!$E$45:$F$59,2,0),"") -> 0.03 | AC391: =IFERROR(VLOOKUP(T391,'Коэфф для прайса 1 оч'!$E$61:$F$67,2,0),"") -> 0 | AD391: =IFERROR(VLOOKUP(U391,'Коэфф для прайса 1 оч'!$E$69:$F$82,2,0),"") -> -0.014 | AE391: =IFERROR(VLOOKUP(PriceList[[#This Row],[Корпус]],'Коэфф для прайса 1 оч'!$I$10:$J$15,2,0),"") -> 0.12 | AF391: =ROUND(V391+(V391*SUM(W391:AE391)),2) -> 397632 | AG391: =AF391*G391 -> 11340465 | AH391: 0 | AI391: =AF391+AF391*AH391 -> 397632 | AJ391: =AI391*G391 -> 11340465 | AK391: Резерв | AL391: 0.1 | AM391: =PriceList[[#This Row],[ИТОГ Цена за кв.м, руб]]*(1+PriceList[[#This Row],[Максимальная скидка]]) -> 437395.2 | AN391: =PriceList[[#This Row],[Цена за кв.м. в CRM]]*PriceList[[#This Row],[Площадь, кв.м]] -> 12474511 | AO391: 6000 | AP391: =PriceList[[#This Row],[Цена за кв.м. в CRM]]+PriceList[[#This Row],[Бронь]] -> 443395.2 | AQ391: =PriceList[[#This Row],[Цена за кв.м. в сайт]]*PriceList[[#This Row],[Площадь, кв.м]] -> 12645631 | AR391: =B391 -> С2-155 | AS391: =H391 -> Ст | AT391: =G391 -> 28.52 | AU391: =PriceList[[#This Row],[Цена за кв.м. в CRM]] -> 437395.2 | AV391: =AK391 -> Резерв | AZ391: =(PriceList[[#This Row],[Цена за кв.м. в сайт]])+$AZ$1 -> 443895.2 | BA391: =AZ391*PriceList[[#This Row],[Площадь, кв.м]] -> 12659891 | BB391: =BA391-PriceList[[#This Row],[Стоимость, руб для сбронированием]] -> 14260 | BD391: =MROUND(AZ391,100) -> 443900 | BE391: =BD391*PriceList[[#This Row],[Площадь, кв.м]] -> 12660028 | BG391: =BE391-$BG$1*PriceList[[#This Row],[Площадь, кв.м]] -> 12488908 | BH391: =BE391-BG391 -> 171120 | BI391: =BG391/PriceList[[#This Row],[Площадь, кв.м]] -> 437900 | BJ391: =BH391/BG391 -> 0.013701758 | BL391: =BI391-10%*BI391 -> 394110 | BM391: =BL391*G391 -> 11240017
A392: 482 | B392: С2-156 | C392: 156 | D392: С2 | E392: 5 | F392: 4 | G392: 32.45 | H392: Ст | I392: Ст | J392: 4.39 | K392: =ROUND(J392*0.3,2) -> 1.32 | L392: =G392-J392 -> 28.06 | M392: =L392+K392 -> 29.38 | N392: S | O392: Угловая | P392: Правильная | Q392: Зона 1 | R392: Озеро | S392: Озеро | T392: Стандарт | U392: 40 | V392: =IFERROR(VLOOKUP(H392,'Коэфф для прайса 1 оч'!$A$3:$C$6,3,0),"") -> 327000 | W392: =IFERROR(VLOOKUP(E392,'Коэфф для прайса 1 оч'!$A$10:$C$23,3,0),"") -> 0.005 | X392: =IFERROR(VLOOKUP(N392,'Коэфф для прайса 1 оч'!$E$25:$F$30,2,0),"") -> 0.04 | Y392: =IFERROR(VLOOKUP(O392,'Коэфф для прайса 1 оч'!$E$32:$F$34,2,0),"") -> 0.03 | Z392: =IFERROR(VLOOKUP(P392,'Коэфф для прайса 1 оч'!$E$36:$F$38,2,0),"") -> 0.03 | AA392: =IFERROR(VLOOKUP(Q392,'Коэфф для прайса 1 оч'!$E$40:$F$43,2,0),"") -> 0.005 | AB392: =IFERROR(VLOOKUP(R392,'Коэфф для прайса 1 оч'!$E$45:$F$59,2,0),"") -> 0.03 | AC392: =IFERROR(VLOOKUP(T392,'Коэфф для прайса 1 оч'!$E$61:$F$67,2,0),"") -> 0 | AD392: =IFERROR(VLOOKUP(U392,'Коэфф для прайса 1 оч'!$E$69:$F$82,2,0),"") -> -0.014 | AE392: =IFERROR(VLOOKUP(PriceList[[#This Row],[Корпус]],'Коэфф для прайса 1 оч'!$I$10:$J$15,2,0),"") -> 0.12 | AF392: =ROUND(V392+(V392*SUM(W392:AE392)),2) -> 407442 | AG392: =AF392*G392 -> 13221493 | AH392: 0 | AI392: =AF392+AF392*AH392 -> 407442 | AJ392: =AI392*G392 -> 13221493 | AK392: Резерв | AL392: 0.1 | AM392: =PriceList[[#This Row],[ИТОГ Цена за кв.м, руб]]*(1+PriceList[[#This Row],[Максимальная скидка]]) -> 448186.2 | AN392: =PriceList[[#This Row],[Цена за кв.м. в CRM]]*PriceList[[#This Row],[Площадь, кв.м]] -> 14543642 | AO392: 6000 | AP392: =PriceList[[#This Row],[Цена за кв.м. в CRM]]+PriceList[[#This Row],[Бронь]] -> 454186.2 | AQ392: =PriceList[[#This Row],[Цена за кв.м. в сайт]]*PriceList[[#This Row],[Площадь, кв.м]] -> 14738342 | AR392: =B392 -> С2-156 | AS392: =H392 -> Ст | AT392: =G392 -> 32.45 | AU392: =PriceList[[#This Row],[Цена за кв.м. в CRM]] -> 448186.2 | AV392: =AK392 -> Резерв | AZ392: =(PriceList[[#This Row],[Цена за кв.м. в сайт]])+$AZ$1 -> 454686.2 | BA392: =AZ392*PriceList[[#This Row],[Площадь, кв.м]] -> 14754567 | BB392: =BA392-PriceList[[#This Row],[Стоимость, руб для сбронированием]] -> 16225 | BD392: =MROUND(AZ392,100) -> 454700 | BE392: =BD392*PriceList[[#This Row],[Площадь, кв.м]] -> 14755015 | BG392: =BE392-$BG$1*PriceList[[#This Row],[Площадь, кв.м]] -> 14560315 | BH392: =BE392-BG392 -> 194700 | BI392: =BG392/PriceList[[#This Row],[Площадь, кв.м]] -> 448700 | BJ392: =BH392/BG392 -> 0.013371963 | BL392: =BI392-10%*BI392 -> 403830 | BM392: =BL392*G392 -> 13104284
A393: 483 | B393: С2-157 | C393: 157 | D393: С2 | E393: 5 | F393: 5 | G393: 32.43 | H393: Ст | I393: Ст | J393: 4.39 | K393: =ROUND(J393*0.3,2) -> 1.32 | L393: =G393-J393 -> 28.04 | M393: =L393+K393 -> 29.36 | N393: S | O393: Угловая | P393: Правильная | Q393: Зона 1 | R393: Двор юг | S393: Двор | T393: Стандарт | U393: 40 | V393: =IFERROR(VLOOKUP(H393,'Коэфф для прайса 1 оч'!$A$3:$C$6,3,0),"") -> 327000 | W393: =IFERROR(VLOOKUP(E393,'Коэфф для прайса 1 оч'!$A$10:$C$23,3,0),"") -> 0.005 | X393: =IFERROR(VLOOKUP(N393,'Коэфф для прайса 1 оч'!$E$25:$F$30,2,0),"") -> 0.04 | Y393: =IFERROR(VLOOKUP(O393,'Коэфф для прайса 1 оч'!$E$32:$F$34,2,0),"") -> 0.03 | Z393: =IFERROR(VLOOKUP(P393,'Коэфф для прайса 1 оч'!$E$36:$F$38,2,0),"") -> 0.03 | AA393: =IFERROR(VLOOKUP(Q393,'Коэфф для прайса 1 оч'!$E$40:$F$43,2,0),"") -> 0.005 | AB393: =IFERROR(VLOOKUP(R393,'Коэфф для прайса 1 оч'!$E$45:$F$59,2,0),"") -> 0 | AC393: =IFERROR(VLOOKUP(T393,'Коэфф для прайса 1 оч'!$E$61:$F$67,2,0),"") -> 0 | AD393: =IFERROR(VLOOKUP(U393,'Коэфф для прайса 1 оч'!$E$69:$F$82,2,0),"") -> -0.014 | AE393: =IFERROR(VLOOKUP(PriceList[[#This Row],[Корпус]],'Коэфф для прайса 1 оч'!$I$10:$J$15,2,0),"") -> 0.12 | AF393: =ROUND(V393+(V393*SUM(W393:AE393)),2) -> 397632 | AG393: =AF393*G393 -> 12895206 | AH393: 0 | AI393: =AF393+AF393*AH393 -> 397632 | AJ393: =AI393*G393 -> 12895206 | AK393: Резерв | AL393: 0.1 | AM393: =PriceList[[#This Row],[ИТОГ Цена за кв.м, руб]]*(1+PriceList[[#This Row],[Максимальная скидка]]) -> 437395.2 | AN393: =PriceList[[#This Row],[Цена за кв.м. в CRM]]*PriceList[[#This Row],[Площадь, кв.м]] -> 14184726 | AO393: 6000 | AP393: =PriceList[[#This Row],[Цена за кв.м. в CRM]]+PriceList[[#This Row],[Бронь]] -> 443395.2 | AQ393: =PriceList[[#This Row],[Цена за кв.м. в сайт]]*PriceList[[#This Row],[Площадь, кв.м]] -> 14379306 | AR393: =B393 -> С2-157 | AS393: =H393 -> Ст | AT393: =G393 -> 32.43 | AU393: =PriceList[[#This Row],[Цена за кв.м. в CRM]] -> 437395.2 | AV393: =AK393 -> Резерв | AZ393: =(PriceList[[#This Row],[Цена за кв.м. в сайт]])+$AZ$1 -> 443895.2 | BA393: =AZ393*PriceList[[#This Row],[Площадь, кв.м]] -> 14395521 | BB393: =BA393-PriceList[[#This Row],[Стоимость, руб для сбронированием]] -> 16215 | BD393: =MROUND(AZ393,100) -> 443900 | BE393: =BD393*PriceList[[#This Row],[Площадь, кв.м]] -> 14395677 | BG393: =BE393-$BG$1*PriceList[[#This Row],[Площадь, кв.м]] -> 14201097 | BH393: =BE393-BG393 -> 194580 | BI393: =BG393/PriceList[[#This Row],[Площадь, кв.м]] -> 437900 | BJ393: =BH393/BG393 -> 0.013701758 | BL393: =BI393-10%*BI393 -> 394110 | BM393: =BL393*G393 -> 12780987
A394: 484 | B394: С2-158 | C394: 158 | D394: С2 | E394: 5 | F394: 6 | G394: 28.52 | H394: Ст | I394: Ст | J394: 4.25 | K394: =ROUND(J394*0.3,2) -> 1.28 | L394: =G394-J394 -> 24.27 | M394: =L394+K394 -> 25.55 | N394: S | O394: Линейная | P394: Правильная | Q394: Зона 1 | R394: Двор юго-запад | S394: Двор | T394: Стандарт | U394: 40 | V394: =IFERROR(VLOOKUP(H394,'Коэфф для прайса 1 оч'!$A$3:$C$6,3,0),"") -> 327000 | W394: =IFERROR(VLOOKUP(E394,'Коэфф для прайса 1 оч'!$A$10:$C$23,3,0),"") -> 0.005 | X394: =IFERROR(VLOOKUP(N394,'Коэфф для прайса 1 оч'!$E$25:$F$30,2,0),"") -> 0.04 | Y394: =IFERROR(VLOOKUP(O394,'Коэфф для прайса 1 оч'!$E$32:$F$34,2,0),"") -> 0 | Z394: =IFERROR(VLOOKUP(P394,'Коэфф для прайса 1 оч'!$E$36:$F$38,2,0),"") -> 0.03 | AA394: =IFERROR(VLOOKUP(Q394,'Коэфф для прайса 1 оч'!$E$40:$F$43,2,0),"") -> 0.005 | AB394: =IFERROR(VLOOKUP(R394,'Коэфф для прайса 1 оч'!$E$45:$F$59,2,0),"") -> 0.02 | AC394: =IFERROR(VLOOKUP(T394,'Коэфф для прайса 1 оч'!$E$61:$F$67,2,0),"") -> 0 | AD394: =IFERROR(VLOOKUP(U394,'Коэфф для прайса 1 оч'!$E$69:$F$82,2,0),"") -> -0.014 | AE394: =IFERROR(VLOOKUP(PriceList[[#This Row],[Корпус]],'Коэфф для прайса 1 оч'!$I$10:$J$15,2,0),"") -> 0.12 | AF394: =ROUND(V394+(V394*SUM(W394:AE394)),2) -> 394362 | AG394: =AF394*G394 -> 11247204 | AH394: 0 | AI394: =AF394+AF394*AH394 -> 394362 | AJ394: =AI394*G394 -> 11247204 | AK394: Резерв | AL394: 0.1 | AM394: =PriceList[[#This Row],[ИТОГ Цена за кв.м, руб]]*(1+PriceList[[#This Row],[Максимальная скидка]]) -> 433798.2 | AN394: =PriceList[[#This Row],[Цена за кв.м. в CRM]]*PriceList[[#This Row],[Площадь, кв.м]] -> 12371925 | AO394: 6000 | AP394: =PriceList[[#This Row],[Цена за кв.м. в CRM]]+PriceList[[#This Row],[Бронь]] -> 439798.2 | AQ394: =PriceList[[#This Row],[Цена за кв.м. в сайт]]*PriceList[[#This Row],[Площадь, кв.м]] -> 12543045 | AR394: =B394 -> С2-158 | AS394: =H394 -> Ст | AT394: =G394 -> 28.52 | AU394: =PriceList[[#This Row],[Цена за кв.м. в CRM]] -> 433798.2 | AV394: =AK394 -> Резерв | AZ394: =(PriceList[[#This Row],[Цена за кв.м. в сайт]])+$AZ$1 -> 440298.2 | BA394: =AZ394*PriceList[[#This Row],[Площадь, кв.м]] -> 12557305 | BB394: =BA394-PriceList[[#This Row],[Стоимость, руб для сбронированием]] -> 14260 | BD394: =MROUND(AZ394,100) -> 440300 | BE394: =BD394*PriceList[[#This Row],[Площадь, кв.м]] -> 12557356 | BG394: =BE394-$BG$1*PriceList[[#This Row],[Площадь, кв.м]] -> 12386236 | BH394: =BE394-BG394 -> 171120 | BI394: =BG394/PriceList[[#This Row],[Площадь, кв.м]] -> 434300 | BJ394: =BH394/BG394 -> 0.013815335 | BL394: =BI394-10%*BI394 -> 390870 | BM394: =BL394*G394 -> 11147612
A395: 485 | B395: С2-159 | C395: 159 | D395: С2 | E395: 5 | F395: 7 | G395: 28.99 | H395: Ст | I395: Ст | J395: 4.25 | K395: =ROUND(J395*0.3,2) -> 1.28 | L395: =G395-J395 -> 24.74 | M395: =L395+K395 -> 26.02 | N395: S | O395: Линейная | P395: Правильная | Q395: Зона 1 | R395: Двор юго-запад | S395: Двор | T395: Стандарт | U395: 40 | V395: =IFERROR(VLOOKUP(H395,'Коэфф для прайса 1 оч'!$A$3:$C$6,3,0),"") -> 327000 | W395: =IFERROR(VLOOKUP(E395,'Коэфф для прайса 1 оч'!$A$10:$C$23,3,0),"") -> 0.005 | X395: =IFERROR(VLOOKUP(N395,'Коэфф для прайса 1 оч'!$E$25:$F$30,2,0),"") -> 0.04 | Y395: =IFERROR(VLOOKUP(O395,'Коэфф для прайса 1 оч'!$E$32:$F$34,2,0),"") -> 0 | Z395: =IFERROR(VLOOKUP(P395,'Коэфф для прайса 1 оч'!$E$36:$F$38,2,0),"") -> 0.03 | AA395: =IFERROR(VLOOKUP(Q395,'Коэфф для прайса 1 оч'!$E$40:$F$43,2,0),"") -> 0.005 | AB395: =IFERROR(VLOOKUP(R395,'Коэфф для прайса 1 оч'!$E$45:$F$59,2,0),"") -> 0.02 | AC395: =IFERROR(VLOOKUP(T395,'Коэфф для прайса 1 оч'!$E$61:$F$67,2,0),"") -> 0 | AD395: =IFERROR(VLOOKUP(U395,'Коэфф для прайса 1 оч'!$E$69:$F$82,2,0),"") -> -0.014 | AE395: =IFERROR(VLOOKUP(PriceList[[#This Row],[Корпус]],'Коэфф для прайса 1 оч'!$I$10:$J$15,2,0),"") -> 0.12 | AF395: =ROUND(V395+(V395*SUM(W395:AE395)),2) -> 394362 | AG395: =AF395*G395 -> 11432554 | AH395: 0 | AI395: =AF395+AF395*AH395 -> 394362 | AJ395: =AI395*G395 -> 11432554 | AK395: Резерв | AL395: 0.1 | AM395: =PriceList[[#This Row],[ИТОГ Цена за кв.м, руб]]*(1+PriceList[[#This Row],[Максимальная скидка]]) -> 433798.2 | AN395: =PriceList[[#This Row],[Цена за кв.м. в CRM]]*PriceList[[#This Row],[Площадь, кв.м]] -> 12575810 | AO395: 6000 | AP395: =PriceList[[#This Row],[Цена за кв.м. в CRM]]+PriceList[[#This Row],[Бронь]] -> 439798.2 | AQ395: =PriceList[[#This Row],[Цена за кв.м. в сайт]]*PriceList[[#This Row],[Площадь, кв.м]] -> 12749750 | AR395: =B395 -> С2-159 | AS395: =H395 -> Ст | AT395: =G395 -> 28.99 | AU395: =PriceList[[#This Row],[Цена за кв.м. в CRM]] -> 433798.2 | AV395: =AK395 -> Резерв | AZ395: =(PriceList[[#This Row],[Цена за кв.м. в сайт]])+$AZ$1 -> 440298.2 | BA395: =AZ395*PriceList[[#This Row],[Площадь, кв.м]] -> 12764245 | BB395: =BA395-PriceList[[#This Row],[Стоимость, руб для сбронированием]] -> 14495 | BD395: =MROUND(AZ395,100) -> 440300 | BE395: =BD395*PriceList[[#This Row],[Площадь, кв.м]] -> 12764297 | BG395: =BE395-$BG$1*PriceList[[#This Row],[Площадь, кв.м]] -> 12590357 | BH395: =BE395-BG395 -> 173940 | BI395: =BG395/PriceList[[#This Row],[Площадь, кв.м]] -> 434300 | BJ395: =BH395/BG395 -> 0.013815335 | BL395: =BI395-10%*BI395 -> 390870 | BM395: =BL395*G395 -> 11331321
A396: 342 | B396: С2-16 | C396: 16 | D396: С2 | E396: 1 | F396: 16 | G396: 32.6 | H396: Ст | I396: Ст | J396: 7.62 | K396: =ROUND(J396*0.3,2) -> 2.29 | L396: =G396-J396 -> 24.98 | M396: =L396+K396 -> 27.27 | N396: S | O396: Линейная | P396: Правильная | Q396: Зона 1 | R396: Двор юг | S396: Двор | T396: У входа в лифтовый холл | U396: 34 | V396: =IFERROR(VLOOKUP(H396,'Коэфф для прайса 1 оч'!$A$3:$C$6,3,0),"") -> 327000 | W396: =IFERROR(VLOOKUP(E396,'Коэфф для прайса 1 оч'!$A$10:$C$23,3,0),"") -> -0.045 | X396: =IFERROR(VLOOKUP(N396,'Коэфф для прайса 1 оч'!$E$25:$F$30,2,0),"") -> 0.04 | Y396: =IFERROR(VLOOKUP(O396,'Коэфф для прайса 1 оч'!$E$32:$F$34,2,0),"") -> 0 | Z396: =IFERROR(VLOOKUP(P396,'Коэфф для прайса 1 оч'!$E$36:$F$38,2,0),"") -> 0.03 | AA396: =IFERROR(VLOOKUP(Q396,'Коэфф для прайса 1 оч'!$E$40:$F$43,2,0),"") -> 0.005 | AB396: =IFERROR(VLOOKUP(R396,'Коэфф для прайса 1 оч'!$E$45:$F$59,2,0),"") -> 0 | AC396: =IFERROR(VLOOKUP(T396,'Коэфф для прайса 1 оч'!$E$61:$F$67,2,0),"") -> -0.01 | AD396: =IFERROR(VLOOKUP(U396,'Коэфф для прайса 1 оч'!$E$69:$F$82,2,0),"") -> -0.008 | AE396: =IFERROR(VLOOKUP(PriceList[[#This Row],[Корпус]],'Коэфф для прайса 1 оч'!$I$10:$J$15,2,0),"") -> 0.12 | AF396: =ROUND(V396+(V396*SUM(W396:AE396)),2) -> 370164 | AG396: =AF396*G396 -> 12067346 | AH396: 0 | AI396: =AF396+AF396*AH396 -> 370164 | AJ396: =AI396*G396 -> 12067346 | AK396: Резерв | AL396: 0.1 | AM396: =PriceList[[#This Row],[ИТОГ Цена за кв.м, руб]]*(1+PriceList[[#This Row],[Максимальная скидка]]) -> 407180.4 | AN396: =PriceList[[#This Row],[Цена за кв.м. в CRM]]*PriceList[[#This Row],[Площадь, кв.м]] -> 13274081 | AO396: 6000 | AP396: =PriceList[[#This Row],[Цена за кв.м. в CRM]]+PriceList[[#This Row],[Бронь]] -> 413180.4 | AQ396: =PriceList[[#This Row],[Цена за кв.м. в сайт]]*PriceList[[#This Row],[Площадь, кв.м]] -> 13469681 | AR396: =B396 -> С2-16 | AS396: =H396 -> Ст | AT396: =G396 -> 32.6 | AU396: =PriceList[[#This Row],[Цена за кв.м. в CRM]] -> 407180.4 | AV396: =AK396 -> Резерв | AZ396: =(PriceList[[#This Row],[Цена за кв.м. в сайт]])+$AZ$1 -> 413680.4 | BA396: =AZ396*PriceList[[#This Row],[Площадь, кв.м]] -> 13485981 | BB396: =BA396-PriceList[[#This Row],[Стоимость, руб для сбронированием]] -> 16300 | BD396: =MROUND(AZ396,100) -> 413700 | BE396: =BD396*PriceList[[#This Row],[Площадь, кв.м]] -> 13486620 | BG396: =BE396-$BG$1*PriceList[[#This Row],[Площадь, кв.м]] -> 13291020 | BH396: =BE396-BG396 -> 195600 | BI396: =BG396/PriceList[[#This Row],[Площадь, кв.м]] -> 407700 | BJ396: =BH396/BG396 -> 0.014716703 | BL396: =BI396-10%*BI396 -> 366930 | BM396: =BL396*G396 -> 11961918
A397: 486 | B397: С2-160 | C397: 160 | D397: С2 | E397: 5 | F397: 8 | G397: 28.53 | H397: Ст | I397: Ст | J397: 3.79 | K397: =ROUND(J397*0.3,2) -> 1.14 | L397: =G397-J397 -> 24.74 | M397: =L397+K397 -> 25.88 | N397: S | O397: Линейная | P397: Правильная | Q397: Зона 1 | R397: Двор юго-запад | S397: Двор | T397: Стандарт | U397: 40 | V397: =IFERROR(VLOOKUP(H397,'Коэфф для прайса 1 оч'!$A$3:$C$6,3,0),"") -> 327000 | W397: =IFERROR(VLOOKUP(E397,'Коэфф для прайса 1 оч'!$A$10:$C$23,3,0),"") -> 0.005 | X397: =IFERROR(VLOOKUP(N397,'Коэфф для прайса 1 оч'!$E$25:$F$30,2,0),"") -> 0.04 | Y397: =IFERROR(VLOOKUP(O397,'Коэфф для прайса 1 оч'!$E$32:$F$34,2,0),"") -> 0 | Z397: =IFERROR(VLOOKUP(P397,'Коэфф для прайса 1 оч'!$E$36:$F$38,2,0),"") -> 0.03 | AA397: =IFERROR(VLOOKUP(Q397,'Коэфф для прайса 1 оч'!$E$40:$F$43,2,0),"") -> 0.005 | AB397: =IFERROR(VLOOKUP(R397,'Коэфф для прайса 1 оч'!$E$45:$F$59,2,0),"") -> 0.02 | AC397: =IFERROR(VLOOKUP(T397,'Коэфф для прайса 1 оч'!$E$61:$F$67,2,0),"") -> 0 | AD397: =IFERROR(VLOOKUP(U397,'Коэфф для прайса 1 оч'!$E$69:$F$82,2,0),"") -> -0.014 | AE397: =IFERROR(VLOOKUP(PriceList[[#This Row],[Корпус]],'Коэфф для прайса 1 оч'!$I$10:$J$15,2,0),"") -> 0.12 | AF397: =ROUND(V397+(V397*SUM(W397:AE397)),2) -> 394362 | AG397: =AF397*G397 -> 11251148 | AH397: 0 | AI397: =AF397+AF397*AH397 -> 394362 | AJ397: =AI397*G397 -> 11251148 | AK397: Резерв | AL397: 0.1 | AM397: =PriceList[[#This Row],[ИТОГ Цена за кв.м, руб]]*(1+PriceList[[#This Row],[Максимальная скидка]]) -> 433798.2 | AN397: =PriceList[[#This Row],[Цена за кв.м. в CRM]]*PriceList[[#This Row],[Площадь, кв.м]] -> 12376263 | AO397: 6000 | AP397: =PriceList[[#This Row],[Цена за кв.м. в CRM]]+PriceList[[#This Row],[Бронь]] -> 439798.2 | AQ397: =PriceList[[#This Row],[Цена за кв.м. в сайт]]*PriceList[[#This Row],[Площадь, кв.м]] -> 12547443 | AR397: =B397 -> С2-160 | AS397: =H397 -> Ст | AT397: =G397 -> 28.53 | AU397: =PriceList[[#This Row],[Цена за кв.м. в CRM]] -> 433798.2 | AV397: =AK397 -> Резерв | AZ397: =(PriceList[[#This Row],[Цена за кв.м. в сайт]])+$AZ$1 -> 440298.2 | BA397: =AZ397*PriceList[[#This Row],[Площадь, кв.м]] -> 12561708 | BB397: =BA397-PriceList[[#This Row],[Стоимость, руб для сбронированием]] -> 14265 | BD397: =MROUND(AZ397,100) -> 440300 | BE397: =BD397*PriceList[[#This Row],[Площадь, кв.м]] -> 12561759 | BG397: =BE397-$BG$1*PriceList[[#This Row],[Площадь, кв.м]] -> 12390579 | BH397: =BE397-BG397 -> 171180 | BI397: =BG397/PriceList[[#This Row],[Площадь, кв.м]] -> 434300 | BJ397: =BH397/BG397 -> 0.013815335 | BL397: =BI397-10%*BI397 -> 390870 | BM397: =BL397*G397 -> 11151521
A398: 487 | B398: С2-161 | C398: 161 | D398: С2 | E398: 5 | F398: 9 | G398: 28.99 | H398: Ст | I398: Ст | J398: 4.25 | K398: =ROUND(J398*0.3,2) -> 1.28 | L398: =G398-J398 -> 24.74 | M398: =L398+K398 -> 26.02 | N398: S | O398: Линейная | P398: Правильная | Q398: Зона 1 | R398: Двор юго-запад | S398: Двор | T398: У входа в лифтовый холл | U398: 40 | V398: =IFERROR(VLOOKUP(H398,'Коэфф для прайса 1 оч'!$A$3:$C$6,3,0),"") -> 327000 | W398: =IFERROR(VLOOKUP(E398,'Коэфф для прайса 1 оч'!$A$10:$C$23,3,0),"") -> 0.005 | X398: =IFERROR(VLOOKUP(N398,'Коэфф для прайса 1 оч'!$E$25:$F$30,2,0),"") -> 0.04 | Y398: =IFERROR(VLOOKUP(O398,'Коэфф для прайса 1 оч'!$E$32:$F$34,2,0),"") -> 0 | Z398: =IFERROR(VLOOKUP(P398,'Коэфф для прайса 1 оч'!$E$36:$F$38,2,0),"") -> 0.03 | AA398: =IFERROR(VLOOKUP(Q398,'Коэфф для прайса 1 оч'!$E$40:$F$43,2,0),"") -> 0.005 | AB398: =IFERROR(VLOOKUP(R398,'Коэфф для прайса 1 оч'!$E$45:$F$59,2,0),"") -> 0.02 | AC398: =IFERROR(VLOOKUP(T398,'Коэфф для прайса 1 оч'!$E$61:$F$67,2,0),"") -> -0.01 | AD398: =IFERROR(VLOOKUP(U398,'Коэфф для прайса 1 оч'!$E$69:$F$82,2,0),"") -> -0.014 | AE398: =IFERROR(VLOOKUP(PriceList[[#This Row],[Корпус]],'Коэфф для прайса 1 оч'!$I$10:$J$15,2,0),"") -> 0.12 | AF398: =ROUND(V398+(V398*SUM(W398:AE398)),2) -> 391092 | AG398: =AF398*G398 -> 11337757 | AH398: 0 | AI398: =AF398+AF398*AH398 -> 391092 | AJ398: =AI398*G398 -> 11337757 | AK398: Свободно | AL398: 0.1 | AM398: =PriceList[[#This Row],[ИТОГ Цена за кв.м, руб]]*(1+PriceList[[#This Row],[Максимальная скидка]]) -> 430201.2 | AN398: =PriceList[[#This Row],[Цена за кв.м. в CRM]]*PriceList[[#This Row],[Площадь, кв.м]] -> 12471533 | AO398: 6000 | AP398: =PriceList[[#This Row],[Цена за кв.м. в CRM]]+PriceList[[#This Row],[Бронь]] -> 436201.2 | AQ398: =PriceList[[#This Row],[Цена за кв.м. в сайт]]*PriceList[[#This Row],[Площадь, кв.м]] -> 12645473 | AR398: =B398 -> С2-161 | AS398: =H398 -> Ст | AT398: =G398 -> 28.99 | AU398: =PriceList[[#This Row],[Цена за кв.м. в CRM]] -> 430201.2 | AV398: =AK398 -> Свободно | AZ398: =(PriceList[[#This Row],[Цена за кв.м. в сайт]])+$AZ$1 -> 436701.2 | BA398: =AZ398*PriceList[[#This Row],[Площадь, кв.м]] -> 12659968 | BB398: =BA398-PriceList[[#This Row],[Стоимость, руб для сбронированием]] -> 14495 | BD398: =MROUND(AZ398,100) -> 436700 | BE398: =BD398*PriceList[[#This Row],[Площадь, кв.м]] -> 12659933 | BG398: =BE398-$BG$1*PriceList[[#This Row],[Площадь, кв.м]] -> 12485993 | BH398: =BE398-BG398 -> 173940 | BI398: =BG398/PriceList[[#This Row],[Площадь, кв.м]] -> 430700 | BJ398: =BH398/BG398 -> 0.01393081 | BL398: =BI398-10%*BI398 -> 387630 | BM398: =BL398*G398 -> 11237394
A399: 488 | B399: С2-162 | C399: 162 | D399: С2 | E399: 5 | F399: 10 | G399: 28.99 | H399: Ст | I399: Ст | J399: 4.25 | K399: =ROUND(J399*0.3,2) -> 1.28 | L399: =G399-J399 -> 24.74 | M399: =L399+K399 -> 26.02 | N399: S | O399: Линейная | P399: Правильная | Q399: Зона 1 | R399: Двор юго-запад | S399: Двор | T399: У входа в лифтовый холл | U399: 40 | V399: =IFERROR(VLOOKUP(H399,'Коэфф для прайса 1 оч'!$A$3:$C$6,3,0),"") -> 327000 | W399: =IFERROR(VLOOKUP(E399,'Коэфф для прайса 1 оч'!$A$10:$C$23,3,0),"") -> 0.005 | X399: =IFERROR(VLOOKUP(N399,'Коэфф для прайса 1 оч'!$E$25:$F$30,2,0),"") -> 0.04 | Y399: =IFERROR(VLOOKUP(O399,'Коэфф для прайса 1 оч'!$E$32:$F$34,2,0),"") -> 0 | Z399: =IFERROR(VLOOKUP(P399,'Коэфф для прайса 1 оч'!$E$36:$F$38,2,0),"") -> 0.03 | AA399: =IFERROR(VLOOKUP(Q399,'Коэфф для прайса 1 оч'!$E$40:$F$43,2,0),"") -> 0.005 | AB399: =IFERROR(VLOOKUP(R399,'Коэфф для прайса 1 оч'!$E$45:$F$59,2,0),"") -> 0.02 | AC399: =IFERROR(VLOOKUP(T399,'Коэфф для прайса 1 оч'!$E$61:$F$67,2,0),"") -> -0.01 | AD399: =IFERROR(VLOOKUP(U399,'Коэфф для прайса 1 оч'!$E$69:$F$82,2,0),"") -> -0.014 | AE399: =IFERROR(VLOOKUP(PriceList[[#This Row],[Корпус]],'Коэфф для прайса 1 оч'!$I$10:$J$15,2,0),"") -> 0.12 | AF399: =ROUND(V399+(V399*SUM(W399:AE399)),2) -> 391092 | AG399: =AF399*G399 -> 11337757 | AH399: 0 | AI399: =AF399+AF399*AH399 -> 391092 | AJ399: =AI399*G399 -> 11337757 | AK399: Резерв | AL399: 0.1 | AM399: =PriceList[[#This Row],[ИТОГ Цена за кв.м, руб]]*(1+PriceList[[#This Row],[Максимальная скидка]]) -> 430201.2 | AN399: =PriceList[[#This Row],[Цена за кв.м. в CRM]]*PriceList[[#This Row],[Площадь, кв.м]] -> 12471533 | AO399: 6000 | AP399: =PriceList[[#This Row],[Цена за кв.м. в CRM]]+PriceList[[#This Row],[Бронь]] -> 436201.2 | AQ399: =PriceList[[#This Row],[Цена за кв.м. в сайт]]*PriceList[[#This Row],[Площадь, кв.м]] -> 12645473 | AR399: =B399 -> С2-162 | AS399: =H399 -> Ст | AT399: =G399 -> 28.99 | AU399: =PriceList[[#This Row],[Цена за кв.м. в CRM]] -> 430201.2 | AV399: =AK399 -> Резерв | AZ399: =(PriceList[[#This Row],[Цена за кв.м. в сайт]])+$AZ$1 -> 436701.2 | BA399: =AZ399*PriceList[[#This Row],[Площадь, кв.м]] -> 12659968 | BB399: =BA399-PriceList[[#This Row],[Стоимость, руб для сбронированием]] -> 14495 | BD399: =MROUND(AZ399,100) -> 436700 | BE399: =BD399*PriceList[[#This Row],[Площадь, кв.м]] -> 12659933 | BG399: =BE399-$BG$1*PriceList[[#This Row],[Площадь, кв.м]] -> 12485993 | BH399: =BE399-BG399 -> 173940 | BI399: =BG399/PriceList[[#This Row],[Площадь, кв.м]] -> 430700 | BJ399: =BH399/BG399 -> 0.01393081 | BL399: =BI399-10%*BI399 -> 387630 | BM399: =BL399*G399 -> 11237394
A400: 489 | B400: С2-163 | C400: 163 | D400: С2 | E400: 5 | F400: 11 | G400: 28.99 | H400: Ст | I400: Ст | J400: 4.25 | K400: =ROUND(J400*0.3,2) -> 1.28 | L400: =G400-J400 -> 24.74 | M400: =L400+K400 -> 26.02 | N400: S | O400: Линейная | P400: Правильная | Q400: Зона 1 | R400: Двор юго-запад | S400: Двор | T400: Стандарт | U400: 40 | V400: =IFERROR(VLOOKUP(H400,'Коэфф для прайса 1 оч'!$A$3:$C$6,3,0),"") -> 327000 | W400: =IFERROR(VLOOKUP(E400,'Коэфф для прайса 1 оч'!$A$10:$C$23,3,0),"") -> 0.005 | X400: =IFERROR(VLOOKUP(N400,'Коэфф для прайса 1 оч'!$E$25:$F$30,2,0),"") -> 0.04 | Y400: =IFERROR(VLOOKUP(O400,'Коэфф для прайса 1 оч'!$E$32:$F$34,2,0),"") -> 0 | Z400: =IFERROR(VLOOKUP(P400,'Коэфф для прайса 1 оч'!$E$36:$F$38,2,0),"") -> 0.03 | AA400: =IFERROR(VLOOKUP(Q400,'Коэфф для прайса 1 оч'!$E$40:$F$43,2,0),"") -> 0.005 | AB400: =IFERROR(VLOOKUP(R400,'Коэфф для прайса 1 оч'!$E$45:$F$59,2,0),"") -> 0.02 | AC400: =IFERROR(VLOOKUP(T400,'Коэфф для прайса 1 оч'!$E$61:$F$67,2,0),"") -> 0 | AD400: =IFERROR(VLOOKUP(U400,'Коэфф для прайса 1 оч'!$E$69:$F$82,2,0),"") -> -0.014 | AE400: =IFERROR(VLOOKUP(PriceList[[#This Row],[Корпус]],'Коэфф для прайса 1 оч'!$I$10:$J$15,2,0),"") -> 0.12 | AF400: =ROUND(V400+(V400*SUM(W400:AE400)),2) -> 394362 | AG400: =AF400*G400 -> 11432554 | AH400: 0 | AI400: =AF400+AF400*AH400 -> 394362 | AJ400: =AI400*G400 -> 11432554 | AK400: Резерв | AL400: 0.1 | AM400: =PriceList[[#This Row],[ИТОГ Цена за кв.м, руб]]*(1+PriceList[[#This Row],[Максимальная скидка]]) -> 433798.2 | AN400: =PriceList[[#This Row],[Цена за кв.м. в CRM]]*PriceList[[#This Row],[Площадь, кв.м]] -> 12575810 | AO400: 6000 | AP400: =PriceList[[#This Row],[Цена за кв.м. в CRM]]+PriceList[[#This Row],[Бронь]] -> 439798.2 | AQ400: =PriceList[[#This Row],[Цена за кв.м. в сайт]]*PriceList[[#This Row],[Площадь, кв.м]] -> 12749750 | AR400: =B400 -> С2-163 | AS400: =H400 -> Ст | AT400: =G400 -> 28.99 | AU400: =PriceList[[#This Row],[Цена за кв.м. в CRM]] -> 433798.2 | AV400: =AK400 -> Резерв | AZ400: =(PriceList[[#This Row],[Цена за кв.м. в сайт]])+$AZ$1 -> 440298.2 | BA400: =AZ400*PriceList[[#This Row],[Площадь, кв.м]] -> 12764245 | BB400: =BA400-PriceList[[#This Row],[Стоимость, руб для сбронированием]] -> 14495 | BD400: =MROUND(AZ400,100) -> 440300 | BE400: =BD400*PriceList[[#This Row],[Площадь, кв.м]] -> 12764297 | BG400: =BE400-$BG$1*PriceList[[#This Row],[Площадь, кв.м]] -> 12590357 | BH400: =BE400-BG400 -> 173940 | BI400: =BG400/PriceList[[#This Row],[Площадь, кв.м]] -> 434300 | BJ400: =BH400/BG400 -> 0.013815335 | BL400: =BI400-10%*BI400 -> 390870 | BM400: =BL400*G400 -> 11331321
... A431: 517 | B431: С2-191 | C431: 191 | D431: С2 | E431: 5 | F431: 39 | G431: 28.41 | H431: Ст | I431: Ст | J431: 3.68 | K431: =ROUND(J431*0.3,2) -> 1.1 | L431: =G431-J431 -> 24.73 | M431: =L431+K431 -> 25.83 | N431: S | O431: Линейная | P431: Правильная | Q431: Зона 1 | R431: Озеро | S431: Озеро | T431: Стандарт | U431: 40 | V431: =IFERROR(VLOOKUP(H431,'Коэфф для прайса 1 оч'!$A$3:$C$6,3,0),"") -> 327000 | W431: =IFERROR(VLOOKUP(E431,'Коэфф для прайса 1 оч'!$A$10:$C$23,3,0),"") -> 0.005 | X431: =IFERROR(VLOOKUP(N431,'Коэфф для прайса 1 оч'!$E$25:$F$30,2,0),"") -> 0.04 | Y431: =IFERROR(VLOOKUP(O431,'Коэфф для прайса 1 оч'!$E$32:$F$34,2,0),"") -> 0 | Z431: =IFERROR(VLOOKUP(P431,'Коэфф для прайса 1 оч'!$E$36:$F$38,2,0),"") -> 0.03 | AA431: =IFERROR(VLOOKUP(Q431,'Коэфф для прайса 1 оч'!$E$40:$F$43,2,0),"") -> 0.005 | AB431: =IFERROR(VLOOKUP(R431,'Коэфф для прайса 1 оч'!$E$45:$F$59,2,0),"") -> 0.03 | AC431: =IFERROR(VLOOKUP(T431,'Коэфф для прайса 1 оч'!$E$61:$F$67,2,0),"") -> 0 | AD431: =IFERROR(VLOOKUP(U431,'Коэфф для прайса 1 оч'!$E$69:$F$82,2,0),"") -> -0.014 | AE431: =IFERROR(VLOOKUP(PriceList[[#This Row],[Корпус]],'Коэфф для прайса 1 оч'!$I$10:$J$15,2,0),"") -> 0.12 | AF431: =ROUND(V431+(V431*SUM(W431:AE431)),2) -> 397632 | AG431: =AF431*G431 -> 11296725 | AH431: 0 | AI431: =AF431+AF431*AH431 -> 397632 | AJ431: =AI431*G431 -> 11296725 | AK431: Резерв | AL431: 0.1 | AM431: =PriceList[[#This Row],[ИТОГ Цена за кв.м, руб]]*(1+PriceList[[#This Row],[Максимальная скидка]]) -> 437395.2 | AN431: =PriceList[[#This Row],[Цена за кв.м. в CRM]]*PriceList[[#This Row],[Площадь, кв.м]] -> 12426398 | AO431: 6000 | AP431: =PriceList[[#This Row],[Цена за кв.м. в CRM]]+PriceList[[#This Row],[Бронь]] -> 443395.2 | AQ431: =PriceList[[#This Row],[Цена за кв.м. в сайт]]*PriceList[[#This Row],[Площадь, кв.м]] -> 12596858 | AR431: =B431 -> С2-191 | AS431: =H431 -> Ст | AT431: =G431 -> 28.41 | AU431: =PriceList[[#This Row],[Цена за кв.м. в CRM]] -> 437395.2 | AV431: =AK431 -> Резерв | AZ431: =(PriceList[[#This Row],[Цена за кв.м. в сайт]])+$AZ$1 -> 443895.2 | BA431: =AZ431*PriceList[[#This Row],[Площадь, кв.м]] -> 12611063 | BB431: =BA431-PriceList[[#This Row],[Стоимость, руб для сбронированием]] -> 14205 | BD431: =MROUND(AZ431,100) -> 443900 | BE431: =BD431*PriceList[[#This Row],[Площадь, кв.м]] -> 12611199 | BG431: =BE431-$BG$1*PriceList[[#This Row],[Площадь, кв.м]] -> 12440739 | BH431: =BE431-BG431 -> 170460 | BI431: =BG431/PriceList[[#This Row],[Площадь, кв.м]] -> 437900 | BJ431: =BH431/BG431 -> 0.013701758 | BL431: =BI431-10%*BI431 -> 394110 | BM431: =BL431*G431 -> 11196665
A432: 518 | B432: С2-192 | C432: 192 | D432: С2 | E432: 5 | F432: 40 | G432: 28.7 | H432: Ст | I432: Ст | J432: 4.11 | K432: =ROUND(J432*0.3,2) -> 1.23 | L432: =G432-J432 -> 24.59 | M432: =L432+K432 -> 25.82 | N432: S | O432: Линейная | P432: Правильная | Q432: Зона 1 | R432: Озеро | S432: Озеро | T432: Стандарт | U432: 40 | V432: =IFERROR(VLOOKUP(H432,'Коэфф для прайса 1 оч'!$A$3:$C$6,3,0),"") -> 327000 | W432: =IFERROR(VLOOKUP(E432,'Коэфф для прайса 1 оч'!$A$10:$C$23,3,0),"") -> 0.005 | X432: =IFERROR(VLOOKUP(N432,'Коэфф для прайса 1 оч'!$E$25:$F$30,2,0),"") -> 0.04 | Y432: =IFERROR(VLOOKUP(O432,'Коэфф для прайса 1 оч'!$E$32:$F$34,2,0),"") -> 0 | Z432: =IFERROR(VLOOKUP(P432,'Коэфф для прайса 1 оч'!$E$36:$F$38,2,0),"") -> 0.03 | AA432: =IFERROR(VLOOKUP(Q432,'Коэфф для прайса 1 оч'!$E$40:$F$43,2,0),"") -> 0.005 | AB432: =IFERROR(VLOOKUP(R432,'Коэфф для прайса 1 оч'!$E$45:$F$59,2,0),"") -> 0.03 | AC432: =IFERROR(VLOOKUP(T432,'Коэфф для прайса 1 оч'!$E$61:$F$67,2,0),"") -> 0 | AD432: =IFERROR(VLOOKUP(U432,'Коэфф для прайса 1 оч'!$E$69:$F$82,2,0),"") -> -0.014 | AE432: =IFERROR(VLOOKUP(PriceList[[#This Row],[Корпус]],'Коэфф для прайса 1 оч'!$I$10:$J$15,2,0),"") -> 0.12 | AF432: =ROUND(V432+(V432*SUM(W432:AE432)),2) -> 397632 | AG432: =AF432*G432 -> 11412038 | AH432: 0 | AK432: Не для продажи | AL432: 0.1 | AM432: =PriceList[[#This Row],[ИТОГ Цена за кв.м, руб]]*(1+PriceList[[#This Row],[Максимальная скидка]]) -> 0 | AN432: =PriceList[[#This Row],[Цена за кв.м. в CRM]]*PriceList[[#This Row],[Площадь, кв.м]] -> 0 | AO432: 6000 | AP432: =PriceList[[#This Row],[Цена за кв.м. в CRM]]+PriceList[[#This Row],[Бронь]] -> 6000 | AQ432: =PriceList[[#This Row],[Цена за кв.м. в сайт]]*PriceList[[#This Row],[Площадь, кв.м]] -> 172200 | AR432: =B432 -> С2-192 | AS432: =H432 -> Ст | AT432: =G432 -> 28.7 | AU432: =PriceList[[#This Row],[Цена за кв.м. в CRM]] -> 0 | AV432: =AK432 -> Не для продажи | BD432: =MROUND(AZ432,100) -> 0 | BE432: =BD432*PriceList[[#This Row],[Площадь, кв.м]] -> 0 | BH432: =BE432-BG432 -> 0 | BI432: =BG432/PriceList[[#This Row],[Площадь, кв.м]] -> 0 | BJ432: =BH432/BG432 -> #DIV/0! | BL432: =BI432-10%*BI432 -> 0 | BM432: =BL432*G432 -> 0
A433: 519 | B433: С2-193 | C433: 193 | D433: С2 | E433: 6 | F433: 1 | G433: 37.48 | H433: Ст | I433: Ст | J433: 7.26 | K433: =ROUND(J433*0.3,2) -> 2.18 | L433: =G433-J433 -> 30.22 | M433: =L433+K433 -> 32.4 | N433: M | O433: Линейная | P433: Правильная | Q433: Зона 1 | R433: Озеро | S433: Озеро | T433: Стандарт | U433: 40 | V433: =IFERROR(VLOOKUP(H433,'Коэфф для прайса 1 оч'!$A$3:$C$6,3,0),"") -> 327000 | W433: =IFERROR(VLOOKUP(E433,'Коэфф для прайса 1 оч'!$A$10:$C$23,3,0),"") -> 0.015 | X433: =IFERROR(VLOOKUP(N433,'Коэфф для прайса 1 оч'!$E$25:$F$30,2,0),"") -> 0 | Y433: =IFERROR(VLOOKUP(O433,'Коэфф для прайса 1 оч'!$E$32:$F$34,2,0),"") -> 0 | Z433: =IFERROR(VLOOKUP(P433,'Коэфф для прайса 1 оч'!$E$36:$F$38,2,0),"") -> 0.03 | AA433: =IFERROR(VLOOKUP(Q433,'Коэфф для прайса 1 оч'!$E$40:$F$43,2,0),"") -> 0.005 | AB433: =IFERROR(VLOOKUP(R433,'Коэфф для прайса 1 оч'!$E$45:$F$59,2,0),"") -> 0.03 | AC433: =IFERROR(VLOOKUP(T433,'Коэфф для прайса 1 оч'!$E$61:$F$67,2,0),"") -> 0 | AD433: =IFERROR(VLOOKUP(U433,'Коэфф для прайса 1 оч'!$E$69:$F$82,2,0),"") -> -0.014 | AE433: =IFERROR(VLOOKUP(PriceList[[#This Row],[Корпус]],'Коэфф для прайса 1 оч'!$I$10:$J$15,2,0),"") -> 0.12 | AF433: =ROUND(V433+(V433*SUM(W433:AE433)),2) -> 387822 | AG433: =AF433*G433 -> 14535569 | AH433: 0 | AI433: =AF433+AF433*AH433 -> 387822 | AJ433: =AI433*G433 -> 14535569 | AK433: Резерв | AL433: 0.1 | AM433: =PriceList[[#This Row],[ИТОГ Цена за кв.м, руб]]*(1+PriceList[[#This Row],[Максимальная скидка]]) -> 426604.2 | AN433: =PriceList[[#This Row],[Цена за кв.м. в CRM]]*PriceList[[#This Row],[Площадь, кв.м]] -> 15989125 | AO433: 6000 | AP433: =PriceList[[#This Row],[Цена за кв.м. в CRM]]+PriceList[[#This Row],[Бронь]] -> 432604.2 | AQ433: =PriceList[[#This Row],[Цена за кв.м. в сайт]]*PriceList[[#This Row],[Площадь, кв.м]] -> 16214005 | AR433: =B433 -> С2-193 | AS433: =H433 -> Ст | AT433: =G433 -> 37.48 | AU433: =PriceList[[#This Row],[Цена за кв.м. в CRM]] -> 426604.2 | AV433: =AK433 -> Резерв | AZ433: =(PriceList[[#This Row],[Цена за кв.м. в сайт]])+$AZ$1 -> 433104.2 | BA433: =AZ433*PriceList[[#This Row],[Площадь, кв.м]] -> 16232745 | BB433: =BA433-PriceList[[#This Row],[Стоимость, руб для сбронированием]] -> 18740 | BD433: =MROUND(AZ433,100) -> 433100 | BE433: =BD433*PriceList[[#This Row],[Площадь, кв.м]] -> 16232588 | BG433: =BE433-$BG$1*PriceList[[#This Row],[Площадь, кв.м]] -> 16007708 | BH433: =BE433-BG433 -> 224880 | BI433: =BG433/PriceList[[#This Row],[Площадь, кв.м]] -> 427100 | BJ433: =BH433/BG433 -> 0.014048232 | BL433: =BI433-10%*BI433 -> 384390 | BM433: =BL433*G433 -> 14406937
A434: 520 | B434: С2-194 | C434: 194 | D434: С2 | E434: 6 | F434: 2 | G434: 29.02 | H434: Ст | I434: Ст | J434: 4.29 | K434: =ROUND(J434*0.3,2) -> 1.29 | L434: =G434-J434 -> 24.73 | M434: =L434+K434 -> 26.02 | N434: S | O434: Линейная | P434: Правильная | Q434: Зона 1 | R434: Озеро | S434: Озеро | T434: Стандарт | U434: 40 | V434: =IFERROR(VLOOKUP(H434,'Коэфф для прайса 1 оч'!$A$3:$C$6,3,0),"") -> 327000 | W434: =IFERROR(VLOOKUP(E434,'Коэфф для прайса 1 оч'!$A$10:$C$23,3,0),"") -> 0.015 | X434: =IFERROR(VLOOKUP(N434,'Коэфф для прайса 1 оч'!$E$25:$F$30,2,0),"") -> 0.04 | Y434: =IFERROR(VLOOKUP(O434,'Коэфф для прайса 1 оч'!$E$32:$F$34,2,0),"") -> 0 | Z434: =IFERROR(VLOOKUP(P434,'Коэфф для прайса 1 оч'!$E$36:$F$38,2,0),"") -> 0.03 | AA434: =IFERROR(VLOOKUP(Q434,'Коэфф для прайса 1 оч'!$E$40:$F$43,2,0),"") -> 0.005 | AB434: =IFERROR(VLOOKUP(R434,'Коэфф для прайса 1 оч'!$E$45:$F$59,2,0),"") -> 0.03 | AC434: =IFERROR(VLOOKUP(T434,'Коэфф для прайса 1 оч'!$E$61:$F$67,2,0),"") -> 0 | AD434: =IFERROR(VLOOKUP(U434,'Коэфф для прайса 1 оч'!$E$69:$F$82,2,0),"") -> -0.014 | AE434: =IFERROR(VLOOKUP(PriceList[[#This Row],[Корпус]],'Коэфф для прайса 1 оч'!$I$10:$J$15,2,0),"") -> 0.12 | AF434: =ROUND(V434+(V434*SUM(W434:AE434)),2) -> 400902 | AG434: =AF434*G434 -> 11634176 | AH434: 0 | AI434: =AF434+AF434*AH434 -> 400902 | AJ434: =AI434*G434 -> 11634176 | AK434: Резерв | AL434: 0.1 | AM434: =PriceList[[#This Row],[ИТОГ Цена за кв.м, руб]]*(1+PriceList[[#This Row],[Максимальная скидка]]) -> 440992.2 | AN434: =PriceList[[#This Row],[Цена за кв.м. в CRM]]*PriceList[[#This Row],[Площадь, кв.м]] -> 12797594 | AO434: 6000 | AP434: =PriceList[[#This Row],[Цена за кв.м. в CRM]]+PriceList[[#This Row],[Бронь]] -> 446992.2 | AQ434: =PriceList[[#This Row],[Цена за кв.м. в сайт]]*PriceList[[#This Row],[Площадь, кв.м]] -> 12971714 | AR434: =B434 -> С2-194 | AS434: =H434 -> Ст | AT434: =G434 -> 29.02 | AU434: =PriceList[[#This Row],[Цена за кв.м. в CRM]] -> 440992.2 | AV434: =AK434 -> Резерв | AZ434: =(PriceList[[#This Row],[Цена за кв.м. в сайт]])+$AZ$1 -> 447492.2 | BA434: =AZ434*PriceList[[#This Row],[Площадь, кв.м]] -> 12986224 | BB434: =BA434-PriceList[[#This Row],[Стоимость, руб для сбронированием]] -> 14510 | BD434: =MROUND(AZ434,100) -> 447500 | BE434: =BD434*PriceList[[#This Row],[Площадь, кв.м]] -> 12986450 | BG434: =BE434-$BG$1*PriceList[[#This Row],[Площадь, кв.м]] -> 12812330 | BH434: =BE434-BG434 -> 174120 | BI434: =BG434/PriceList[[#This Row],[Площадь, кв.м]] -> 441500 | BJ434: =BH434/BG434 -> 0.013590034 | BL434: =BI434-10%*BI434 -> 397350 | BM434: =BL434*G434 -> 11531097
A435: 521 | B435: С2-195 | C435: 195 | D435: С2 | E435: 6 | F435: 3 | G435: 28.56 | H435: Ст | I435: Ст | J435: 4.29 | K435: =ROUND(J435*0.3,2) -> 1.29 | L435: =G435-J435 -> 24.27 | M435: =L435+K435 -> 25.56 | N435: S | O435: Линейная | P435: Правильная | Q435: Зона 1 | R435: Озеро | S435: Озеро | T435: Стандарт | U435: 40 | V435: =IFERROR(VLOOKUP(H435,'Коэфф для прайса 1 оч'!$A$3:$C$6,3,0),"") -> 327000 | W435: =IFERROR(VLOOKUP(E435,'Коэфф для прайса 1 оч'!$A$10:$C$23,3,0),"") -> 0.015 | X435: =IFERROR(VLOOKUP(N435,'Коэфф для прайса 1 оч'!$E$25:$F$30,2,0),"") -> 0.04 | Y435: =IFERROR(VLOOKUP(O435,'Коэфф для прайса 1 оч'!$E$32:$F$34,2,0),"") -> 0 | Z435: =IFERROR(VLOOKUP(P435,'Коэфф для прайса 1 оч'!$E$36:$F$38,2,0),"") -> 0.03 | AA435: =IFERROR(VLOOKUP(Q435,'Коэфф для прайса 1 оч'!$E$40:$F$43,2,0),"") -> 0.005 | AB435: =IFERROR(VLOOKUP(R435,'Коэфф для прайса 1 оч'!$E$45:$F$59,2,0),"") -> 0.03 | AC435: =IFERROR(VLOOKUP(T435,'Коэфф для прайса 1 оч'!$E$61:$F$67,2,0),"") -> 0 | AD435: =IFERROR(VLOOKUP(U435,'Коэфф для прайса 1 оч'!$E$69:$F$82,2,0),"") -> -0.014 | AE435: =IFERROR(VLOOKUP(PriceList[[#This Row],[Корпус]],'Коэфф для прайса 1 оч'!$I$10:$J$15,2,0),"") -> 0.12 | AF435: =ROUND(V435+(V435*SUM(W435:AE435)),2) -> 400902 | AG435: =AF435*G435 -> 11449761 | AH435: 0 | AI435: =AF435+AF435*AH435 -> 400902 | AJ435: =AI435*G435 -> 11449761 | AK435: Резерв | AL435: 0.1 | AM435: =PriceList[[#This Row],[ИТОГ Цена за кв.м, руб]]*(1+PriceList[[#This Row],[Максимальная скидка]]) -> 440992.2 | AN435: =PriceList[[#This Row],[Цена за кв.м. в CRM]]*PriceList[[#This Row],[Площадь, кв.м]] -> 12594737 | AO435: 6000 | AP435: =PriceList[[#This Row],[Цена за кв.м. в CRM]]+PriceList[[#This Row],[Бронь]] -> 446992.2 | AQ435: =PriceList[[#This Row],[Цена за кв.м. в сайт]]*PriceList[[#This Row],[Площадь, кв.м]] -> 12766097 | AR435: =B435 -> С2-195 | AS435: =H435 -> Ст | AT435: =G435 -> 28.56 | AU435: =PriceList[[#This Row],[Цена за кв.м. в CRM]] -> 440992.2 | AV435: =AK435 -> Резерв | AZ435: =(PriceList[[#This Row],[Цена за кв.м. в сайт]])+$AZ$1 -> 447492.2 | BA435: =AZ435*PriceList[[#This Row],[Площадь, кв.м]] -> 12780377 | BB435: =BA435-PriceList[[#This Row],[Стоимость, руб для сбронированием]] -> 14280 | BD435: =MROUND(AZ435,100) -> 447500 | BE435: =BD435*PriceList[[#This Row],[Площадь, кв.м]] -> 12780600 | BG435: =BE435-$BG$1*PriceList[[#This Row],[Площадь, кв.м]] -> 12609240 | BH435: =BE435-BG435 -> 171360 | BI435: =BG435/PriceList[[#This Row],[Площадь, кв.м]] -> 441500 | BJ435: =BH435/BG435 -> 0.013590034 | BL435: =BI435-10%*BI435 -> 397350 | BM435: =BL435*G435 -> 11348316
A436: 522 | B436: С2-196 | C436: 196 | D436: С2 | E436: 6 | F436: 4 | G436: 32.46 | H436: Ст | I436: Ст | J436: 4.4 | K436: =ROUND(J436*0.3,2) -> 1.32 | L436: =G436-J436 -> 28.06 | M436: =L436+K436 -> 29.38 | N436: S | O436: Угловая | P436: Правильная | Q436: Зона 1 | R436: Озеро | S436: Озеро | T436: Стандарт | U436: 40 | V436: =IFERROR(VLOOKUP(H436,'Коэфф для прайса 1 оч'!$A$3:$C$6,3,0),"") -> 327000 | W436: =IFERROR(VLOOKUP(E436,'Коэфф для прайса 1 оч'!$A$10:$C$23,3,0),"") -> 0.015 | X436: =IFERROR(VLOOKUP(N436,'Коэфф для прайса 1 оч'!$E$25:$F$30,2,0),"") -> 0.04 | Y436: =IFERROR(VLOOKUP(O436,'Коэфф для прайса 1 оч'!$E$32:$F$34,2,0),"") -> 0.03 | Z436: =IFERROR(VLOOKUP(P436,'Коэфф для прайса 1 оч'!$E$36:$F$38,2,0),"") -> 0.03 | AA436: =IFERROR(VLOOKUP(Q436,'Коэфф для прайса 1 оч'!$E$40:$F$43,2,0),"") -> 0.005 | AB436: =IFERROR(VLOOKUP(R436,'Коэфф для прайса 1 оч'!$E$45:$F$59,2,0),"") -> 0.03 | AC436: =IFERROR(VLOOKUP(T436,'Коэфф для прайса 1 оч'!$E$61:$F$67,2,0),"") -> 0 | AD436: =IFERROR(VLOOKUP(U436,'Коэфф для прайса 1 оч'!$E$69:$F$82,2,0),"") -> -0.014 | AE436: =IFERROR(VLOOKUP(PriceList[[#This Row],[Корпус]],'Коэфф для прайса 1 оч'!$I$10:$J$15,2,0),"") -> 0.12 | AF436: =ROUND(V436+(V436*SUM(W436:AE436)),2) -> 410712 | AG436: =AF436*G436 -> 13331712 | AH436: 0 | AI436: =AF436+AF436*AH436 -> 410712 | AJ436: =AI436*G436 -> 13331712 | AK436: Резерв | AL436: 0.1 | AM436: =PriceList[[#This Row],[ИТОГ Цена за кв.м, руб]]*(1+PriceList[[#This Row],[Максимальная скидка]]) -> 451783.2 | AN436: =PriceList[[#This Row],[Цена за кв.м. в CRM]]*PriceList[[#This Row],[Площадь, кв.м]] -> 14664883 | AO436: 6000 | AP436: =PriceList[[#This Row],[Цена за кв.м. в CRM]]+PriceList[[#This Row],[Бронь]] -> 457783.2 | AQ436: =PriceList[[#This Row],[Цена за кв.м. в сайт]]*PriceList[[#This Row],[Площадь, кв.м]] -> 14859643 | AR436: =B436 -> С2-196 | AS436: =H436 -> Ст | AT436: =G436 -> 32.46 | AU436: =PriceList[[#This Row],[Цена за кв.м. в CRM]] -> 451783.2 | AV436: =AK436 -> Резерв | AZ436: =(PriceList[[#This Row],[Цена за кв.м. в сайт]])+$AZ$1 -> 458283.2 | BA436: =AZ436*PriceList[[#This Row],[Площадь, кв.м]] -> 14875873 | BB436: =BA436-PriceList[[#This Row],[Стоимость, руб для сбронированием]] -> 16230 | BD436: =MROUND(AZ436,100) -> 458300 | BE436: =BD436*PriceList[[#This Row],[Площадь, кв.м]] -> 14876418 | BG436: =BE436-$BG$1*PriceList[[#This Row],[Площадь, кв.м]] -> 14681658 | BH436: =BE436-BG436 -> 194760 | BI436: =BG436/PriceList[[#This Row],[Площадь, кв.м]] -> 452300 | BJ436: =BH436/BG436 -> 0.013265532 | BL436: =BI436-10%*BI436 -> 407070 | BM436: =BL436*G436 -> 13213492
A437: 523 | B437: С2-197 | C437: 197 | D437: С2 | E437: 6 | F437: 5 | G437: 32.44 | H437: Ст | I437: Ст | J437: 4.4 | K437: =ROUND(J437*0.3,2) -> 1.32 | L437: =G437-J437 -> 28.04 | M437: =L437+K437 -> 29.36 | N437: S | O437: Угловая | P437: Правильная | Q437: Зона 1 | R437: Двор юг | S437: Двор | T437: Стандарт | U437: 40 | V437: =IFERROR(VLOOKUP(H437,'Коэфф для прайса 1 оч'!$A$3:$C$6,3,0),"") -> 327000 | W437: =IFERROR(VLOOKUP(E437,'Коэфф для прайса 1 оч'!$A$10:$C$23,3,0),"") -> 0.015 | X437: =IFERROR(VLOOKUP(N437,'Коэфф для прайса 1 оч'!$E$25:$F$30,2,0),"") -> 0.04 | Y437: =IFERROR(VLOOKUP(O437,'Коэфф для прайса 1 оч'!$E$32:$F$34,2,0),"") -> 0.03 | Z437: =IFERROR(VLOOKUP(P437,'Коэфф для прайса 1 оч'!$E$36:$F$38,2,0),"") -> 0.03 | AA437: =IFERROR(VLOOKUP(Q437,'Коэфф для прайса 1 оч'!$E$40:$F$43,2,0),"") -> 0.005 | AB437: =IFERROR(VLOOKUP(R437,'Коэфф для прайса 1 оч'!$E$45:$F$59,2,0),"") -> 0 | AC437: =IFERROR(VLOOKUP(T437,'Коэфф для прайса 1 оч'!$E$61:$F$67,2,0),"") -> 0 | AD437: =IFERROR(VLOOKUP(U437,'Коэфф для прайса 1 оч'!$E$69:$F$82,2,0),"") -> -0.014 | AE437: =IFERROR(VLOOKUP(PriceList[[#This Row],[Корпус]],'Коэфф для прайса 1 оч'!$I$10:$J$15,2,0),"") -> 0.12 | AF437: =ROUND(V437+(V437*SUM(W437:AE437)),2) -> 400902 | AG437: =AF437*G437 -> 13005261 | AH437: 0 | AI437: =AF437+AF437*AH437 -> 400902 | AJ437: =AI437*G437 -> 13005261 | AK437: Резерв | AL437: 0.1 | AM437: =PriceList[[#This Row],[ИТОГ Цена за кв.м, руб]]*(1+PriceList[[#This Row],[Максимальная скидка]]) -> 440992.2 | AN437: =PriceList[[#This Row],[Цена за кв.м. в CRM]]*PriceList[[#This Row],[Площадь, кв.м]] -> 14305787 | AO437: 6000 | AP437: =PriceList[[#This Row],[Цена за кв.м. в CRM]]+PriceList[[#This Row],[Бронь]] -> 446992.2 | AQ437: =PriceList[[#This Row],[Цена за кв.м. в сайт]]*PriceList[[#This Row],[Площадь, кв.м]] -> 14500427 | AR437: =B437 -> С2-197 | AS437: =H437 -> Ст | AT437: =G437 -> 32.44 | AU437: =PriceList[[#This Row],[Цена за кв.м. в CRM]] -> 440992.2 | AV437: =AK437 -> Резерв | AZ437: =(PriceList[[#This Row],[Цена за кв.м. в сайт]])+$AZ$1 -> 447492.2 | BA437: =AZ437*PriceList[[#This Row],[Площадь, кв.м]] -> 14516647 | BB437: =BA437-PriceList[[#This Row],[Стоимость, руб для сбронированием]] -> 16220 | BD437: =MROUND(AZ437,100) -> 447500 | BE437: =BD437*PriceList[[#This Row],[Площадь, кв.м]] -> 14516900 | BG437: =BE437-$BG$1*PriceList[[#This Row],[Площадь, кв.м]] -> 14322260 | BH437: =BE437-BG437 -> 194640 | BI437: =BG437/PriceList[[#This Row],[Площадь, кв.м]] -> 441500 | BJ437: =BH437/BG437 -> 0.013590034 | BL437: =BI437-10%*BI437 -> 397350 | BM437: =BL437*G437 -> 12890034
A438: 524 | B438: С2-198 | C438: 198 | D438: С2 | E438: 6 | F438: 6 | G438: 28.56 | H438: Ст | I438: Ст | J438: 4.29 | K438: =ROUND(J438*0.3,2) -> 1.29 | L438: =G438-J438 -> 24.27 | M438: =L438+K438 -> 25.56 | N438: S | O438: Линейная | P438: Правильная | Q438: Зона 1 | R438: Двор юго-запад | S438: Двор | T438: Стандарт | U438: 40 | V438: =IFERROR(VLOOKUP(H438,'Коэфф для прайса 1 оч'!$A$3:$C$6,3,0),"") -> 327000 | W438: =IFERROR(VLOOKUP(E438,'Коэфф для прайса 1 оч'!$A$10:$C$23,3,0),"") -> 0.015 | X438: =IFERROR(VLOOKUP(N438,'Коэфф для прайса 1 оч'!$E$25:$F$30,2,0),"") -> 0.04 | Y438: =IFERROR(VLOOKUP(O438,'Коэфф для прайса 1 оч'!$E$32:$F$34,2,0),"") -> 0 | Z438: =IFERROR(VLOOKUP(P438,'Коэфф для прайса 1 оч'!$E$36:$F$38,2,0),"") -> 0.03 | AA438: =IFERROR(VLOOKUP(Q438,'Коэфф для прайса 1 оч'!$E$40:$F$43,2,0),"") -> 0.005 | AB438: =IFERROR(VLOOKUP(R438,'Коэфф для прайса 1 оч'!$E$45:$F$59,2,0),"") -> 0.02 | AC438: =IFERROR(VLOOKUP(T438,'Коэфф для прайса 1 оч'!$E$61:$F$67,2,0),"") -> 0 | AD438: =IFERROR(VLOOKUP(U438,'Коэфф для прайса 1 оч'!$E$69:$F$82,2,0),"") -> -0.014 | AE438: =IFERROR(VLOOKUP(PriceList[[#This Row],[Корпус]],'Коэфф для прайса 1 оч'!$I$10:$J$15,2,0),"") -> 0.12 | AF438: =ROUND(V438+(V438*SUM(W438:AE438)),2) -> 397632 | AG438: =AF438*G438 -> 11356370 | AH438: 0 | AI438: =AF438+AF438*AH438 -> 397632 | AJ438: =AI438*G438 -> 11356370 | AK438: Резерв | AL438: 0.1 | AM438: =PriceList[[#This Row],[ИТОГ Цена за кв.м, руб]]*(1+PriceList[[#This Row],[Максимальная скидка]]) -> 437395.2 | AN438: =PriceList[[#This Row],[Цена за кв.м. в CRM]]*PriceList[[#This Row],[Площадь, кв.м]] -> 12492007 | AO438: 6000 | AP438: =PriceList[[#This Row],[Цена за кв.м. в CRM]]+PriceList[[#This Row],[Бронь]] -> 443395.2 | AQ438: =PriceList[[#This Row],[Цена за кв.м. в сайт]]*PriceList[[#This Row],[Площадь, кв.м]] -> 12663367 | AR438: =B438 -> С2-198 | AS438: =H438 -> Ст | AT438: =G438 -> 28.56 | AU438: =PriceList[[#This Row],[Цена за кв.м. в CRM]] -> 437395.2 | AV438: =AK438 -> Резерв | AZ438: =(PriceList[[#This Row],[Цена за кв.м. в сайт]])+$AZ$1 -> 443895.2 | BA438: =AZ438*PriceList[[#This Row],[Площадь, кв.м]] -> 12677647 | BB438: =BA438-PriceList[[#This Row],[Стоимость, руб для сбронированием]] -> 14280 | BD438: =MROUND(AZ438,100) -> 443900 | BE438: =BD438*PriceList[[#This Row],[Площадь, кв.м]] -> 12677784 | BG438: =BE438-$BG$1*PriceList[[#This Row],[Площадь, кв.м]] -> 12506424 | BH438: =BE438-BG438 -> 171360 | BI438: =BG438/PriceList[[#This Row],[Площадь, кв.м]] -> 437900 | BJ438: =BH438/BG438 -> 0.013701758 | BL438: =BI438-10%*BI438 -> 394110 | BM438: =BL438*G438 -> 11255782
A439: 525 | B439: С2-199 | C439: 199 | D439: С2 | E439: 6 | F439: 7 | G439: 29.03 | H439: Ст | I439: Ст | J439: 4.29 | K439: =ROUND(J439*0.3,2) -> 1.29 | L439: =G439-J439 -> 24.74 | M439: =L439+K439 -> 26.03 | N439: S | O439: Линейная | P439: Правильная | Q439: Зона 1 | R439: Двор юго-запад | S439: Двор | T439: Стандарт | U439: 40 | V439: =IFERROR(VLOOKUP(H439,'Коэфф для прайса 1 оч'!$A$3:$C$6,3,0),"") -> 327000 | W439: =IFERROR(VLOOKUP(E439,'Коэфф для прайса 1 оч'!$A$10:$C$23,3,0),"") -> 0.015 | X439: =IFERROR(VLOOKUP(N439,'Коэфф для прайса 1 оч'!$E$25:$F$30,2,0),"") -> 0.04 | Y439: =IFERROR(VLOOKUP(O439,'Коэфф для прайса 1 оч'!$E$32:$F$34,2,0),"") -> 0 | Z439: =IFERROR(VLOOKUP(P439,'Коэфф для прайса 1 оч'!$E$36:$F$38,2,0),"") -> 0.03 | AA439: =IFERROR(VLOOKUP(Q439,'Коэфф для прайса 1 оч'!$E$40:$F$43,2,0),"") -> 0.005 | AB439: =IFERROR(VLOOKUP(R439,'Коэфф для прайса 1 оч'!$E$45:$F$59,2,0),"") -> 0.02 | AC439: =IFERROR(VLOOKUP(T439,'Коэфф для прайса 1 оч'!$E$61:$F$67,2,0),"") -> 0 | AD439: =IFERROR(VLOOKUP(U439,'Коэфф для прайса 1 оч'!$E$69:$F$82,2,0),"") -> -0.014 | AE439: =IFERROR(VLOOKUP(PriceList[[#This Row],[Корпус]],'Коэфф для прайса 1 оч'!$I$10:$J$15,2,0),"") -> 0.12 | AF439: =ROUND(V439+(V439*SUM(W439:AE439)),2) -> 397632 | AG439: =AF439*G439 -> 11543257 | AH439: 0 | AI439: =AF439+AF439*AH439 -> 397632 | AJ439: =AI439*G439 -> 11543257 | AK439: Свободно | AL439: 0.1 | AM439: =PriceList[[#This Row],[ИТОГ Цена за кв.м, руб]]*(1+PriceList[[#This Row],[Максимальная скидка]]) -> 437395.2 | AN439: =PriceList[[#This Row],[Цена за кв.м. в CRM]]*PriceList[[#This Row],[Площадь, кв.м]] -> 12697583 | AO439: 6000 | AP439: =PriceList[[#This Row],[Цена за кв.м. в CRM]]+PriceList[[#This Row],[Бронь]] -> 443395.2 | AQ439: =PriceList[[#This Row],[Цена за кв.м. в сайт]]*PriceList[[#This Row],[Площадь, кв.м]] -> 12871763 | AR439: =B439 -> С2-199 | AS439: =H439 -> Ст | AT439: =G439 -> 29.03 | AU439: =PriceList[[#This Row],[Цена за кв.м. в CRM]] -> 437395.2 | AV439: =AK439 -> Свободно | AZ439: =(PriceList[[#This Row],[Цена за кв.м. в сайт]])+$AZ$1 -> 443895.2 | BA439: =AZ439*PriceList[[#This Row],[Площадь, кв.м]] -> 12886278 | BB439: =BA439-PriceList[[#This Row],[Стоимость, руб для сбронированием]] -> 14515 | BD439: =MROUND(AZ439,100) -> 443900 | BE439: =BD439*PriceList[[#This Row],[Площадь, кв.м]] -> 12886417 | BG439: =BE439-$BG$1*PriceList[[#This Row],[Площадь, кв.м]] -> 12712237 | BH439: =BE439-BG439 -> 174180 | BI439: =BG439/PriceList[[#This Row],[Площадь, кв.м]] -> 437900 | BJ439: =BH439/BG439 -> 0.013701758 | BL439: =BI439-10%*BI439 -> 394110 | BM439: =BL439*G439 -> 11441013
A440: 328 | B440: С2-2 | C440: 2 | D440: С2 | E440: 1 | F440: 2 | G440: 28.99 | H440: Ст | I440: Ст | J440: 4.25 | K440: =ROUND(J440*0.3,2) -> 1.28 | L440: =G440-J440 -> 24.74 | M440: =L440+K440 -> 26.02 | N440: S | O440: Линейная | P440: Правильная | Q440: Зона 1 | R440: Улица северо-восток | S440: ул.Морская | T440: Стандарт | U440: 34 | V440: =IFERROR(VLOOKUP(H440,'Коэфф для прайса 1 оч'!$A$3:$C$6,3,0),"") -> 327000 | W440: =IFERROR(VLOOKUP(E440,'Коэфф для прайса 1 оч'!$A$10:$C$23,3,0),"") -> -0.045 | X440: =IFERROR(VLOOKUP(N440,'Коэфф для прайса 1 оч'!$E$25:$F$30,2,0),"") -> 0.04 | Y440: =IFERROR(VLOOKUP(O440,'Коэфф для прайса 1 оч'!$E$32:$F$34,2,0),"") -> 0 | Z440: =IFERROR(VLOOKUP(P440,'Коэфф для прайса 1 оч'!$E$36:$F$38,2,0),"") -> 0.03 | AA440: =IFERROR(VLOOKUP(Q440,'Коэфф для прайса 1 оч'!$E$40:$F$43,2,0),"") -> 0.005 | AB440: =IFERROR(VLOOKUP(R440,'Коэфф для прайса 1 оч'!$E$45:$F$59,2,0),"") -> -0.02 | AC440: =IFERROR(VLOOKUP(T440,'Коэфф для прайса 1 оч'!$E$61:$F$67,2,0),"") -> 0 | AD440: =IFERROR(VLOOKUP(U440,'Коэфф для прайса 1 оч'!$E$69:$F$82,2,0),"") -> -0.008 | AE440: =IFERROR(VLOOKUP(PriceList[[#This Row],[Корпус]],'Коэфф для прайса 1 оч'!$I$10:$J$15,2,0),"") -> 0.12 | AF440: =ROUND(V440+(V440*SUM(W440:AE440)),2) -> 366894 | AG440: =AF440*G440 -> 10636257 | AH440: 0 | AI440: =AF440+AF440*AH440 -> 366894 | AJ440: =AI440*G440 -> 10636257 | AK440: Свободно | AL440: 0.1 | AM440: =PriceList[[#This Row],[ИТОГ Цена за кв.м, руб]]*(1+PriceList[[#This Row],[Максимальная скидка]]) -> 403583.4 | AN440: =PriceList[[#This Row],[Цена за кв.м. в CRM]]*PriceList[[#This Row],[Площадь, кв.м]] -> 11699883 | AO440: 6000 | AP440: =PriceList[[#This Row],[Цена за кв.м. в CRM]]+PriceList[[#This Row],[Бронь]] -> 409583.4 | AQ440: =PriceList[[#This Row],[Цена за кв.м. в сайт]]*PriceList[[#This Row],[Площадь, кв.м]] -> 11873823 | AR440: =B440 -> С2-2 | AS440: =H440 -> Ст | AT440: =G440 -> 28.99 | AU440: =PriceList[[#This Row],[Цена за кв.м. в CRM]] -> 403583.4 | AV440: =AK440 -> Свободно | AZ440: =(PriceList[[#This Row],[Цена за кв.м. в сайт]])+$AZ$1 -> 410083.4 | BA440: =AZ440*PriceList[[#This Row],[Площадь, кв.м]] -> 11888318 | BB440: =BA440-PriceList[[#This Row],[Стоимость, руб для сбронированием]] -> 14495 | BD440: =MROUND(AZ440,100) -> 410100 | BE440: =BD440*PriceList[[#This Row],[Площадь, кв.м]] -> 11888799 | BG440: =BE440-$BG$1*PriceList[[#This Row],[Площадь, кв.м]] -> 11714859 | BH440: =BE440-BG440 -> 173940 | BI440: =BG440/PriceList[[#This Row],[Площадь, кв.м]] -> 404100 | BJ440: =BH440/BG440 -> 0.01484781 | BL440: =BI440-10%*BI440 -> 363690 | BM440: =BL440*G440 -> 10543373
